{"text": "שלום לך ארצי שלי\nהיפהפיה והנשכחת\nאבי שלי אותך חלם\nבלהט הקדחת.\n\nאבי היה אידיאליסט\nאמר צריך לחיות ביחד\nאבי לימד אותי לתת\nאני למדתי לקחת\nאבי הלך בכפר לחיות\nחלוץ היה מגיל צעיר\nנשם מיזוג של גלויות\nאני נושם מיזוג אוויר\nאבי ראה בכל - שליחות\nברפת, בשדה, בלול\nאני יודע ששליחות\nהיא כששולחים אותך לחו\"ל\nהוא חי על פיתה וזיתים\nרעב לא פעם בלילות\nאני עוד לא רעבתי יום\nבזכות פנקס הקבלות.\n\nשלום לך ארצי שלי\nשלום לך ירושלים\nאבי שלי לחש את שמך\nעם רטט בשפתיים.\n\n\"חזרנו אל בורות המים\"\nגם אם המחיר היה יקר\nהיום עירי ירושלים\nמוכרים אותך לכל ספסר\nוכל קבלן אותך אוהב\nבונה אותך ירושלים\nוהמחיר שהוא נוקב\nאינו צורב לו בשפתיים.\n\n\"מעל פסגת הר הצופים\"\nשנית נבנית פה עיר של מעלה\nבונים אותך לתלפיות\nהפועלים שברמאללה\nירושלים הבנויה\nהעיר אשר ישבה בדד\nעל חורבנך בכו דורות\nעל בניינך יבכו לעד.\n\nשלום לך ארצי שלי\n\"ארץ חמדת אבות\"\nאבי הקריב למענך\nהרבה שנים טובות\n\nוכך חומסים הם את ארצי\nומוצצים את כל דמיה\nאוכלים אותה ועוד אומרים\nשהיא אוכלת את יושביה\nמתי, מתי כל זה קרה?\nאיך לפתע השתנינו?\nאבי חלם חלום יפה -\nתראו מה התגשם ממנו.\n\nשלום לך ארצי שלי\n\"עוד לא אבדה תקוותנו\"\nגברת כבר על אוייבים רבים,\nוודאי תתגברי גם עלינו.", "tokens": [{"token": "שלום", "offsets": {"start": 0, "end": 4}, "syntax": {"word": "שלום", "dep_head_idx": 54, "dep_func": "discourse", "dep_head": "יודע"}, "seg": ["שלום"], "lex": "שלום", "morph": {"token": "שלום", "pos": "INTJ", "feats": {"Gender": "Masc", "Number": "Sing"}, "prefixes": [], "suffix": false}}, {"token": "לך", "offsets": {"start": 5, "end": 7}, "syntax": {"word": "לך", "dep_head_idx": 0, "dep_func": "obl", "dep_head": "שלום"}, "seg": ["לך"], "lex": "לי", "morph": {"token": "לך", "pos": "PRON", "feats": {"Gender": "Masc", "Number": "Sing", "Person": "2"}, "prefixes": [], "suffix": "PRON", "suffix_feats": {"Number": "Sing"}}}, {"token": "ארצי", "offsets": {"start": 8, "end": 12}, "syntax": {"word": "ארצי", "dep_head_idx": 0, "dep_func": "vocative", "dep_head": "שלום"}, "seg": ["ארצי"], "lex": "ארצי", "morph": {"token": "ארצי", "pos": "NOUN", "feats": {"Number": "Sing"}, "prefixes": [], "suffix": "PRON", "suffix_feats": {"Gender": "Masc", "Number": "Sing", "Person": "1"}}}, {"token": "שלי", "offsets": {"start": 13, "end": 16}, "syntax": {"word": "שלי", "dep_head_idx": 0, "dep_func": "nmod:poss", "dep_head": "שלום"}, "seg": ["שלי"], "lex": "של", "morph": {"token": "שלי", "pos": "ADP", "feats": {}, "prefixes": [], "suffix": "PRON", "suffix_feats": {"Gender": "Masc", "Number": "Sing", "Person": "1"}}}, {"token": "היפהפיה", "offsets": {"start": 17, "end": 24}, "syntax": {"word": "היפהפיה", "dep_head_idx": 2, "dep_func": "amod", "dep_head": "ארצי"}, "seg": ["ה", "יפהפיה"], "lex": "יפהפה", "morph": {"token": "היפהפיה", "pos": "ADJ", "feats": {"Gender": "Fem", "Number": "Sing"}, "prefixes": ["DET"], "suffix": false}}, {"token": "והנשכחת", "offsets": {"start": 25, "end": 32}, "syntax": {"word": "והנשכחת", "dep_head_idx": 4, "dep_func": "conj", "dep_head": "היפהפיה"}, "seg": ["וה", "נשכחת"], "lex": "נואש", "morph": {"token": "והנשכחת", "pos": "VERB", "feats": {"Gender": "Fem", "Number": "Sing", "Person": "3", "Tense": "Pres"}, "prefixes": ["CCONJ"], "suffix": false}}, {"token": "אבי", "offsets": {"start": 33, "end": 36}, "syntax": {"word": "אבי", "dep_head_idx": 169, "dep_func": "nsubj", "dep_head": "הקריב"}, "seg": ["אבי"], "lex": "אבי", "morph": {"token": "אבי", "pos": "NOUN", "feats": {"Gender": "Masc", "Number": "Sing"}, "prefixes": [], "suffix": "PRON", "suffix_feats": {"Gender": "Masc", "Number": "Sing", "Person": "1"}}}, {"token": "שלי", "offsets": {"start": 37, "end": 40}, "syntax": {"word": "שלי", "dep_head_idx": 75, "dep_func": "nmod:poss", "dep_head": "פנקס"}, "seg": ["שלי"], "lex": "של", "morph": {"token": "שלי", "pos": "ADP", "feats": {}, "prefixes": [], "suffix": "PRON", "suffix_feats": {"Gender": "Masc", "Number": "Sing", "Person": "1"}}}, {"token": "אותך", "offsets": {"start": 41, "end": 45}, "syntax": {"word": "אותך", "dep_head_idx": 175, "dep_func": "obj", "dep_head": "חומסים"}, "seg": ["אותך"], "lex": "את", "morph": {"token": "אותך", "pos": "ADP", "feats": {}, "prefixes": [], "suffix": "PRON", "suffix_feats": {"Gender": "Masc", "Number": "Sing", "Person": "2"}}}, {"token": "חלם", "offsets": {"start": 46, "end": 49}, "syntax": {"word": "חלם", "dep_head_idx": 153, "dep_func": "appos", "dep_head": "דורות"}, "seg": ["חלם"], "lex": "חלם", "morph": {"token": "חלם", "pos": "VERB", "feats": {"Gender": "Masc", "Number": "Sing", "Person": "3", "Tense": "Past"}, "prefixes": [], "suffix": false}}, {"token": "בלהט", "offsets": {"start": 50, "end": 54}, "syntax": {"word": "בלהט", "dep_head_idx": 152, "dep_func": "obl", "dep_head": "בכו"}, "seg": ["ב", "להט"], "lex": "להט", "morph": {"token": "בלהט", "pos": "NOUN", "feats": {"Gender": "Masc", "Number": "Sing"}, "prefixes": ["ADP"], "suffix": false}}, {"token": "הקדחת", "offsets": {"start": 55, "end": 60}, "syntax": {"word": "הקדחת", "dep_head_idx": 10, "dep_func": "compound:smixut", "dep_head": "בלהט"}, "seg": ["ה", "קדחת"], "lex": "קדחת", "morph": {"token": "הקדחת", "pos": "NOUN", "feats": {"Gender": "Fem", "Number": "Sing"}, "prefixes": ["DET"], "suffix": false}}, {"token": ".", "offsets": {"start": 60, "end": 61}, "syntax": {"word": ".", "dep_head_idx": 203, "dep_func": "punct", "dep_head": "חלם"}, "seg": ["."], "lex": ".", "morph": {"token": ".", "pos": "PUNCT", "feats": {}, "prefixes": [], "suffix": false}}, {"token": "אבי", "offsets": {"start": 63, "end": 66}, "syntax": {"word": "אבי", "dep_head_idx": 203, "dep_func": "nsubj", "dep_head": "חלם"}, "seg": ["אבי"], "lex": "אבי", "morph": {"token": "אבי", "pos": "NOUN", "feats": {"Gender": "Masc", "Number": "Sing"}, "prefixes": [], "suffix": "PRON", "suffix_feats": {"Gender": "Masc", "Number": "Sing", "Person": "1"}}}, {"token": "היה", "offsets": {"start": 67, "end": 70}, "syntax": {"word": "היה", "dep_head_idx": 104, "dep_func": "cop", "dep_head": "יקר"}, "seg": ["היה"], "lex": "היי", "morph": {"token": "היה", "pos": "AUX", "feats": {"Gender": "Masc", "Number": "Sing", "Person": "3", "Tense": "Past"}, "prefixes": [], "suffix": false}}, {"token": "אידיאליסט", "offsets": {"start": 71, "end": 80}, "syntax": {"word": "אידיאליסט", "dep_head_idx": 78, "dep_func": "parataxis", "dep_head": "שלום"}, "seg": ["אידיאליסט"], "lex": "##סט", "morph": {"token": "אידיאליסט", "pos": "NOUN", "feats": {"Gender": "Masc", "Number": "Sing"}, "prefixes": [], "suffix": false}}, {"token": "אמר", "offsets": {"start": 81, "end": 84}, "syntax": {"word": "אמר", "dep_head_idx": 87, "dep_func": "parataxis", "dep_head": "לחש"}, "seg": ["אמר"], "lex": "אמר", "morph": {"token": "אמר", "pos": "VERB", "feats": {"Gender": "Masc", "Number": "Sing", "Person": "3", "Tense": "Past"}, "prefixes": [], "suffix": false}}, {"token": "צריך", "offsets": {"start": 85, "end": 89}, "syntax": {"word": "צריך", "dep_head_idx": 87, "dep_func": "aux", "dep_head": "לחש"}, "seg": ["צריך"], "lex": "צריך", "morph": {"token": "צריך", "pos": "AUX", "feats": {"Gender": "Masc", "Number": "Sing"}, "prefixes": [], "suffix": false}}, {"token": "לחיות", "offsets": {"start": 90, "end": 95}, "syntax": {"word": "לחיות", "dep_head_idx": 16, "dep_func": "ccomp", "dep_head": "אמר"}, "seg": ["לחיות"], "lex": "חי", "morph": {"token": "לחיות", "pos": "VERB", "feats": {}, "prefixes": [], "suffix": false}}, {"token": "ביחד", "offsets": {"start": 96, "end": 100}, "syntax": {"word": "ביחד", "dep_head_idx": 18, "dep_func": "advmod", "dep_head": "לחיות"}, "seg": ["ביחד"], "lex": "יחד", "morph": {"token": "ביחד", "pos": "ADV", "feats": {}, "prefixes": [], "suffix": false}}, {"token": "אבי", "offsets": {"start": 101, "end": 104}, "syntax": {"word": "אבי", "dep_head_idx": 108, "dep_func": "nsubj", "dep_head": "מוכרים"}, "seg": ["אבי"], "lex": "אבי", "morph": {"token": "אבי", "pos": "NOUN", "feats": {"Gender": "Masc", "Number": "Sing"}, "prefixes": [], "suffix": "PRON", "suffix_feats": {"Gender": "Masc", "Number": "Sing", "Person": "1"}}}, {"token": "לימד", "offsets": {"start": 105, "end": 109}, "syntax": {"word": "לימד", "dep_head_idx": 16, "dep_func": "ccomp", "dep_head": "אמר"}, "seg": ["לימד"], "lex": "לימד", "morph": {"token": "לימד", "pos": "VERB", "feats": {"Gender": "Masc", "Number": "Sing", "Person": "3", "Tense": "Past"}, "prefixes": [], "suffix": false}}, {"token": "אותי", "offsets": {"start": 110, "end": 114}, "syntax": {"word": "אותי", "dep_head_idx": 21, "dep_func": "obj", "dep_head": "לימד"}, "seg": ["אותי"], "lex": "את", "morph": {"token": "אותי", "pos": "ADP", "feats": {}, "prefixes": [], "suffix": "PRON", "suffix_feats": {"Gender": "Masc", "Number": "Sing", "Person": "1"}}}, {"token": "לתת", "offsets": {"start": 115, "end": 118}, "syntax": {"word": "לתת", "dep_head_idx": 21, "dep_func": "xcomp", "dep_head": "לימד"}, "seg": ["לתת"], "lex": "[BLANK]", "morph": {"token": "לתת", "pos": "VERB", "feats": {}, "prefixes": [], "suffix": false}}, {"token": "אני", "offsets": {"start": 119, "end": 122}, "syntax": {"word": "אני", "dep_head_idx": 115, "dep_func": "nsubj", "dep_head": "אוהב"}, "seg": ["אני"], "lex": "אני", "morph": {"token": "אני", "pos": "PRON", "feats": {"Gender": "Masc", "Number": "Sing", "Person": "1"}, "prefixes": [], "suffix": false}}, {"token": "למדתי", "offsets": {"start": 123, "end": 128}, "syntax": {"word": "למדתי", "dep_head_idx": 95, "dep_func": "parataxis", "dep_head": "חזרנו"}, "seg": ["למדתי"], "lex": "לימד", "morph": {"token": "למדתי", "pos": "VERB", "feats": {"Gender": "Fem", "Number": "Sing", "Person": "1", "Tense": "Past"}, "prefixes": [], "suffix": false}}, {"token": "לקחת", "offsets": {"start": 129, "end": 133}, "syntax": {"word": "לקחת", "dep_head_idx": 25, "dep_func": "xcomp", "dep_head": "למדתי"}, "seg": ["לקחת"], "lex": "לקחו", "morph": {"token": "לקחת", "pos": "VERB", "feats": {}, "prefixes": [], "suffix": false}}, {"token": "אבי", "offsets": {"start": 134, "end": 137}, "syntax": {"word": "אבי", "dep_head_idx": 116, "dep_func": "obj", "dep_head": "בונה"}, "seg": ["אבי"], "lex": "אבי", "morph": {"token": "אבי", "pos": "NOUN", "feats": {"Gender": "Masc", "Number": "Sing"}, "prefixes": [], "suffix": "PRON", "suffix_feats": {"Gender": "Masc", "Number": "Sing", "Person": "1"}}}, {"token": "הלך", "offsets": {"start": 138, "end": 141}, "syntax": {"word": "הלך", "dep_head_idx": 136, "dep_func": "acl:relcl", "dep_head": "עיר"}, "seg": ["הלך"], "lex": "הלך", "morph": {"token": "הלך", "pos": "VERB", "feats": {"Gender": "Masc", "Number": "Sing", "Person": "3", "Tense": "Past"}, "prefixes": [], "suffix": false}}, {"token": "בכפר", "offsets": {"start": 142, "end": 146}, "syntax": {"word": "בכפר", "dep_head_idx": 116, "dep_func": "obl", "dep_head": "בונה"}, "seg": ["ב", "כפר"], "lex": "כפר", "morph": {"token": "בכפר", "pos": "NOUN", "feats": {"Gender": "Masc", "Number": "Sing"}, "prefixes": ["ADP"], "suffix": false}}, {"token": "לחיות", "offsets": {"start": 147, "end": 152}, "syntax": {"word": "לחיות", "dep_head_idx": 29, "dep_func": "flat:name", "dep_head": "בכפר"}, "seg": ["לחיות"], "lex": "לחיות", "morph": {"token": "לחיות", "pos": "PROPN", "feats": {}, "prefixes": [], "suffix": false}}, {"token": "חלוץ", "offsets": {"start": 153, "end": 157}, "syntax": {"word": "חלוץ", "dep_head_idx": 29, "dep_func": "flat", "dep_head": "בכפר"}, "seg": ["חלוץ"], "lex": "חלוץ", "morph": {"token": "חלוץ", "pos": "PROPN", "feats": {}, "prefixes": [], "suffix": false}}, {"token": "היה", "offsets": {"start": 158, "end": 161}, "syntax": {"word": "היה", "dep_head_idx": 141, "dep_func": "cop", "dep_head": "לתלפיות"}, "seg": ["היה"], "lex": "היי", "morph": {"token": "היה", "pos": "AUX", "feats": {"Gender": "Masc", "Number": "Sing", "Person": "3", "Tense": "Past"}, "prefixes": [], "suffix": false}}, {"token": "מגיל", "offsets": {"start": 162, "end": 166}, "syntax": {"word": "מגיל", "dep_head_idx": 121, "dep_func": "obl", "dep_head": "נוקב"}, "seg": ["מ", "גיל"], "lex": "גיל", "morph": {"token": "מגיל", "pos": "NOUN", "feats": {"Gender": "Masc", "Number": "Sing"}, "prefixes": ["ADP"], "suffix": false}}, {"token": "צעיר", "offsets": {"start": 167, "end": 171}, "syntax": {"word": "צעיר", "dep_head_idx": 33, "dep_func": "amod", "dep_head": "מגיל"}, "seg": ["צעיר"], "lex": "צעיר", "morph": {"token": "צעיר", "pos": "ADJ", "feats": {"Gender": "Masc", "Number": "Sing"}, "prefixes": [], "suffix": false}}, {"token": "נשם", "offsets": {"start": 172, "end": 175}, "syntax": {"word": "נשם", "dep_head_idx": 142, "dep_func": "conj", "dep_head": "הפועלים"}, "seg": ["נשם"], "lex": "נשם", "morph": {"token": "נשם", "pos": "VERB", "feats": {"Gender": "Masc", "Number": "Sing", "Person": "3", "Tense": "Past"}, "prefixes": [], "suffix": false}}, {"token": "מיזוג", "offsets": {"start": 176, "end": 181}, "syntax": {"word": "מיזוג", "dep_head_idx": 148, "dep_func": "nsubj", "dep_head": "ישבה"}, "seg": ["מיזוג"], "lex": "מיזוג", "morph": {"token": "מיזוג", "pos": "NOUN", "feats": {"Gender": "Masc", "Number": "Sing"}, "prefixes": [], "suffix": false}}, {"token": "של", "offsets": {"start": 182, "end": 184}, "syntax": {"word": "של", "dep_head_idx": 38, "dep_func": "case:gen", "dep_head": "גלויות"}, "seg": ["של"], "lex": "של", "morph": {"token": "של", "pos": "ADP", "feats": {}, "prefixes": [], "suffix": false}}, {"token": "גלויות", "offsets": {"start": 185, "end": 191}, "syntax": {"word": "גלויות", "dep_head_idx": 36, "dep_func": "nmod:poss", "dep_head": "מיזוג"}, "seg": ["גלויות"], "lex": "גלות", "morph": {"token": "גלויות", "pos": "NOUN", "feats": {"Gender": "Fem", "Number": "Plur"}, "prefixes": [], "suffix": false}}, {"token": "אני", "offsets": {"start": 192, "end": 195}, "syntax": {"word": "אני", "dep_head_idx": 40, "dep_func": "nsubj", "dep_head": "נושם"}, "seg": ["אני"], "lex": "אני", "morph": {"token": "אני", "pos": "PRON", "feats": {"Gender": "Masc", "Number": "Sing", "Person": "1"}, "prefixes": [], "suffix": false}}, {"token": "נושם", "offsets": {"start": 196, "end": 200}, "syntax": {"word": "נושם", "dep_head_idx": 136, "dep_func": "acl:relcl", "dep_head": "עיר"}, "seg": ["נושם"], "lex": "נושם", "morph": {"token": "נושם", "pos": "VERB", "feats": {"Gender": "Masc", "Number": "Sing", "Person": "3", "Tense": "Pres"}, "prefixes": [], "suffix": false}}, {"token": "מיזוג", "offsets": {"start": 201, "end": 206}, "syntax": {"word": "מיזוג", "dep_head_idx": 40, "dep_func": "obj", "dep_head": "נושם"}, "seg": ["מיזוג"], "lex": "מיזוג", "morph": {"token": "מיזוג", "pos": "NOUN", "feats": {"Gender": "Masc", "Number": "Sing"}, "prefixes": [], "suffix": false}}, {"token": "אוויר", "offsets": {"start": 207, "end": 212}, "syntax": {"word": "אוויר", "dep_head_idx": 41, "dep_func": "compound:smixut", "dep_head": "מיזוג"}, "seg": ["אוויר"], "lex": "אוויר", "morph": {"token": "אוויר", "pos": "NOUN", "feats": {"Gender": "Masc", "Number": "Sing"}, "prefixes": [], "suffix": false}}, {"token": "אבי", "offsets": {"start": 213, "end": 216}, "syntax": {"word": "אבי", "dep_head_idx": 44, "dep_func": "obj", "dep_head": "ראה"}, "seg": ["אבי"], "lex": "אבי", "morph": {"token": "אבי", "pos": "NOUN", "feats": {"Gender": "Masc", "Number": "Sing"}, "prefixes": [], "suffix": "PRON", "suffix_feats": {"Gender": "Masc", "Number": "Sing", "Person": "1"}}}, {"token": "ראה", "offsets": {"start": 217, "end": 220}, "syntax": {"word": "ראה", "dep_head_idx": 136, "dep_func": "acl:relcl", "dep_head": "עיר"}, "seg": ["ראה"], "lex": "ראה", "morph": {"token": "ראה", "pos": "VERB", "feats": {"Gender": "Masc", "Number": "Sing", "Person": "3", "Tense": "Past"}, "prefixes": [], "suffix": false}}, {"token": "בכל", "offsets": {"start": 221, "end": 224}, "syntax": {"word": "בכל", "dep_head_idx": 47, "dep_func": "det", "dep_head": "שליחות"}, "seg": ["ב", "כל"], "lex": "כל", "morph": {"token": "בכל", "pos": "DET", "feats": {}, "prefixes": ["ADP"], "suffix": false}}, {"token": "-", "offsets": {"start": 225, "end": 226}, "syntax": {"word": "-", "dep_head_idx": 45, "dep_func": "punct", "dep_head": "בכל"}, "seg": ["-"], "lex": "-", "morph": {"token": "-", "pos": "PUNCT", "feats": {}, "prefixes": [], "suffix": false}}, {"token": "שליחות", "offsets": {"start": 227, "end": 233}, "syntax": {"word": "שליחות", "dep_head_idx": 44, "dep_func": "obj", "dep_head": "ראה"}, "seg": ["שליחות"], "lex": "שליחות", "morph": {"token": "שליחות", "pos": "NOUN", "feats": {"Gender": "Fem", "Number": "Sing"}, "prefixes": [], "suffix": false}}, {"token": "ברפת", "offsets": {"start": 234, "end": 238}, "syntax": {"word": "ברפת", "dep_head_idx": 47, "dep_func": "nmod", "dep_head": "שליחות"}, "seg": ["ב", "רפת"], "lex": "רפת", "morph": {"token": "ברפת", "pos": "NOUN", "feats": {"Gender": "Fem", "Number": "Sing"}, "prefixes": ["DET", "ADP"], "suffix": false}}, {"token": ",", "offsets": {"start": 238, "end": 239}, "syntax": {"word": ",", "dep_head_idx": 52, "dep_func": "punct", "dep_head": "בלול"}, "seg": [","], "lex": ",", "morph": {"token": ",", "pos": "PUNCT", "feats": {}, "prefixes": [], "suffix": false}}, {"token": "בשדה", "offsets": {"start": 240, "end": 244}, "syntax": {"word": "בשדה", "dep_head_idx": 142, "dep_func": "nmod", "dep_head": "הפועלים"}, "seg": ["ב", "שדה"], "lex": "שדה", "morph": {"token": "בשדה", "pos": "NOUN", "feats": {"Gender": "Masc", "Number": "Sing"}, "prefixes": ["DET", "ADP"], "suffix": false}}, {"token": ",", "offsets": {"start": 244, "end": 245}, "syntax": {"word": ",", "dep_head_idx": 52, "dep_func": "punct", "dep_head": "בלול"}, "seg": [","], "lex": ",", "morph": {"token": ",", "pos": "PUNCT", "feats": {}, "prefixes": [], "suffix": false}}, {"token": "בלול", "offsets": {"start": 246, "end": 250}, "syntax": {"word": "בלול", "dep_head_idx": 142, "dep_func": "obl", "dep_head": "הפועלים"}, "seg": ["ב", "לול"], "lex": "לול", "morph": {"token": "בלול", "pos": "NOUN", "feats": {"Gender": "Masc", "Number": "Sing"}, "prefixes": ["DET", "ADP"], "suffix": false}}, {"token": "אני", "offsets": {"start": 251, "end": 254}, "syntax": {"word": "אני", "dep_head_idx": 54, "dep_func": "nsubj", "dep_head": "יודע"}, "seg": ["אני"], "lex": "אני", "morph": {"token": "אני", "pos": "PRON", "feats": {"Gender": "Masc", "Number": "Sing", "Person": "1"}, "prefixes": [], "suffix": false}}, {"token": "יודע", "offsets": {"start": 255, "end": 259}, "syntax": {"word": "יודע", "dep_head_idx": 141, "dep_func": "parataxis", "dep_head": "לתלפיות"}, "seg": ["יודע"], "lex": "יודע", "morph": {"token": "יודע", "pos": "VERB", "feats": {"Gender": "Masc", "Number": "Sing", "Person": "1", "Tense": "Pres"}, "prefixes": [], "suffix": false}}, {"token": "ששליחות", "offsets": {"start": 260, "end": 267}, "syntax": {"word": "ששליחות", "dep_head_idx": 169, "dep_func": "nsubj", "dep_head": "הקריב"}, "seg": ["ש", "שליחות"], "lex": "מלחמה", "morph": {"token": "ששליחות", "pos": "NOUN", "feats": {"Gender": "Fem", "Number": "Sing"}, "prefixes": ["SCONJ"], "suffix": false}}, {"token": "היא", "offsets": {"start": 268, "end": 271}, "syntax": {"word": "היא", "dep_head_idx": 152, "dep_func": "cop", "dep_head": "בכו"}, "seg": ["היא"], "lex": "הוא", "morph": {"token": "היא", "pos": "PRON", "feats": {"Gender": "Fem", "Number": "Sing", "Person": "3"}, "prefixes": [], "suffix": false}}, {"token": "כששולחים", "offsets": {"start": 272, "end": 280}, "syntax": {"word": "כששולחים", "dep_head_idx": 152, "dep_func": "advcl", "dep_head": "בכו"}, "seg": ["כש", "שולחים"], "lex": "[BLANK]", "morph": {"token": "כששולחים", "pos": "VERB", "feats": {"Gender": "Masc", "Number": "Plur", "Person": "3", "Tense": "Pres"}, "prefixes": ["SCONJ"], "suffix": false}}, {"token": "אותך", "offsets": {"start": 281, "end": 285}, "syntax": {"word": "אותך", "dep_head_idx": 57, "dep_func": "obj", "dep_head": "כששולחים"}, "seg": ["אותך"], "lex": "את", "morph": {"token": "אותך", "pos": "ADP", "feats": {}, "prefixes": [], "suffix": "PRON", "suffix_feats": {"Gender": "Masc", "Number": "Sing", "Person": "2"}}}, {"token": "לחו\"ל", "offsets": {"start": 286, "end": 291}, "syntax": {"word": "לחו\"ל", "dep_head_idx": 57, "dep_func": "obl", "dep_head": "כששולחים"}, "seg": ["ל", "חו\"ל"], "lex": "חו\"ל", "morph": {"token": "לחו\"ל", "pos": "NOUN", "feats": {"Gender": "Masc", "Number": "Sing"}, "prefixes": ["ADP"], "suffix": false}}, {"token": "הוא", "offsets": {"start": 292, "end": 295}, "syntax": {"word": "הוא", "dep_head_idx": 61, "dep_func": "nsubj", "dep_head": "חי"}, "seg": ["הוא"], "lex": "הוא", "morph": {"token": "הוא", "pos": "PRON", "feats": {"Gender": "Masc", "Number": "Sing", "Person": "3"}, "prefixes": [], "suffix": false}}, {"token": "חי", "offsets": {"start": 296, "end": 298}, "syntax": {"word": "חי", "dep_head_idx": 44, "dep_func": "conj", "dep_head": "ראה"}, "seg": ["חי"], "lex": "חי", "morph": {"token": "חי", "pos": "VERB", "feats": {"Gender": "Masc", "Number": "Sing", "Person": "3", "Tense": "Pres"}, "prefixes": [], "suffix": false}}, {"token": "על", "offsets": {"start": 299, "end": 301}, "syntax": {"word": "על", "dep_head_idx": 47, "dep_func": "case", "dep_head": "שליחות"}, "seg": ["על"], "lex": "על", "morph": {"token": "על", "pos": "ADP", "feats": {}, "prefixes": [], "suffix": false}}, {"token": "פיתה", "offsets": {"start": 302, "end": 306}, "syntax": {"word": "פיתה", "dep_head_idx": 152, "dep_func": "obl", "dep_head": "בכו"}, "seg": ["פיתה"], "lex": "פיתה", "morph": {"token": "פיתה", "pos": "NOUN", "feats": {"Gender": "Fem", "Number": "Sing"}, "prefixes": [], "suffix": false}}, {"token": "וזיתים", "offsets": {"start": 307, "end": 313}, "syntax": {"word": "וזיתים", "dep_head_idx": 152, "dep_func": "conj", "dep_head": "בכו"}, "seg": ["ו", "זיתים"], "lex": "זית", "morph": {"token": "וזיתים", "pos": "NOUN", "feats": {"Gender": "Masc", "Number": "Plur"}, "prefixes": ["CCONJ"], "suffix": false}}, {"token": "רעב", "offsets": {"start": 314, "end": 317}, "syntax": {"word": "רעב", "dep_head_idx": 152, "dep_func": "obl", "dep_head": "בכו"}, "seg": ["רעב"], "lex": "רעב", "morph": {"token": "רעב", "pos": "ADJ", "feats": {"Gender": "Masc", "Number": "Sing"}, "prefixes": [], "suffix": false}}, {"token": "לא", "offsets": {"start": 318, "end": 320}, "syntax": {"word": "לא", "dep_head_idx": 67, "dep_func": "advmod", "dep_head": "פעם"}, "seg": ["לא"], "lex": "לא", "morph": {"token": "לא", "pos": "ADV", "feats": {}, "prefixes": [], "suffix": false}}, {"token": "פעם", "offsets": {"start": 321, "end": 324}, "syntax": {"word": "פעם", "dep_head_idx": 66, "dep_func": "fixed", "dep_head": "לא"}, "seg": ["פעם"], "lex": "פעם", "morph": {"token": "פעם", "pos": "ADV", "feats": {}, "prefixes": [], "suffix": false}}, {"token": "בלילות", "offsets": {"start": 325, "end": 331}, "syntax": {"word": "בלילות", "dep_head_idx": 72, "dep_func": "obl", "dep_head": "רעבתי"}, "seg": ["ב", "לילות"], "lex": "ליל", "morph": {"token": "בלילות", "pos": "NOUN", "feats": {"Gender": "Masc", "Number": "Plur"}, "prefixes": ["ADP"], "suffix": false}}, {"token": "אני", "offsets": {"start": 332, "end": 335}, "syntax": {"word": "אני", "dep_head_idx": 87, "dep_func": "nsubj", "dep_head": "לחש"}, "seg": ["אני"], "lex": "אני", "morph": {"token": "אני", "pos": "PRON", "feats": {"Gender": "Masc", "Number": "Sing", "Person": "1"}, "prefixes": [], "suffix": false}}, {"token": "עוד", "offsets": {"start": 336, "end": 339}, "syntax": {"word": "עוד", "dep_head_idx": 218, "dep_func": "advmod", "dep_head": "לא"}, "seg": ["עוד"], "lex": "עוד", "morph": {"token": "עוד", "pos": "ADV", "feats": {}, "prefixes": [], "suffix": false}}, {"token": "לא", "offsets": {"start": 340, "end": 342}, "syntax": {"word": "לא", "dep_head_idx": 72, "dep_func": "advmod", "dep_head": "רעבתי"}, "seg": ["לא"], "lex": "לא", "morph": {"token": "לא", "pos": "ADV", "feats": {}, "prefixes": [], "suffix": false}}, {"token": "רעבתי", "offsets": {"start": 343, "end": 348}, "syntax": {"word": "רעבתי", "dep_head_idx": 54, "dep_func": "ccomp", "dep_head": "יודע"}, "seg": ["רעבתי"], "lex": "רעב", "morph": {"token": "רעבתי", "pos": "VERB", "feats": {"Gender": "Masc", "Number": "Sing", "Person": "3", "Tense": "Past"}, "prefixes": [], "suffix": false}}, {"token": "יום", "offsets": {"start": 349, "end": 352}, "syntax": {"word": "יום", "dep_head_idx": 169, "dep_func": "obl:tmod", "dep_head": "הקריב"}, "seg": ["יום"], "lex": "יום", "morph": {"token": "יום", "pos": "NOUN", "feats": {"Gender": "Masc", "Number": "Sing"}, "prefixes": [], "suffix": false}}, {"token": "בזכות", "offsets": {"start": 353, "end": 358}, "syntax": {"word": "בזכות", "dep_head_idx": 75, "dep_func": "case", "dep_head": "פנקס"}, "seg": ["בזכות"], "lex": "בזכות", "morph": {"token": "בזכות", "pos": "ADP", "feats": {}, "prefixes": [], "suffix": false}}, {"token": "פנקס", "offsets": {"start": 359, "end": 363}, "syntax": {"word": "פנקס", "dep_head_idx": 61, "dep_func": "obl", "dep_head": "חי"}, "seg": ["פנקס"], "lex": "פנקס", "morph": {"token": "פנקס", "pos": "NOUN", "feats": {"Gender": "Masc", "Number": "Sing"}, "prefixes": [], "suffix": false}}, {"token": "הקבלות", "offsets": {"start": 364, "end": 370}, "syntax": {"word": "הקבלות", "dep_head_idx": 75, "dep_func": "compound:smixut", "dep_head": "פנקס"}, "seg": ["ה", "קבלות"], "lex": "קבלה", "morph": {"token": "הקבלות", "pos": "NOUN", "feats": {"Gender": "Fem", "Number": "Plur"}, "prefixes": ["DET"], "suffix": false}}, {"token": ".", "offsets": {"start": 370, "end": 371}, "syntax": {"word": ".", "dep_head_idx": 203, "dep_func": "punct", "dep_head": "חלם"}, "seg": ["."], "lex": ".", "morph": {"token": ".", "pos": "PUNCT", "feats": {}, "prefixes": [], "suffix": false}}, {"token": "שלום", "offsets": {"start": 373, "end": 377}, "syntax": {"word": "שלום", "dep_head_idx": 95, "dep_func": "vocative", "dep_head": "חזרנו"}, "seg": ["שלום"], "lex": "שלום", "morph": {"token": "שלום", "pos": "INTJ", "feats": {"Gender": "Masc", "Number": "Sing"}, "prefixes": [], "suffix": false}}, {"token": "לך", "offsets": {"start": 378, "end": 380}, "syntax": {"word": "לך", "dep_head_idx": 78, "dep_func": "obl", "dep_head": "שלום"}, "seg": ["לך"], "lex": "לי", "morph": {"token": "לך", "pos": "PRON", "feats": {"Gender": "Masc", "Number": "Sing", "Person": "2"}, "prefixes": [], "suffix": "PRON", "suffix_feats": {"Number": "Sing"}}}, {"token": "ארצי", "offsets": {"start": 381, "end": 385}, "syntax": {"word": "ארצי", "dep_head_idx": 87, "dep_func": "nsubj", "dep_head": "לחש"}, "seg": ["ארצי"], "lex": "ארצי", "morph": {"token": "ארצי", "pos": "PROPN", "feats": {}, "prefixes": [], "suffix": "PRON", "suffix_feats": {"Gender": "Masc", "Number": "Sing", "Person": "1"}}}, {"token": "שלי", "offsets": {"start": 386, "end": 389}, "syntax": {"word": "שלי", "dep_head_idx": 78, "dep_func": "nmod:poss", "dep_head": "שלום"}, "seg": ["שלי"], "lex": "של", "morph": {"token": "שלי", "pos": "ADP", "feats": {}, "prefixes": [], "suffix": "PRON", "suffix_feats": {"Gender": "Masc", "Number": "Sing", "Person": "1"}}}, {"token": "שלום", "offsets": {"start": 390, "end": 394}, "syntax": {"word": "שלום", "dep_head_idx": 87, "dep_func": "parataxis", "dep_head": "לחש"}, "seg": ["שלום"], "lex": "שלום", "morph": {"token": "שלום", "pos": "NOUN", "feats": {"Gender": "Masc", "Number": "Sing"}, "prefixes": [], "suffix": false}}, {"token": "לך", "offsets": {"start": 395, "end": 397}, "syntax": {"word": "לך", "dep_head_idx": 82, "dep_func": "obl", "dep_head": "שלום"}, "seg": ["לך"], "lex": "לו", "morph": {"token": "לך", "pos": "PRON", "feats": {"Gender": "Masc", "Number": "Sing", "Person": "2"}, "prefixes": [], "suffix": "PRON", "suffix_feats": {"Number": "Sing"}}}, {"token": "ירושלים", "offsets": {"start": 398, "end": 405}, "syntax": {"word": "ירושלים", "dep_head_idx": 87, "dep_func": "obj", "dep_head": "לחש"}, "seg": ["ירושלים"], "lex": "ירושלים", "morph": {"token": "ירושלים", "pos": "PROPN", "feats": {}, "prefixes": [], "suffix": false}}, {"token": "אבי", "offsets": {"start": 406, "end": 409}, "syntax": {"word": "אבי", "dep_head_idx": 87, "dep_func": "nsubj", "dep_head": "לחש"}, "seg": ["אבי"], "lex": "אבי", "morph": {"token": "אבי", "pos": "NOUN", "feats": {"Gender": "Masc", "Number": "Sing"}, "prefixes": [], "suffix": "PRON", "suffix_feats": {"Gender": "Masc", "Number": "Sing", "Person": "1"}}}, {"token": "שלי", "offsets": {"start": 410, "end": 413}, "syntax": {"word": "שלי", "dep_head_idx": 85, "dep_func": "nmod:poss", "dep_head": "אבי"}, "seg": ["שלי"], "lex": "של", "morph": {"token": "שלי", "pos": "ADP", "feats": {}, "prefixes": [], "suffix": "PRON", "suffix_feats": {"Gender": "Masc", "Number": "Sing", "Person": "1"}}}, {"token": "לחש", "offsets": {"start": 414, "end": 417}, "syntax": {"word": "לחש", "dep_head_idx": 95, "dep_func": "parataxis", "dep_head": "חזרנו"}, "seg": ["לחש"], "lex": "לחש", "morph": {"token": "לחש", "pos": "VERB", "feats": {"Gender": "Masc", "Number": "Sing", "Person": "3", "Tense": "Past"}, "prefixes": [], "suffix": false}}, {"token": "את", "offsets": {"start": 418, "end": 420}, "syntax": {"word": "את", "dep_head_idx": 89, "dep_func": "case:acc", "dep_head": "שמך"}, "seg": ["את"], "lex": "את", "morph": {"token": "את", "pos": "ADP", "feats": {}, "prefixes": [], "suffix": false}}, {"token": "שמך", "offsets": {"start": 421, "end": 424}, "syntax": {"word": "שמך", "dep_head_idx": 87, "dep_func": "obj", "dep_head": "לחש"}, "seg": ["שמך"], "lex": "שמות", "morph": {"token": "שמך", "pos": "NOUN", "feats": {"Gender": "Masc", "Number": "Sing"}, "prefixes": [], "suffix": "PRON", "suffix_feats": {"Gender": "Masc", "Number": "Sing", "Person": "2"}}}, {"token": "עם", "offsets": {"start": 425, "end": 427}, "syntax": {"word": "עם", "dep_head_idx": 111, "dep_func": "case", "dep_head": "ספסר"}, "seg": ["עם"], "lex": "עם", "morph": {"token": "עם", "pos": "ADP", "feats": {}, "prefixes": [], "suffix": false}}, {"token": "רטט", "offsets": {"start": 428, "end": 431}, "syntax": {"word": "רטט", "dep_head_idx": 87, "dep_func": "obl", "dep_head": "לחש"}, "seg": ["רטט"], "lex": "רטט", "morph": {"token": "רטט", "pos": "NOUN", "feats": {"Gender": "Masc", "Number": "Sing"}, "prefixes": [], "suffix": false}}, {"token": "בשפתיים", "offsets": {"start": 432, "end": 439}, "syntax": {"word": "בשפתיים", "dep_head_idx": 87, "dep_func": "obl", "dep_head": "לחש"}, "seg": ["ב", "שפתיים"], "lex": "שפה", "morph": {"token": "בשפתיים", "pos": "NOUN", "feats": {"Gender": "Fem", "Number": "Plur"}, "prefixes": ["ADP"], "suffix": false}}, {"token": ".", "offsets": {"start": 439, "end": 440}, "syntax": {"word": ".", "dep_head_idx": 203, "dep_func": "punct", "dep_head": "חלם"}, "seg": ["."], "lex": ".", "morph": {"token": ".", "pos": "PUNCT", "feats": {}, "prefixes": [], "suffix": false}}, {"token": "\"", "offsets": {"start": 442, "end": 443}, "syntax": {"word": "\"", "dep_head_idx": 203, "dep_func": "punct", "dep_head": "חלם"}, "seg": ["\""], "lex": "\"", "morph": {"token": "\"", "pos": "PUNCT", "feats": {}, "prefixes": [], "suffix": false}}, {"token": "חזרנו", "offsets": {"start": 443, "end": 448}, "syntax": {"word": "חזרנו", "dep_head_idx": 134, "dep_func": "parataxis", "dep_head": "נבנית"}, "seg": ["חזרנו"], "lex": "חזר", "morph": {"token": "חזרנו", "pos": "VERB", "feats": {"Gender": "Masc", "Number": "Plur", "Person": "1", "Tense": "Past"}, "prefixes": [], "suffix": false}}, {"token": "אל", "offsets": {"start": 449, "end": 451}, "syntax": {"word": "אל", "dep_head_idx": 97, "dep_func": "case", "dep_head": "בורות"}, "seg": ["אל"], "lex": "אל", "morph": {"token": "אל", "pos": "ADP", "feats": {}, "prefixes": [], "suffix": false}}, {"token": "בורות", "offsets": {"start": 452, "end": 457}, "syntax": {"word": "בורות", "dep_head_idx": 18, "dep_func": "obl", "dep_head": "לחיות"}, "seg": ["בורות"], "lex": "בור", "morph": {"token": "בורות", "pos": "NOUN", "feats": {"Gender": "Masc", "Number": "Plur"}, "prefixes": [], "suffix": false}}, {"token": "המים", "offsets": {"start": 458, "end": 462}, "syntax": {"word": "המים", "dep_head_idx": 97, "dep_func": "compound:smixut", "dep_head": "בורות"}, "seg": ["ה", "מים"], "lex": "מים", "morph": {"token": "המים", "pos": "NOUN", "feats": {"Gender": "Masc", "Number": "Plur"}, "prefixes": ["DET"], "suffix": false}}, {"token": "\"", "offsets": {"start": 462, "end": 463}, "syntax": {"word": "\"", "dep_head_idx": 203, "dep_func": "punct", "dep_head": "חלם"}, "seg": ["\""], "lex": "\"", "morph": {"token": "\"", "pos": "PUNCT", "feats": {}, "prefixes": [], "suffix": false}}, {"token": "גם", "offsets": {"start": 464, "end": 466}, "syntax": {"word": "גם", "dep_head_idx": 104, "dep_func": "advmod", "dep_head": "יקר"}, "seg": ["גם"], "lex": "גם", "morph": {"token": "גם", "pos": "ADV", "feats": {}, "prefixes": [], "suffix": false}}, {"token": "אם", "offsets": {"start": 467, "end": 469}, "syntax": {"word": "אם", "dep_head_idx": 207, "dep_func": "mark", "dep_head": "תראו"}, "seg": ["אם"], "lex": "אם", "morph": {"token": "אם", "pos": "SCONJ", "feats": {}, "prefixes": [], "suffix": false}}, {"token": "המחיר", "offsets": {"start": 470, "end": 475}, "syntax": {"word": "המחיר", "dep_head_idx": 123, "dep_func": "nsubj", "dep_head": "צורב"}, "seg": ["ה", "מחיר"], "lex": "מחיר", "morph": {"token": "המחיר", "pos": "NOUN", "feats": {"Gender": "Masc", "Number": "Sing"}, "prefixes": ["DET"], "suffix": false}}, {"token": "היה", "offsets": {"start": 476, "end": 479}, "syntax": {"word": "היה", "dep_head_idx": 104, "dep_func": "cop", "dep_head": "יקר"}, "seg": ["היה"], "lex": "היי", "morph": {"token": "היה", "pos": "AUX", "feats": {"Gender": "Masc", "Number": "Sing", "Person": "3", "Tense": "Past"}, "prefixes": [], "suffix": false}}, {"token": "יקר", "offsets": {"start": 480, "end": 483}, "syntax": {"word": "יקר", "dep_head_idx": 87, "dep_func": "ccomp", "dep_head": "לחש"}, "seg": ["יקר"], "lex": "יקר", "morph": {"token": "יקר", "pos": "ADJ", "feats": {"Gender": "Masc", "Number": "Sing"}, "prefixes": [], "suffix": false}}, {"token": "היום", "offsets": {"start": 484, "end": 488}, "syntax": {"word": "היום", "dep_head_idx": 104, "dep_func": "advmod", "dep_head": "יקר"}, "seg": ["ה", "יום"], "lex": "יום", "morph": {"token": "היום", "pos": "ADV", "feats": {}, "prefixes": ["DET"], "suffix": false}}, {"token": "עירי", "offsets": {"start": 489, "end": 493}, "syntax": {"word": "עירי", "dep_head_idx": 82, "dep_func": "vocative", "dep_head": "שלום"}, "seg": ["עירי"], "lex": "עיר", "morph": {"token": "עירי", "pos": "NOUN", "feats": {"Gender": "Fem", "Number": "Sing"}, "prefixes": [], "suffix": "PRON", "suffix_feats": {"Gender": "Fem", "Number": "Sing", "Person": "1"}}}, {"token": "ירושלים", "offsets": {"start": 494, "end": 501}, "syntax": {"word": "ירושלים", "dep_head_idx": 106, "dep_func": "appos", "dep_head": "עירי"}, "seg": ["ירושלים"], "lex": "ירושלים", "morph": {"token": "ירושלים", "pos": "PROPN", "feats": {}, "prefixes": [], "suffix": false}}, {"token": "מוכרים", "offsets": {"start": 502, "end": 508}, "syntax": {"word": "מוכרים", "dep_head_idx": 16, "dep_func": "ccomp", "dep_head": "אמר"}, "seg": ["מוכרים"], "lex": "מוכר", "morph": {"token": "מוכרים", "pos": "VERB", "feats": {"Gender": "Masc", "Number": "Plur", "Person": "3"}, "prefixes": [], "suffix": false}}, {"token": "אותך", "offsets": {"start": 509, "end": 513}, "syntax": {"word": "אותך", "dep_head_idx": 87, "dep_func": "obj", "dep_head": "לחש"}, "seg": ["אותך"], "lex": "את", "morph": {"token": "אותך", "pos": "ADP", "feats": {}, "prefixes": [], "suffix": "PRON", "suffix_feats": {"Gender": "Masc", "Number": "Sing", "Person": "2"}}}, {"token": "לכל", "offsets": {"start": 514, "end": 517}, "syntax": {"word": "לכל", "dep_head_idx": 111, "dep_func": "det", "dep_head": "ספסר"}, "seg": ["ל", "כל"], "lex": "כול", "morph": {"token": "לכל", "pos": "DET", "feats": {}, "prefixes": ["ADP"], "suffix": false}}, {"token": "ספסר", "offsets": {"start": 518, "end": 522}, "syntax": {"word": "ספסר", "dep_head_idx": 87, "dep_func": "obl", "dep_head": "לחש"}, "seg": ["ספסר"], "lex": "[BLANK]", "morph": {"token": "ספסר", "pos": "NOUN", "feats": {"Gender": "Masc", "Number": "Sing"}, "prefixes": [], "suffix": false}}, {"token": "וכל", "offsets": {"start": 523, "end": 526}, "syntax": {"word": "וכל", "dep_head_idx": 113, "dep_func": "det", "dep_head": "קבלן"}, "seg": ["ו", "כל"], "lex": "כל", "morph": {"token": "וכל", "pos": "DET", "feats": {}, "prefixes": ["CCONJ"], "suffix": false}}, {"token": "קבלן", "offsets": {"start": 527, "end": 531}, "syntax": {"word": "קבלן", "dep_head_idx": 115, "dep_func": "nsubj", "dep_head": "אוהב"}, "seg": ["קבלן"], "lex": "קבלן", "morph": {"token": "קבלן", "pos": "NOUN", "feats": {"Gender": "Masc", "Number": "Sing"}, "prefixes": [], "suffix": false}}, {"token": "אותך", "offsets": {"start": 532, "end": 536}, "syntax": {"word": "אותך", "dep_head_idx": 116, "dep_func": "obj", "dep_head": "בונה"}, "seg": ["אותך"], "lex": "את", "morph": {"token": "אותך", "pos": "ADP", "feats": {}, "prefixes": [], "suffix": "PRON", "suffix_feats": {"Gender": "Masc", "Number": "Sing", "Person": "2"}}}, {"token": "אוהב", "offsets": {"start": 537, "end": 541}, "syntax": {"word": "אוהב", "dep_head_idx": 25, "dep_func": "conj", "dep_head": "למדתי"}, "seg": ["אוהב"], "lex": "אוהב", "morph": {"token": "אוהב", "pos": "VERB", "feats": {"Gender": "Masc", "Number": "Sing", "Person": "3", "Tense": "Pres"}, "prefixes": [], "suffix": false}}, {"token": "בונה", "offsets": {"start": 542, "end": 546}, "syntax": {"word": "בונה", "dep_head_idx": 115, "dep_func": "xcomp", "dep_head": "אוהב"}, "seg": ["בונה"], "lex": "בונה", "morph": {"token": "בונה", "pos": "VERB", "feats": {"Gender": "Masc", "Number": "Sing", "Person": "3", "Tense": "Pres"}, "prefixes": [], "suffix": false}}, {"token": "אותך", "offsets": {"start": 547, "end": 551}, "syntax": {"word": "אותך", "dep_head_idx": 116, "dep_func": "obj", "dep_head": "בונה"}, "seg": ["אותך"], "lex": "את", "morph": {"token": "אותך", "pos": "ADP", "feats": {}, "prefixes": [], "suffix": "PRON", "suffix_feats": {"Gender": "Masc", "Number": "Sing", "Person": "2"}}}, {"token": "ירושלים", "offsets": {"start": 552, "end": 559}, "syntax": {"word": "ירושלים", "dep_head_idx": 116, "dep_func": "obj", "dep_head": "בונה"}, "seg": ["ירושלים"], "lex": "ירושלים", "morph": {"token": "ירושלים", "pos": "PROPN", "feats": {}, "prefixes": [], "suffix": false}}, {"token": "והמחיר", "offsets": {"start": 560, "end": 566}, "syntax": {"word": "והמחיר", "dep_head_idx": 123, "dep_func": "nsubj", "dep_head": "צורב"}, "seg": ["וה", "מחיר"], "lex": "מחיר", "morph": {"token": "והמחיר", "pos": "NOUN", "feats": {"Gender": "Masc", "Number": "Sing"}, "prefixes": ["DET", "CCONJ"], "suffix": false}}, {"token": "שהוא", "offsets": {"start": 567, "end": 571}, "syntax": {"word": "שהוא", "dep_head_idx": 121, "dep_func": "nsubj", "dep_head": "נוקב"}, "seg": ["ש", "הוא"], "lex": "הוא", "morph": {"token": "שהוא", "pos": "PRON", "feats": {"Gender": "Masc", "Number": "Sing", "Person": "3"}, "prefixes": ["SCONJ"], "suffix": false}}, {"token": "נוקב", "offsets": {"start": 572, "end": 576}, "syntax": {"word": "נוקב", "dep_head_idx": 119, "dep_func": "acl:relcl", "dep_head": "והמחיר"}, "seg": ["נוקב"], "lex": "נוקב", "morph": {"token": "נוקב", "pos": "VERB", "feats": {"Gender": "Masc", "Number": "Sing", "Person": "3", "Tense": "Pres"}, "prefixes": [], "suffix": false}}, {"token": "אינו", "offsets": {"start": 577, "end": 581}, "syntax": {"word": "אינו", "dep_head_idx": 123, "dep_func": "advmod", "dep_head": "צורב"}, "seg": ["אינו"], "lex": "אינו", "morph": {"token": "אינו", "pos": "AUX", "feats": {"Gender": "Masc", "Number": "Sing", "Person": "3"}, "prefixes": [], "suffix": false}}, {"token": "צורב", "offsets": {"start": 582, "end": 586}, "syntax": {"word": "צורב", "dep_head_idx": 28, "dep_func": "conj", "dep_head": "הלך"}, "seg": ["צורב"], "lex": "צורב", "morph": {"token": "צורב", "pos": "VERB", "feats": {"Gender": "Masc", "Number": "Sing", "Person": "1,2,3"}, "prefixes": [], "suffix": false}}, {"token": "לו", "offsets": {"start": 587, "end": 589}, "syntax": {"word": "לו", "dep_head_idx": 123, "dep_func": "obl", "dep_head": "צורב"}, "seg": ["לו"], "lex": "לו", "morph": {"token": "לו", "pos": "PRON", "feats": {"Gender": "Masc", "Number": "Sing", "Person": "3"}, "prefixes": ["ADP"], "suffix": false}}, {"token": "בשפתיים", "offsets": {"start": 590, "end": 597}, "syntax": {"word": "בשפתיים", "dep_head_idx": 123, "dep_func": "obl", "dep_head": "צורב"}, "seg": ["ב", "שפתיים"], "lex": "שפה", "morph": {"token": "בשפתיים", "pos": "NOUN", "feats": {"Gender": "Fem", "Number": "Plur"}, "prefixes": ["DET", "ADP"], "suffix": false}}, {"token": ".", "offsets": {"start": 597, "end": 598}, "syntax": {"word": ".", "dep_head_idx": 203, "dep_func": "punct", "dep_head": "חלם"}, "seg": ["."], "lex": ".", "morph": {"token": ".", "pos": "PUNCT", "feats": {}, "prefixes": [], "suffix": false}}, {"token": "\"", "offsets": {"start": 600, "end": 601}, "syntax": {"word": "\"", "dep_head_idx": 54, "dep_func": "punct", "dep_head": "יודע"}, "seg": ["\""], "lex": "\"", "morph": {"token": "\"", "pos": "PUNCT", "feats": {}, "prefixes": [], "suffix": false}}, {"token": "מעל", "offsets": {"start": 601, "end": 604}, "syntax": {"word": "מעל", "dep_head_idx": 129, "dep_func": "case", "dep_head": "פסגת"}, "seg": ["מעל"], "lex": "על", "morph": {"token": "מעל", "pos": "ADP", "feats": {}, "prefixes": [], "suffix": false}}, {"token": "פסגת", "offsets": {"start": 605, "end": 609}, "syntax": {"word": "פסגת", "dep_head_idx": 229, "dep_func": "obl", "dep_head": "תתגברי"}, "seg": ["פסגת"], "lex": "פסגה", "morph": {"token": "פסגת", "pos": "NOUN", "feats": {"Gender": "Fem", "Number": "Sing"}, "prefixes": [], "suffix": false}}, {"token": "הר", "offsets": {"start": 610, "end": 612}, "syntax": {"word": "הר", "dep_head_idx": 129, "dep_func": "compound:smixut", "dep_head": "פסגת"}, "seg": ["הר"], "lex": "הר", "morph": {"token": "הר", "pos": "PROPN", "feats": {"Gender": "Masc", "Number": "Sing"}, "prefixes": [], "suffix": false}}, {"token": "הצופים", "offsets": {"start": 613, "end": 619}, "syntax": {"word": "הצופים", "dep_head_idx": 130, "dep_func": "compound:smixut", "dep_head": "הר"}, "seg": ["ה", "צופים"], "lex": "צופה", "morph": {"token": "הצופים", "pos": "PROPN", "feats": {"Number": "Plur"}, "prefixes": ["DET"], "suffix": false}}, {"token": "\"", "offsets": {"start": 619, "end": 620}, "syntax": {"word": "\"", "dep_head_idx": 134, "dep_func": "punct", "dep_head": "נבנית"}, "seg": ["\""], "lex": "\"", "morph": {"token": "\"", "pos": "PUNCT", "feats": {}, "prefixes": [], "suffix": false}}, {"token": "שנית", "offsets": {"start": 621, "end": 625}, "syntax": {"word": "שנית", "dep_head_idx": 134, "dep_func": "advmod", "dep_head": "נבנית"}, "seg": ["שנית"], "lex": "שנית", "morph": {"token": "שנית", "pos": "ADV", "feats": {}, "prefixes": [], "suffix": false}}, {"token": "נבנית", "offsets": {"start": 626, "end": 631}, "syntax": {"word": "נבנית", "dep_head_idx": -1, "dep_func": "root", "dep_head": "."}, "seg": ["נבנית"], "lex": "נבנה", "morph": {"token": "נבנית", "pos": "VERB", "feats": {"Gender": "Fem", "Number": "Sing", "Person": "3", "Tense": "Pres"}, "prefixes": [], "suffix": false}}, {"token": "פה", "offsets": {"start": 632, "end": 634}, "syntax": {"word": "פה", "dep_head_idx": 134, "dep_func": "advmod", "dep_head": "נבנית"}, "seg": ["פה"], "lex": "פה", "morph": {"token": "פה", "pos": "ADV", "feats": {}, "prefixes": [], "suffix": false}}, {"token": "עיר", "offsets": {"start": 635, "end": 638}, "syntax": {"word": "עיר", "dep_head_idx": 134, "dep_func": "nsubj", "dep_head": "נבנית"}, "seg": ["עיר"], "lex": "עיר", "morph": {"token": "עיר", "pos": "NOUN", "feats": {"Gender": "Fem", "Number": "Sing"}, "prefixes": [], "suffix": false}}, {"token": "של", "offsets": {"start": 639, "end": 641}, "syntax": {"word": "של", "dep_head_idx": 138, "dep_func": "case:gen", "dep_head": "מעלה"}, "seg": ["של"], "lex": "של", "morph": {"token": "של", "pos": "ADP", "feats": {}, "prefixes": [], "suffix": false}}, {"token": "מעלה", "offsets": {"start": 642, "end": 646}, "syntax": {"word": "מעלה", "dep_head_idx": 136, "dep_func": "nmod:poss", "dep_head": "עיר"}, "seg": ["מעלה"], "lex": "מעלה", "morph": {"token": "מעלה", "pos": "NOUN", "feats": {"Number": "Sing"}, "prefixes": [], "suffix": false}}, {"token": "בונים", "offsets": {"start": 647, "end": 652}, "syntax": {"word": "בונים", "dep_head_idx": 136, "dep_func": "acl:relcl", "dep_head": "עיר"}, "seg": ["בונים"], "lex": "בונה", "morph": {"token": "בונים", "pos": "VERB", "feats": {"Gender": "Masc", "Number": "Plur", "Person": "3", "Tense": "Pres"}, "prefixes": [], "suffix": false}}, {"token": "אותך", "offsets": {"start": 653, "end": 657}, "syntax": {"word": "אותך", "dep_head_idx": 139, "dep_func": "obj", "dep_head": "בונים"}, "seg": ["אותך"], "lex": "את", "morph": {"token": "אותך", "pos": "ADP", "feats": {}, "prefixes": [], "suffix": "PRON", "suffix_feats": {"Gender": "Masc", "Number": "Sing", "Person": "2"}}}, {"token": "לתלפיות", "offsets": {"start": 658, "end": 665}, "syntax": {"word": "לתלפיות", "dep_head_idx": 139, "dep_func": "obl", "dep_head": "בונים"}, "seg": ["ל", "תלפיות"], "lex": "לתלפיות", "morph": {"token": "לתלפיות", "pos": "PROPN", "feats": {}, "prefixes": ["ADP"], "suffix": false}}, {"token": "הפועלים", "offsets": {"start": 666, "end": 673}, "syntax": {"word": "הפועלים", "dep_head_idx": 139, "dep_func": "obl", "dep_head": "בונים"}, "seg": ["ה", "פועלים"], "lex": "הפועלים", "morph": {"token": "הפועלים", "pos": "NOUN", "feats": {"Gender": "Masc", "Number": "Plur"}, "prefixes": ["DET"], "suffix": false}}, {"token": "שברמאללה", "offsets": {"start": 674, "end": 682}, "syntax": {"word": "שברמאללה", "dep_head_idx": 142, "dep_func": "obl", "dep_head": "הפועלים"}, "seg": ["שב", "רמאללה"], "lex": "רמאללה", "morph": {"token": "שברמאללה", "pos": "PROPN", "feats": {}, "prefixes": ["SCONJ", "ADP"], "suffix": false}}, {"token": "ירושלים", "offsets": {"start": 683, "end": 690}, "syntax": {"word": "ירושלים", "dep_head_idx": 44, "dep_func": "obj", "dep_head": "ראה"}, "seg": ["ירושלים"], "lex": "ירושלים", "morph": {"token": "ירושלים", "pos": "PROPN", "feats": {}, "prefixes": [], "suffix": false}}, {"token": "הבנויה", "offsets": {"start": 691, "end": 697}, "syntax": {"word": "הבנויה", "dep_head_idx": 146, "dep_func": "acl:relcl", "dep_head": "העיר"}, "seg": ["ה", "בנויה"], "lex": "בנוי", "morph": {"token": "הבנויה", "pos": "ADJ", "feats": {"Gender": "Fem", "Number": "Sing", "Person": "3", "Tense": "Pres"}, "prefixes": [], "suffix": false}}, {"token": "העיר", "offsets": {"start": 698, "end": 702}, "syntax": {"word": "העיר", "dep_head_idx": 44, "dep_func": "obj", "dep_head": "ראה"}, "seg": ["ה", "עיר"], "lex": "עיר", "morph": {"token": "העיר", "pos": "NOUN", "feats": {"Gender": "Fem", "Number": "Sing"}, "prefixes": ["DET"], "suffix": false}}, {"token": "אשר", "offsets": {"start": 703, "end": 706}, "syntax": {"word": "אשר", "dep_head_idx": 148, "dep_func": "mark", "dep_head": "ישבה"}, "seg": ["אשר"], "lex": "אשר", "morph": {"token": "אשר", "pos": "SCONJ", "feats": {}, "prefixes": [], "suffix": false}}, {"token": "ישבה", "offsets": {"start": 707, "end": 711}, "syntax": {"word": "ישבה", "dep_head_idx": 146, "dep_func": "acl:relcl", "dep_head": "העיר"}, "seg": ["ישבה"], "lex": "ישב", "morph": {"token": "ישבה", "pos": "VERB", "feats": {"Gender": "Fem", "Number": "Sing", "Person": "3", "Tense": "Past"}, "prefixes": [], "suffix": false}}, {"token": "בדד", "offsets": {"start": 712, "end": 715}, "syntax": {"word": "בדד", "dep_head_idx": 148, "dep_func": "obl", "dep_head": "ישבה"}, "seg": ["ב", "דד"], "lex": "בדד", "morph": {"token": "בדד", "pos": "ADJ", "feats": {}, "prefixes": ["ADP"], "suffix": false}}, {"token": "על", "offsets": {"start": 716, "end": 718}, "syntax": {"word": "על", "dep_head_idx": 151, "dep_func": "case", "dep_head": "חורבנך"}, "seg": ["על"], "lex": "על", "morph": {"token": "על", "pos": "ADP", "feats": {}, "prefixes": [], "suffix": false}}, {"token": "חורבנך", "offsets": {"start": 719, "end": 725}, "syntax": {"word": "חורבנך", "dep_head_idx": 148, "dep_func": "obl", "dep_head": "ישבה"}, "seg": ["חורבנך"], "lex": "[BLANK]", "morph": {"token": "חורבנך", "pos": "NOUN", "feats": {"Gender": "Masc", "Number": "Sing"}, "prefixes": [], "suffix": "PRON", "suffix_feats": {"Gender": "Fem", "Number": "Sing", "Person": "3"}}}, {"token": "בכו", "offsets": {"start": 726, "end": 729}, "syntax": {"word": "בכו", "dep_head_idx": 44, "dep_func": "conj", "dep_head": "ראה"}, "seg": ["בכו"], "lex": "בכו", "morph": {"token": "בכו", "pos": "VERB", "feats": {"Gender": "Masc", "Number": "Plur", "Person": "3", "Tense": "Past"}, "prefixes": [], "suffix": false}}, {"token": "דורות", "offsets": {"start": 730, "end": 735}, "syntax": {"word": "דורות", "dep_head_idx": 152, "dep_func": "obl", "dep_head": "בכו"}, "seg": ["דורות"], "lex": "דור", "morph": {"token": "דורות", "pos": "NOUN", "feats": {"Gender": "Masc", "Number": "Plur"}, "prefixes": [], "suffix": false}}, {"token": "על", "offsets": {"start": 736, "end": 738}, "syntax": {"word": "על", "dep_head_idx": 151, "dep_func": "case", "dep_head": "חורבנך"}, "seg": ["על"], "lex": "על", "morph": {"token": "על", "pos": "ADP", "feats": {}, "prefixes": [], "suffix": false}}, {"token": "בניינך", "offsets": {"start": 739, "end": 745}, "syntax": {"word": "בניינך", "dep_head_idx": 152, "dep_func": "obl", "dep_head": "בכו"}, "seg": ["בניינך"], "lex": "[BLANK]", "morph": {"token": "בניינך", "pos": "NOUN", "feats": {"Gender": "Masc", "Number": "Sing"}, "prefixes": [], "suffix": "PRON", "suffix_feats": {"Gender": "Masc", "Number": "Sing", "Person": "1"}}}, {"token": "יבכו", "offsets": {"start": 746, "end": 750}, "syntax": {"word": "יבכו", "dep_head_idx": 44, "dep_func": "xcomp", "dep_head": "ראה"}, "seg": ["יבכו"], "lex": "מבכה", "morph": {"token": "יבכו", "pos": "VERB", "feats": {"Gender": "Masc", "Number": "Plur", "Person": "3", "Tense": "Fut"}, "prefixes": [], "suffix": false}}, {"token": "לעד", "offsets": {"start": 751, "end": 754}, "syntax": {"word": "לעד", "dep_head_idx": 156, "dep_func": "obl", "dep_head": "יבכו"}, "seg": ["ל", "עד"], "lex": "לעד", "morph": {"token": "לעד", "pos": "ADV", "feats": {}, "prefixes": ["ADP"], "suffix": false}}, {"token": ".", "offsets": {"start": 754, "end": 755}, "syntax": {"word": ".", "dep_head_idx": 54, "dep_func": "punct", "dep_head": "יודע"}, "seg": ["."], "lex": ".", "morph": {"token": ".", "pos": "PUNCT", "feats": {}, "prefixes": [], "suffix": false}}, {"token": "שלום", "offsets": {"start": 757, "end": 761}, "syntax": {"word": "שלום", "dep_head_idx": 44, "dep_func": "discourse", "dep_head": "ראה"}, "seg": ["שלום"], "lex": "שלום", "morph": {"token": "שלום", "pos": "INTJ", "feats": {"Gender": "Masc", "Number": "Sing"}, "prefixes": [], "suffix": false}}, {"token": "לך", "offsets": {"start": 762, "end": 764}, "syntax": {"word": "לך", "dep_head_idx": 54, "dep_func": "obl", "dep_head": "יודע"}, "seg": ["לך"], "lex": "לי", "morph": {"token": "לך", "pos": "ADP", "feats": {"Gender": "Masc", "Number": "Sing", "Person": "2"}, "prefixes": [], "suffix": "PRON", "suffix_feats": {"Gender": "Masc", "Number": "Sing", "Person": "2"}}}, {"token": "ארצי", "offsets": {"start": 765, "end": 769}, "syntax": {"word": "ארצי", "dep_head_idx": 159, "dep_func": "vocative", "dep_head": "שלום"}, "seg": ["ארצי"], "lex": "ארצי", "morph": {"token": "ארצי", "pos": "PROPN", "feats": {}, "prefixes": [], "suffix": "PRON", "suffix_feats": {"Gender": "Masc", "Number": "Sing", "Person": "1"}}}, {"token": "שלי", "offsets": {"start": 770, "end": 773}, "syntax": {"word": "שלי", "dep_head_idx": 225, "dep_func": "nmod:poss", "dep_head": "אוייבים"}, "seg": ["שלי"], "lex": "של", "morph": {"token": "שלי", "pos": "ADP", "feats": {}, "prefixes": [], "suffix": "PRON", "suffix_feats": {"Gender": "Masc", "Number": "Sing", "Person": "1"}}}, {"token": "\"", "offsets": {"start": 774, "end": 775}, "syntax": {"word": "\"", "dep_head_idx": 164, "dep_func": "punct", "dep_head": "ארץ"}, "seg": ["\""], "lex": "\"", "morph": {"token": "\"", "pos": "PUNCT", "feats": {}, "prefixes": [], "suffix": false}}, {"token": "ארץ", "offsets": {"start": 775, "end": 778}, "syntax": {"word": "ארץ", "dep_head_idx": 44, "dep_func": "obj", "dep_head": "ראה"}, "seg": ["ארץ"], "lex": "ארץ", "morph": {"token": "ארץ", "pos": "NOUN", "feats": {"Gender": "Fem", "Number": "Sing"}, "prefixes": [], "suffix": false}}, {"token": "חמדת", "offsets": {"start": 779, "end": 783}, "syntax": {"word": "חמדת", "dep_head_idx": 164, "dep_func": "compound:smixut", "dep_head": "ארץ"}, "seg": ["חמדת"], "lex": "חמדה", "morph": {"token": "חמדת", "pos": "PROPN", "feats": {"Gender": "Fem", "Number": "Sing"}, "prefixes": [], "suffix": false}}, {"token": "אבות", "offsets": {"start": 784, "end": 788}, "syntax": {"word": "אבות", "dep_head_idx": 164, "dep_func": "compound:smixut", "dep_head": "ארץ"}, "seg": ["אבות"], "lex": "אב", "morph": {"token": "אבות", "pos": "NOUN", "feats": {"Gender": "Masc", "Number": "Plur"}, "prefixes": [], "suffix": false}}, {"token": "\"", "offsets": {"start": 788, "end": 789}, "syntax": {"word": "\"", "dep_head_idx": 164, "dep_func": "punct", "dep_head": "ארץ"}, "seg": ["\""], "lex": "\"", "morph": {"token": "\"", "pos": "PUNCT", "feats": {}, "prefixes": [], "suffix": false}}, {"token": "אבי", "offsets": {"start": 790, "end": 793}, "syntax": {"word": "אבי", "dep_head_idx": 169, "dep_func": "nsubj", "dep_head": "הקריב"}, "seg": ["אבי"], "lex": "אבי", "morph": {"token": "אבי", "pos": "NOUN", "feats": {"Gender": "Masc", "Number": "Sing"}, "prefixes": [], "suffix": "PRON", "suffix_feats": {"Gender": "Masc", "Number": "Sing", "Person": "1"}}}, {"token": "הקריב", "offsets": {"start": 794, "end": 799}, "syntax": {"word": "הקריב", "dep_head_idx": 54, "dep_func": "ccomp", "dep_head": "יודע"}, "seg": ["הקריב"], "lex": "הקריב", "morph": {"token": "הקריב", "pos": "VERB", "feats": {"Gender": "Masc", "Number": "Sing", "Person": "3", "Tense": "Past"}, "prefixes": [], "suffix": false}}, {"token": "למענך", "offsets": {"start": 800, "end": 805}, "syntax": {"word": "למענך", "dep_head_idx": 148, "dep_func": "obl", "dep_head": "ישבה"}, "seg": ["ל", "מענך"], "lex": "למען", "morph": {"token": "למענך", "pos": "ADP", "feats": {"Number": "Sing"}, "prefixes": ["ADP"], "suffix": "PRON", "suffix_feats": {"Gender": "Masc", "Number": "Plur", "Person": "2"}}}, {"token": "הרבה", "offsets": {"start": 806, "end": 810}, "syntax": {"word": "הרבה", "dep_head_idx": 172, "dep_func": "det", "dep_head": "שנים"}, "seg": ["הרבה"], "lex": "הרבה", "morph": {"token": "הרבה", "pos": "DET", "feats": {}, "prefixes": [], "suffix": false}}, {"token": "שנים", "offsets": {"start": 811, "end": 815}, "syntax": {"word": "שנים", "dep_head_idx": 152, "dep_func": "obl:tmod", "dep_head": "בכו"}, "seg": ["שנים"], "lex": "שנה", "morph": {"token": "שנים", "pos": "NOUN", "feats": {"Gender": "Fem", "Number": "Plur"}, "prefixes": [], "suffix": false}}, {"token": "טובות", "offsets": {"start": 816, "end": 821}, "syntax": {"word": "טובות", "dep_head_idx": 172, "dep_func": "amod", "dep_head": "שנים"}, "seg": ["טובות"], "lex": "טוב", "morph": {"token": "טובות", "pos": "ADJ", "feats": {"Gender": "Fem", "Number": "Plur"}, "prefixes": [], "suffix": false}}, {"token": "וכך", "offsets": {"start": 823, "end": 826}, "syntax": {"word": "וכך", "dep_head_idx": 61, "dep_func": "advmod", "dep_head": "חי"}, "seg": ["ו", "כך"], "lex": "כך", "morph": {"token": "וכך", "pos": "ADV", "feats": {}, "prefixes": ["CCONJ"], "suffix": false}}, {"token": "חומסים", "offsets": {"start": 827, "end": 833}, "syntax": {"word": "חומסים", "dep_head_idx": 152, "dep_func": "advcl", "dep_head": "בכו"}, "seg": ["חומסים"], "lex": "חומס", "morph": {"token": "חומסים", "pos": "VERB", "feats": {"Gender": "Masc", "Number": "Plur", "Person": "1,2,3"}, "prefixes": [], "suffix": false}}, {"token": "הם", "offsets": {"start": 834, "end": 836}, "syntax": {"word": "הם", "dep_head_idx": 152, "dep_func": "nsubj", "dep_head": "בכו"}, "seg": ["הם"], "lex": "הוא", "morph": {"token": "הם", "pos": "PRON", "feats": {"Gender": "Masc", "Number": "Plur", "Person": "3"}, "prefixes": [], "suffix": false}}, {"token": "את", "offsets": {"start": 837, "end": 839}, "syntax": {"word": "את", "dep_head_idx": 178, "dep_func": "case:acc", "dep_head": "ארצי"}, "seg": ["את"], "lex": "את", "morph": {"token": "את", "pos": "ADP", "feats": {}, "prefixes": [], "suffix": false}}, {"token": "ארצי", "offsets": {"start": 840, "end": 844}, "syntax": {"word": "ארצי", "dep_head_idx": 152, "dep_func": "obj", "dep_head": "בכו"}, "seg": ["ארצי"], "lex": "ארצי", "morph": {"token": "ארצי", "pos": "NOUN", "feats": {"Number": "Sing"}, "prefixes": [], "suffix": "PRON", "suffix_feats": {"Gender": "Fem", "Number": "Sing", "Person": "1"}}}, {"token": "ומוצצים", "offsets": {"start": 845, "end": 852}, "syntax": {"word": "ומוצצים", "dep_head_idx": 200, "dep_func": "conj", "dep_head": "השתנינו"}, "seg": ["ו", "מוצצים"], "lex": "[BLANK]", "morph": {"token": "ומוצצים", "pos": "VERB", "feats": {"Gender": "Masc", "Number": "Plur", "Person": "3", "Tense": "Pres"}, "prefixes": ["CCONJ"], "suffix": false}}, {"token": "את", "offsets": {"start": 853, "end": 855}, "syntax": {"word": "את", "dep_head_idx": 182, "dep_func": "case:acc", "dep_head": "דמיה"}, "seg": ["את"], "lex": "את", "morph": {"token": "את", "pos": "ADP", "feats": {}, "prefixes": [], "suffix": false}}, {"token": "כל", "offsets": {"start": 856, "end": 858}, "syntax": {"word": "כל", "dep_head_idx": 182, "dep_func": "det", "dep_head": "דמיה"}, "seg": ["כל"], "lex": "כל", "morph": {"token": "כל", "pos": "DET", "feats": {}, "prefixes": [], "suffix": false}}, {"token": "דמיה", "offsets": {"start": 859, "end": 863}, "syntax": {"word": "דמיה", "dep_head_idx": 183, "dep_func": "obj", "dep_head": "אוכלים"}, "seg": ["דמיה"], "lex": "[BLANK]", "morph": {"token": "דמיה", "pos": "NOUN", "feats": {"Gender": "Masc", "Number": "Plur"}, "prefixes": [], "suffix": "PRON", "suffix_feats": {"Gender": "Fem", "Number": "Sing", "Person": "1"}}}, {"token": "אוכלים", "offsets": {"start": 864, "end": 870}, "syntax": {"word": "אוכלים", "dep_head_idx": 87, "dep_func": "ccomp", "dep_head": "לחש"}, "seg": ["אוכלים"], "lex": "אוכל", "morph": {"token": "אוכלים", "pos": "VERB", "feats": {"Gender": "Masc", "Number": "Plur", "Person": "3", "Tense": "Pres"}, "prefixes": [], "suffix": false}}, {"token": "אותה", "offsets": {"start": 871, "end": 875}, "syntax": {"word": "אותה", "dep_head_idx": 87, "dep_func": "obj", "dep_head": "לחש"}, "seg": ["אותה"], "lex": "את", "morph": {"token": "אותה", "pos": "ADP", "feats": {}, "prefixes": [], "suffix": "PRON", "suffix_feats": {"Gender": "Fem", "Number": "Sing", "Person": "3"}}}, {"token": "ועוד", "offsets": {"start": 876, "end": 880}, "syntax": {"word": "ועוד", "dep_head_idx": 178, "dep_func": "advmod", "dep_head": "ארצי"}, "seg": ["ו", "עוד"], "lex": "עוד", "morph": {"token": "ועוד", "pos": "ADV", "feats": {}, "prefixes": ["CCONJ"], "suffix": false}}, {"token": "אומרים", "offsets": {"start": 881, "end": 887}, "syntax": {"word": "אומרים", "dep_head_idx": 72, "dep_func": "conj", "dep_head": "רעבתי"}, "seg": ["אומרים"], "lex": "אומר", "morph": {"token": "אומרים", "pos": "VERB", "feats": {"Gender": "Masc", "Number": "Plur", "Person": "3", "Tense": "Pres"}, "prefixes": [], "suffix": false}}, {"token": "שהיא", "offsets": {"start": 888, "end": 892}, "syntax": {"word": "שהיא", "dep_head_idx": 188, "dep_func": "nsubj", "dep_head": "אוכלת"}, "seg": ["ש", "היא"], "lex": "הוא", "morph": {"token": "שהיא", "pos": "PRON", "feats": {"Gender": "Fem", "Number": "Sing", "Person": "3"}, "prefixes": ["SCONJ"], "suffix": false}}, {"token": "אוכלת", "offsets": {"start": 893, "end": 898}, "syntax": {"word": "אוכלת", "dep_head_idx": 87, "dep_func": "ccomp", "dep_head": "לחש"}, "seg": ["אוכלת"], "lex": "אוכל", "morph": {"token": "אוכלת", "pos": "VERB", "feats": {"Gender": "Fem", "Number": "Sing", "Person": "3", "Tense": "Pres"}, "prefixes": [], "suffix": false}}, {"token": "את", "offsets": {"start": 899, "end": 901}, "syntax": {"word": "את", "dep_head_idx": 190, "dep_func": "case:acc", "dep_head": "יושביה"}, "seg": ["את"], "lex": "את", "morph": {"token": "את", "pos": "ADP", "feats": {}, "prefixes": [], "suffix": false}}, {"token": "יושביה", "offsets": {"start": 902, "end": 908}, "syntax": {"word": "יושביה", "dep_head_idx": 188, "dep_func": "obj", "dep_head": "אוכלת"}, "seg": ["יושביה"], "lex": "יושב", "morph": {"token": "יושביה", "pos": "NOUN", "feats": {"Gender": "Masc", "Number": "Plur"}, "prefixes": [], "suffix": false}}, {"token": "מתי", "offsets": {"start": 909, "end": 912}, "syntax": {"word": "מתי", "dep_head_idx": 169, "dep_func": "advmod", "dep_head": "הקריב"}, "seg": ["מתי"], "lex": "מתי", "morph": {"token": "מתי", "pos": "ADV", "feats": {}, "prefixes": [], "suffix": false}}, {"token": ",", "offsets": {"start": 912, "end": 913}, "syntax": {"word": ",", "dep_head_idx": 196, "dep_func": "punct", "dep_head": "קרה"}, "seg": [","], "lex": ",", "morph": {"token": ",", "pos": "PUNCT", "feats": {}, "prefixes": [], "suffix": false}}, {"token": "מתי", "offsets": {"start": 914, "end": 917}, "syntax": {"word": "מתי", "dep_head_idx": 196, "dep_func": "advmod", "dep_head": "קרה"}, "seg": ["מתי"], "lex": "מתי", "morph": {"token": "מתי", "pos": "ADV", "feats": {}, "prefixes": [], "suffix": false}}, {"token": "כל", "offsets": {"start": 918, "end": 920}, "syntax": {"word": "כל", "dep_head_idx": 195, "dep_func": "det", "dep_head": "זה"}, "seg": ["כל"], "lex": "כל", "morph": {"token": "כל", "pos": "DET", "feats": {}, "prefixes": [], "suffix": false}}, {"token": "זה", "offsets": {"start": 921, "end": 923}, "syntax": {"word": "זה", "dep_head_idx": 196, "dep_func": "nsubj", "dep_head": "קרה"}, "seg": ["זה"], "lex": "זה", "morph": {"token": "זה", "pos": "PRON", "feats": {"Gender": "Masc", "Number": "Sing", "Person": "3"}, "prefixes": [], "suffix": false}}, {"token": "קרה", "offsets": {"start": 924, "end": 927}, "syntax": {"word": "קרה", "dep_head_idx": 87, "dep_func": "ccomp", "dep_head": "לחש"}, "seg": ["קרה"], "lex": "קרה", "morph": {"token": "קרה", "pos": "VERB", "feats": {"Gender": "Masc", "Number": "Sing", "Person": "3", "Tense": "Past"}, "prefixes": [], "suffix": false}}, {"token": "?", "offsets": {"start": 927, "end": 928}, "syntax": {"word": "?", "dep_head_idx": 152, "dep_func": "punct", "dep_head": "בכו"}, "seg": ["?"], "lex": "?", "morph": {"token": "?", "pos": "PUNCT", "feats": {}, "prefixes": [], "suffix": false}}, {"token": "איך", "offsets": {"start": 929, "end": 932}, "syntax": {"word": "איך", "dep_head_idx": 219, "dep_func": "advmod", "dep_head": "אבדה"}, "seg": ["איך"], "lex": "איך", "morph": {"token": "איך", "pos": "ADV", "feats": {}, "prefixes": [], "suffix": false}}, {"token": "לפתע", "offsets": {"start": 933, "end": 937}, "syntax": {"word": "לפתע", "dep_head_idx": 196, "dep_func": "advmod", "dep_head": "קרה"}, "seg": ["לפתע"], "lex": "לפתע", "morph": {"token": "לפתע", "pos": "ADV", "feats": {}, "prefixes": [], "suffix": false}}, {"token": "השתנינו", "offsets": {"start": 938, "end": 945}, "syntax": {"word": "השתנינו", "dep_head_idx": 95, "dep_func": "parataxis", "dep_head": "חזרנו"}, "seg": ["השתנינו"], "lex": "[BLANK]", "morph": {"token": "השתנינו", "pos": "VERB", "feats": {"Gender": "Masc", "Number": "Plur", "Person": "1", "Tense": "Past"}, "prefixes": [], "suffix": false}}, {"token": "?", "offsets": {"start": 945, "end": 946}, "syntax": {"word": "?", "dep_head_idx": 87, "dep_func": "punct", "dep_head": "לחש"}, "seg": ["?"], "lex": "?", "morph": {"token": "?", "pos": "PUNCT", "feats": {}, "prefixes": [], "suffix": false}}, {"token": "אבי", "offsets": {"start": 947, "end": 950}, "syntax": {"word": "אבי", "dep_head_idx": 203, "dep_func": "nsubj", "dep_head": "חלם"}, "seg": ["אבי"], "lex": "אבי", "morph": {"token": "אבי", "pos": "NOUN", "feats": {"Gender": "Masc", "Number": "Sing"}, "prefixes": [], "suffix": "PRON", "suffix_feats": {"Gender": "Masc", "Number": "Sing", "Person": "1"}}}, {"token": "חלם", "offsets": {"start": 951, "end": 954}, "syntax": {"word": "חלם", "dep_head_idx": 16, "dep_func": "parataxis", "dep_head": "אמר"}, "seg": ["חלם"], "lex": "חלם", "morph": {"token": "חלם", "pos": "VERB", "feats": {"Gender": "Masc", "Number": "Sing", "Person": "3", "Tense": "Past"}, "prefixes": [], "suffix": false}}, {"token": "חלום", "offsets": {"start": 955, "end": 959}, "syntax": {"word": "חלום", "dep_head_idx": 87, "dep_func": "obj", "dep_head": "לחש"}, "seg": ["חלום"], "lex": "חלום", "morph": {"token": "חלום", "pos": "NOUN", "feats": {"Gender": "Masc", "Number": "Sing"}, "prefixes": [], "suffix": false}}, {"token": "יפה", "offsets": {"start": 960, "end": 963}, "syntax": {"word": "יפה", "dep_head_idx": 204, "dep_func": "amod", "dep_head": "חלום"}, "seg": ["יפה"], "lex": "יפה", "morph": {"token": "יפה", "pos": "ADJ", "feats": {"Gender": "Masc", "Number": "Sing"}, "prefixes": [], "suffix": false}}, {"token": "-", "offsets": {"start": 964, "end": 965}, "syntax": {"word": "-", "dep_head_idx": 104, "dep_func": "punct", "dep_head": "יקר"}, "seg": ["-"], "lex": "-", "morph": {"token": "-", "pos": "PUNCT", "feats": {}, "prefixes": [], "suffix": false}}, {"token": "תראו", "offsets": {"start": 966, "end": 970}, "syntax": {"word": "תראו", "dep_head_idx": 87, "dep_func": "parataxis", "dep_head": "לחש"}, "seg": ["תראו"], "lex": "הראה", "morph": {"token": "תראו", "pos": "VERB", "feats": {"Gender": "Masc", "Number": "Plur", "Person": "2", "Tense": "Fut"}, "prefixes": [], "suffix": false}}, {"token": "מה", "offsets": {"start": 971, "end": 973}, "syntax": {"word": "מה", "dep_head_idx": 87, "dep_func": "obj", "dep_head": "לחש"}, "seg": ["מה"], "lex": "מה", "morph": {"token": "מה", "pos": "PRON", "feats": {}, "prefixes": [], "suffix": false}}, {"token": "התגשם", "offsets": {"start": 974, "end": 979}, "syntax": {"word": "התגשם", "dep_head_idx": 186, "dep_func": "ccomp", "dep_head": "אומרים"}, "seg": ["התגשם"], "lex": "התגשם", "morph": {"token": "התגשם", "pos": "VERB", "feats": {"Gender": "Masc", "Number": "Sing", "Person": "3", "Tense": "Past"}, "prefixes": [], "suffix": false}}, {"token": "ממנו", "offsets": {"start": 980, "end": 984}, "syntax": {"word": "ממנו", "dep_head_idx": 87, "dep_func": "obl", "dep_head": "לחש"}, "seg": ["ממנו"], "lex": "[BLANK]", "morph": {"token": "ממנו", "pos": "ADP", "feats": {}, "prefixes": [], "suffix": "PRON", "suffix_feats": {"Gender": "Masc", "Number": "Sing", "Person": "3"}}}, {"token": ".", "offsets": {"start": 984, "end": 985}, "syntax": {"word": ".", "dep_head_idx": 203, "dep_func": "punct", "dep_head": "חלם"}, "seg": ["."], "lex": ".", "morph": {"token": ".", "pos": "PUNCT", "feats": {}, "prefixes": [], "suffix": false}}, {"token": "שלום", "offsets": {"start": 987, "end": 991}, "syntax": {"word": "שלום", "dep_head_idx": 87, "dep_func": "parataxis", "dep_head": "לחש"}, "seg": ["שלום"], "lex": "שלום", "morph": {"token": "שלום", "pos": "INTJ", "feats": {"Number": "Sing"}, "prefixes": [], "suffix": false}}, {"token": "לך", "offsets": {"start": 992, "end": 994}, "syntax": {"word": "לך", "dep_head_idx": 21, "dep_func": "obl", "dep_head": "לימד"}, "seg": ["לך"], "lex": "לו", "morph": {"token": "לך", "pos": "PRON", "feats": {"Number": "Sing", "Person": "2"}, "prefixes": [], "suffix": "PRON", "suffix_feats": {"Gender": "Masc", "Number": "Sing", "Person": "2"}}}, {"token": "ארצי", "offsets": {"start": 995, "end": 999}, "syntax": {"word": "ארצי", "dep_head_idx": 87, "dep_func": "vocative", "dep_head": "לחש"}, "seg": ["ארצי"], "lex": "ארצי", "morph": {"token": "ארצי", "pos": "PROPN", "feats": {}, "prefixes": [], "suffix": "PRON", "suffix_feats": {"Number": "Sing", "Person": "1"}}}, {"token": "שלי", "offsets": {"start": 1000, "end": 1003}, "syntax": {"word": "שלי", "dep_head_idx": 111, "dep_func": "nmod:poss", "dep_head": "ספסר"}, "seg": ["שלי"], "lex": "של", "morph": {"token": "שלי", "pos": "ADP", "feats": {}, "prefixes": [], "suffix": "PRON", "suffix_feats": {"Gender": "Masc", "Number": "Sing", "Person": "1"}}}, {"token": "\"", "offsets": {"start": 1004, "end": 1005}, "syntax": {"word": "\"", "dep_head_idx": 207, "dep_func": "punct", "dep_head": "תראו"}, "seg": ["\""], "lex": "\"", "morph": {"token": "\"", "pos": "PUNCT", "feats": {}, "prefixes": [], "suffix": false}}, {"token": "עוד", "offsets": {"start": 1005, "end": 1008}, "syntax": {"word": "עוד", "dep_head_idx": 218, "dep_func": "advmod", "dep_head": "לא"}, "seg": ["עוד"], "lex": "עוד", "morph": {"token": "עוד", "pos": "ADV", "feats": {}, "prefixes": [], "suffix": false}}, {"token": "לא", "offsets": {"start": 1009, "end": 1011}, "syntax": {"word": "לא", "dep_head_idx": 115, "dep_func": "advmod", "dep_head": "אוהב"}, "seg": ["לא"], "lex": "לא", "morph": {"token": "לא", "pos": "ADV", "feats": {}, "prefixes": [], "suffix": false}}, {"token": "אבדה", "offsets": {"start": 1012, "end": 1016}, "syntax": {"word": "אבדה", "dep_head_idx": 54, "dep_func": "ccomp", "dep_head": "יודע"}, "seg": ["אבדה"], "lex": "אבדה", "morph": {"token": "אבדה", "pos": "VERB", "feats": {"Gender": "Fem", "Number": "Sing", "Person": "3", "Tense": "Past"}, "prefixes": [], "suffix": false}}, {"token": "תקוותנו", "offsets": {"start": 1017, "end": 1024}, "syntax": {"word": "תקוותנו", "dep_head_idx": 115, "dep_func": "obj", "dep_head": "אוהב"}, "seg": ["תקוותנו"], "lex": "תקווה", "morph": {"token": "תקוותנו", "pos": "NOUN", "feats": {"Gender": "Fem", "Number": "Sing"}, "prefixes": [], "suffix": "PRON", "suffix_feats": {"Number": "Plur", "Person": "1"}}}, {"token": "\"", "offsets": {"start": 1024, "end": 1025}, "syntax": {"word": "\"", "dep_head_idx": 134, "dep_func": "punct", "dep_head": "נבנית"}, "seg": ["\""], "lex": "\"", "morph": {"token": "\"", "pos": "PUNCT", "feats": {}, "prefixes": [], "suffix": false}}, {"token": "גברת", "offsets": {"start": 1026, "end": 1030}, "syntax": {"word": "גברת", "dep_head_idx": 44, "dep_func": "vocative", "dep_head": "ראה"}, "seg": ["גברת"], "lex": "גברת", "morph": {"token": "גברת", "pos": "NOUN", "feats": {"Gender": "Fem", "Number": "Sing"}, "prefixes": [], "suffix": false}}, {"token": "כבר", "offsets": {"start": 1031, "end": 1034}, "syntax": {"word": "כבר", "dep_head_idx": 222, "dep_func": "advmod", "dep_head": "גברת"}, "seg": ["כבר"], "lex": "כבר", "morph": {"token": "כבר", "pos": "ADV", "feats": {}, "prefixes": [], "suffix": false}}, {"token": "על", "offsets": {"start": 1035, "end": 1037}, "syntax": {"word": "על", "dep_head_idx": 225, "dep_func": "case", "dep_head": "אוייבים"}, "seg": ["על"], "lex": "על", "morph": {"token": "על", "pos": "ADP", "feats": {}, "prefixes": [], "suffix": false}}, {"token": "אוייבים", "offsets": {"start": 1038, "end": 1045}, "syntax": {"word": "אוייבים", "dep_head_idx": 136, "dep_func": "nmod", "dep_head": "עיר"}, "seg": ["אוייבים"], "lex": "אויב", "morph": {"token": "אוייבים", "pos": "NOUN", "feats": {"Gender": "Masc", "Number": "Plur"}, "prefixes": [], "suffix": false}}, {"token": "רבים", "offsets": {"start": 1046, "end": 1050}, "syntax": {"word": "רבים", "dep_head_idx": 225, "dep_func": "amod", "dep_head": "אוייבים"}, "seg": ["רבים"], "lex": "רב", "morph": {"token": "רבים", "pos": "ADJ", "feats": {"Gender": "Masc", "Number": "Plur"}, "prefixes": [], "suffix": false}}, {"token": ",", "offsets": {"start": 1050, "end": 1051}, "syntax": {"word": ",", "dep_head_idx": 54, "dep_func": "punct", "dep_head": "יודע"}, "seg": [","], "lex": ",", "morph": {"token": ",", "pos": "PUNCT", "feats": {}, "prefixes": [], "suffix": false}}, {"token": "וודאי", "offsets": {"start": 1052, "end": 1057}, "syntax": {"word": "וודאי", "dep_head_idx": 54, "dep_func": "advmod", "dep_head": "יודע"}, "seg": ["ו", "ודאי"], "lex": "ודאי", "morph": {"token": "וודאי", "pos": "ADV", "feats": {}, "prefixes": [], "suffix": false}}, {"token": "תתגברי", "offsets": {"start": 1058, "end": 1064}, "syntax": {"word": "תתגברי", "dep_head_idx": 54, "dep_func": "ccomp", "dep_head": "יודע"}, "seg": ["תתגברי"], "lex": "התגבר", "morph": {"token": "תתגברי", "pos": "VERB", "feats": {"Gender": "Fem", "Number": "Plur", "Person": "3", "Tense": "Fut"}, "prefixes": [], "suffix": false}}, {"token": "גם", "offsets": {"start": 1065, "end": 1067}, "syntax": {"word": "גם", "dep_head_idx": 231, "dep_func": "advmod", "dep_head": "עלינו"}, "seg": ["גם"], "lex": "גם", "morph": {"token": "גם", "pos": "ADV", "feats": {}, "prefixes": [], "suffix": false}}, {"token": "עלינו", "offsets": {"start": 1068, "end": 1073}, "syntax": {"word": "עלינו", "dep_head_idx": 123, "dep_func": "obl", "dep_head": "צורב"}, "seg": ["עלינו"], "lex": "על", "morph": {"token": "עלינו", "pos": "ADP", "feats": {}, "prefixes": [], "suffix": "PRON", "suffix_feats": {"Gender": "Masc", "Number": "Plur", "Person": "1"}}}, {"token": ".", "offsets": {"start": 1073, "end": 1074}, "syntax": {"word": ".", "dep_head_idx": 54, "dep_func": "punct", "dep_head": "יודע"}, "seg": ["."], "lex": ".", "morph": {"token": ".", "pos": "PUNCT", "feats": {}, "prefixes": [], "suffix": false}}], "root_idx": 134, "ner_entities": [{"phrase": "ירושלים", "label": "GPE", "start": 398, "end": 405, "token_start": 84, "token_end": 84}, {"phrase": "ירושלים", "label": "GPE", "start": 494, "end": 501, "token_start": 107, "token_end": 107}, {"phrase": "ירושלים", "label": "GPE", "start": 552, "end": 559, "token_start": 118, "token_end": 118}, {"phrase": "הר הצופים", "label": "LOC", "start": 610, "end": 619, "token_start": 130, "token_end": 131}, {"phrase": "שבר", "label": "GPE", "start": 674, "end": 682, "token_start": 143, "token_end": 143}, {"phrase": "ירושלים", "label": "GPE", "start": 683, "end": 690, "token_start": 144, "token_end": 144}]}
