{"text": "אבא היה אבן מתגלגלת\nוגם אחויה לא טלית של תכלת\nשומר על הגחלת עם אנרגיה מחשמלת,\nאני כאן לשבור תשמור את המפתחות נשבור תדלת\n\nהלך הקיר הלך המלט\nיו יותר מידי מחתרת תן לי למלא ת'כיס\nחמש שנים אותם הפאקינג ג'ינס\nקבל ת'אזעקה וקבל אותי מביא את המכה\nשובר קופה דופק שפגט לזכר פרינס\n\nחי מסשן לסשן גם כשכל המדינה נופשת\nשברתי את השוק, ריסקתי את המשק\nאמרתי סום סום היפתח והיקום נפתח\nנצרח על הבמה לכבוד המהפך\n\nהמהפך שלי טרי, אתמול הכל היה בצבע אפור\nהיום כולם זורקים בדיחות על איך גם זה יעבור\nאז בוא תשאל אותנו, מה גרם להיפ הופ לחזור\nותמשיך להמליך ולקבור\n\nאני כאן לשבור\nאין דבר שיעצור חביבי כלום לא יעזור\nאני כאן לשבור\nזה בוער לי בורידים וזה חרוט לי על העור\nאני כאן לשבור\nתן לזה לצאת, תן לזה לבעור\nאני כאן לשבור\nאינעל דינק העולם עושים טרור\n\nוזה מוקדש לכל רודפי החלומות אנחנו לא זרים לסבל\nשונא להיות ריאלי, ריאליזם יש כמו זבל\nלכן אני חותך ת'מציאות הזאת, פסטרמה\nלא המצאתי ת'גלגל אבל פינצ'רתי כמה\n\nכמה דרמה למה, עזוב שטויות עלינו ליגה\nשוורצע חייה, משוגע עם מאשין גאן\nהלב שלי נמצא על כל שיר, אני, גבוה על ענן\nגיטרות ניר דנן, סטריט כמו שאנן\n\nנקי ורענן, אני הורג אותם עם ליריקס\nאלוהים הוא בטח דיג'יי, החיים שלי הם רמיקס\nזה לא מייק צ'ק וואן טו - זה קוואנטום פיזיקס\nממריא מהמדבר כמו פיניקס\n\nאמרתי לשקל בתחילת הדרך, תקשיב לי ג'ונאם\nנשחק את הקלפים נכון, נצא כל אחד עם 7 דונאם\nטונה, ניתן להם מיליון סיבות לחפור\nשיהיה מי להמליך את מי לקבור", "tokens": [{"token": "אבא", "offsets": {"start": 0, "end": 3}, "syntax": {"word": "אבא", "dep_head_idx": 2, "dep_func": "nsubj", "dep_head": "אבן"}, "seg": ["אבא"], "lex": "אבא", "morph": {"token": "אבא", "pos": "PROPN", "feats": {}, "prefixes": [], "suffix": false}}, {"token": "היה", "offsets": {"start": 4, "end": 7}, "syntax": {"word": "היה", "dep_head_idx": 2, "dep_func": "cop", "dep_head": "אבן"}, "seg": ["היה"], "lex": "היי", "morph": {"token": "היה", "pos": "AUX", "feats": {"Gender": "Masc", "Number": "Sing", "Person": "3", "Tense": "Past"}, "prefixes": [], "suffix": false}}, {"token": "אבן", "offsets": {"start": 8, "end": 11}, "syntax": {"word": "אבן", "dep_head_idx": -1, "dep_func": "root", "dep_head": "לקבור"}, "seg": ["אבן"], "lex": "אבן", "morph": {"token": "אבן", "pos": "NOUN", "feats": {"Gender": "Fem", "Number": "Sing"}, "prefixes": [], "suffix": false}}, {"token": "מתגלגלת", "offsets": {"start": 12, "end": 19}, "syntax": {"word": "מתגלגלת", "dep_head_idx": 2, "dep_func": "amod", "dep_head": "אבן"}, "seg": ["מתגלגלת"], "lex": "התגלגל", "morph": {"token": "מתגלגלת", "pos": "VERB", "feats": {"Gender": "Fem", "Number": "Sing"}, "prefixes": [], "suffix": false}}, {"token": "וגם", "offsets": {"start": 20, "end": 23}, "syntax": {"word": "וגם", "dep_head_idx": 184, "dep_func": "advmod", "dep_head": "פינצ"}, "seg": ["ו", "גם"], "lex": "גם", "morph": {"token": "וגם", "pos": "ADV", "feats": {}, "prefixes": ["CCONJ"], "suffix": false}}, {"token": "אחויה", "offsets": {"start": 24, "end": 29}, "syntax": {"word": "אחויה", "dep_head_idx": 2, "dep_func": "conj", "dep_head": "אבן"}, "seg": ["אחויה"], "lex": "[BLANK]", "morph": {"token": "אחויה", "pos": "VERB", "feats": {"Gender": "Fem", "Number": "Sing", "Person": "3", "Tense": "Fut"}, "prefixes": [], "suffix": false}}, {"token": "לא", "offsets": {"start": 30, "end": 32}, "syntax": {"word": "לא", "dep_head_idx": 168, "dep_func": "advmod", "dep_head": "יש"}, "seg": ["לא"], "lex": "לא", "morph": {"token": "לא", "pos": "ADV", "feats": {}, "prefixes": [], "suffix": false}}, {"token": "טלית", "offsets": {"start": 33, "end": 37}, "syntax": {"word": "טלית", "dep_head_idx": 168, "dep_func": "nsubj", "dep_head": "יש"}, "seg": ["טלית"], "lex": "טלית", "morph": {"token": "טלית", "pos": "NOUN", "feats": {"Gender": "Fem", "Number": "Sing"}, "prefixes": [], "suffix": false}}, {"token": "של", "offsets": {"start": 38, "end": 40}, "syntax": {"word": "של", "dep_head_idx": 9, "dep_func": "case:gen", "dep_head": "תכלת"}, "seg": ["של"], "lex": "של", "morph": {"token": "של", "pos": "ADP", "feats": {}, "prefixes": [], "suffix": false}}, {"token": "תכלת", "offsets": {"start": 41, "end": 45}, "syntax": {"word": "תכלת", "dep_head_idx": 168, "dep_func": "nsubj", "dep_head": "יש"}, "seg": ["תכלת"], "lex": "תכלת", "morph": {"token": "תכלת", "pos": "NOUN", "feats": {"Gender": "Fem", "Number": "Sing"}, "prefixes": [], "suffix": false}}, {"token": "שומר", "offsets": {"start": 46, "end": 50}, "syntax": {"word": "שומר", "dep_head_idx": 72, "dep_func": "ccomp", "dep_head": "אמרתי"}, "seg": ["שומר"], "lex": "שומר", "morph": {"token": "שומר", "pos": "VERB", "feats": {"Gender": "Masc", "Number": "Sing", "Person": "3", "Tense": "Pres"}, "prefixes": [], "suffix": false}}, {"token": "על", "offsets": {"start": 51, "end": 53}, "syntax": {"word": "על", "dep_head_idx": 12, "dep_func": "case", "dep_head": "הגחלת"}, "seg": ["על"], "lex": "על", "morph": {"token": "על", "pos": "ADP", "feats": {}, "prefixes": [], "suffix": false}}, {"token": "הגחלת", "offsets": {"start": 54, "end": 59}, "syntax": {"word": "הגחלת", "dep_head_idx": 10, "dep_func": "obl", "dep_head": "שומר"}, "seg": ["ה", "גחלת"], "lex": "גחלת", "morph": {"token": "הגחלת", "pos": "NOUN", "feats": {"Gender": "Fem", "Number": "Sing"}, "prefixes": ["DET"], "suffix": false}}, {"token": "עם", "offsets": {"start": 60, "end": 62}, "syntax": {"word": "עם", "dep_head_idx": 14, "dep_func": "case", "dep_head": "אנרגיה"}, "seg": ["עם"], "lex": "עם", "morph": {"token": "עם", "pos": "ADP", "feats": {}, "prefixes": [], "suffix": false}}, {"token": "אנרגיה", "offsets": {"start": 63, "end": 69}, "syntax": {"word": "אנרגיה", "dep_head_idx": 77, "dep_func": "obl", "dep_head": "נפתח"}, "seg": ["אנרגיה"], "lex": "לאנרגיה", "morph": {"token": "אנרגיה", "pos": "NOUN", "feats": {"Gender": "Fem", "Number": "Sing"}, "prefixes": [], "suffix": false}}, {"token": "מחשמלת", "offsets": {"start": 70, "end": 76}, "syntax": {"word": "מחשמלת", "dep_head_idx": 72, "dep_func": "ccomp", "dep_head": "אמרתי"}, "seg": ["מ", "חשמלת"], "lex": "מחשמלת", "morph": {"token": "מחשמלת", "pos": "ADJ", "feats": {"Gender": "Fem", "Number": "Sing"}, "prefixes": [], "suffix": false}}, {"token": ",", "offsets": {"start": 76, "end": 77}, "syntax": {"word": ",", "dep_head_idx": 77, "dep_func": "punct", "dep_head": "נפתח"}, "seg": [","], "lex": ",", "morph": {"token": ",", "pos": "PUNCT", "feats": {}, "prefixes": [], "suffix": false}}, {"token": "אני", "offsets": {"start": 78, "end": 81}, "syntax": {"word": "אני", "dep_head_idx": 19, "dep_func": "nsubj", "dep_head": "לשבור"}, "seg": ["אני"], "lex": "אני", "morph": {"token": "אני", "pos": "PRON", "feats": {"Gender": "Masc", "Number": "Sing", "Person": "1"}, "prefixes": [], "suffix": false}}, {"token": "כאן", "offsets": {"start": 82, "end": 85}, "syntax": {"word": "כאן", "dep_head_idx": 19, "dep_func": "advmod", "dep_head": "לשבור"}, "seg": ["כאן"], "lex": "כאן", "morph": {"token": "כאן", "pos": "ADV", "feats": {}, "prefixes": [], "suffix": false}}, {"token": "לשבור", "offsets": {"start": 86, "end": 91}, "syntax": {"word": "לשבור", "dep_head_idx": 72, "dep_func": "ccomp", "dep_head": "אמרתי"}, "seg": ["לשבור"], "lex": "שבר", "morph": {"token": "לשבור", "pos": "VERB", "feats": {}, "prefixes": [], "suffix": false}}, {"token": "תשמור", "offsets": {"start": 92, "end": 97}, "syntax": {"word": "תשמור", "dep_head_idx": 72, "dep_func": "ccomp", "dep_head": "אמרתי"}, "seg": ["תשמור"], "lex": "שומר", "morph": {"token": "תשמור", "pos": "VERB", "feats": {"Gender": "Masc", "Number": "Sing", "Person": "3", "Tense": "Fut"}, "prefixes": [], "suffix": false}}, {"token": "את", "offsets": {"start": 98, "end": 100}, "syntax": {"word": "את", "dep_head_idx": 22, "dep_func": "case:acc", "dep_head": "המפתחות"}, "seg": ["את"], "lex": "את", "morph": {"token": "את", "pos": "ADP", "feats": {}, "prefixes": [], "suffix": false}}, {"token": "המפתחות", "offsets": {"start": 101, "end": 108}, "syntax": {"word": "המפתחות", "dep_head_idx": 20, "dep_func": "obj", "dep_head": "תשמור"}, "seg": ["ה", "מפתחות"], "lex": "מפתח", "morph": {"token": "המפתחות", "pos": "NOUN", "feats": {"Gender": "Masc", "Number": "Plur"}, "prefixes": ["DET"], "suffix": false}}, {"token": "נשבור", "offsets": {"start": 109, "end": 114}, "syntax": {"word": "נשבור", "dep_head_idx": 72, "dep_func": "ccomp", "dep_head": "אמרתי"}, "seg": ["נשבור"], "lex": "שברה", "morph": {"token": "נשבור", "pos": "VERB", "feats": {"Gender": "Masc", "Number": "Sing", "Person": "3", "Tense": "Fut"}, "prefixes": [], "suffix": false}}, {"token": "תדלת", "offsets": {"start": 115, "end": 119}, "syntax": {"word": "תדלת", "dep_head_idx": 72, "dep_func": "parataxis", "dep_head": "אמרתי"}, "seg": ["תדלת"], "lex": "הדליק", "morph": {"token": "תדלת", "pos": "VERB", "feats": {"Gender": "Fem", "Number": "Sing", "Person": "2", "Tense": "Fut"}, "prefixes": [], "suffix": false}}, {"token": "הלך", "offsets": {"start": 121, "end": 124}, "syntax": {"word": "הלך", "dep_head_idx": 23, "dep_func": "conj", "dep_head": "נשבור"}, "seg": ["הלך"], "lex": "הלך", "morph": {"token": "הלך", "pos": "VERB", "feats": {"Gender": "Masc", "Number": "Sing", "Person": "3"}, "prefixes": [], "suffix": false}}, {"token": "הקיר", "offsets": {"start": 125, "end": 129}, "syntax": {"word": "הקיר", "dep_head_idx": 10, "dep_func": "conj", "dep_head": "שומר"}, "seg": ["ה", "קיר"], "lex": "קיר", "morph": {"token": "הקיר", "pos": "NOUN", "feats": {"Gender": "Masc", "Number": "Sing"}, "prefixes": ["DET"], "suffix": false}}, {"token": "הלך", "offsets": {"start": 130, "end": 133}, "syntax": {"word": "הלך", "dep_head_idx": 23, "dep_func": "conj", "dep_head": "נשבור"}, "seg": ["הלך"], "lex": "הלך", "morph": {"token": "הלך", "pos": "VERB", "feats": {"Gender": "Masc", "Number": "Sing", "Person": "3", "Tense": "Past"}, "prefixes": [], "suffix": false}}, {"token": "המלט", "offsets": {"start": 134, "end": 138}, "syntax": {"word": "המלט", "dep_head_idx": 41, "dep_func": "compound:smixut", "dep_head": "הפאקינג"}, "seg": ["ה", "מלט"], "lex": "המלט", "morph": {"token": "המלט", "pos": "PROPN", "feats": {}, "prefixes": ["DET"], "suffix": false}}, {"token": "יו", "offsets": {"start": 139, "end": 141}, "syntax": {"word": "יו", "dep_head_idx": 244, "dep_func": "flat", "dep_head": "צ'"}, "seg": ["יו"], "lex": "יו", "morph": {"token": "יו", "pos": "X", "feats": {}, "prefixes": [], "suffix": false}}, {"token": "יותר", "offsets": {"start": 142, "end": 146}, "syntax": {"word": "יותר", "dep_head_idx": 32, "dep_func": "advmod", "dep_head": "מחתרת"}, "seg": ["יותר"], "lex": "יותר", "morph": {"token": "יותר", "pos": "ADV", "feats": {}, "prefixes": [], "suffix": false}}, {"token": "מידי", "offsets": {"start": 147, "end": 151}, "syntax": {"word": "מידי", "dep_head_idx": 32, "dep_func": "det", "dep_head": "מחתרת"}, "seg": ["מ", "ידי"], "lex": "מדי", "morph": {"token": "מידי", "pos": "ADV", "feats": {}, "prefixes": ["ADP"], "suffix": false}}, {"token": "מחתרת", "offsets": {"start": 152, "end": 157}, "syntax": {"word": "מחתרת", "dep_head_idx": 117, "dep_func": "nsubj", "dep_head": "אין"}, "seg": ["מחתרת"], "lex": "מחתרת", "morph": {"token": "מחתרת", "pos": "NOUN", "feats": {"Gender": "Fem", "Number": "Sing"}, "prefixes": [], "suffix": false}}, {"token": "תן", "offsets": {"start": 158, "end": 160}, "syntax": {"word": "תן", "dep_head_idx": 2, "dep_func": "parataxis", "dep_head": "אבן"}, "seg": ["תן"], "lex": "תן", "morph": {"token": "תן", "pos": "VERB", "feats": {"Gender": "Masc", "Number": "Sing", "Person": "2", "Tense": "Imp"}, "prefixes": [], "suffix": false}}, {"token": "לי", "offsets": {"start": 161, "end": 163}, "syntax": {"word": "לי", "dep_head_idx": 33, "dep_func": "obl", "dep_head": "תן"}, "seg": ["לי"], "lex": "לי", "morph": {"token": "לי", "pos": "PRON", "feats": {"Gender": "Masc", "Number": "Sing", "Person": "1"}, "prefixes": ["ADP"], "suffix": false}}, {"token": "למלא", "offsets": {"start": 164, "end": 168}, "syntax": {"word": "למלא", "dep_head_idx": 256, "dep_func": "ccomp", "dep_head": "אמרתי"}, "seg": ["למלא"], "lex": "מילא", "morph": {"token": "למלא", "pos": "VERB", "feats": {}, "prefixes": [], "suffix": false}}, {"token": "ת'", "offsets": {"start": 169, "end": 171}, "syntax": {"word": "ת'", "dep_head_idx": 35, "dep_func": "obj", "dep_head": "למלא"}, "seg": ["ת'"], "lex": "ת'", "morph": {"token": "ת'", "pos": "X", "feats": {"Gender": "Masc"}, "prefixes": [], "suffix": false}}, {"token": "כיס", "offsets": {"start": 171, "end": 174}, "syntax": {"word": "כיס", "dep_head_idx": 35, "dep_func": "obj", "dep_head": "למלא"}, "seg": ["כיס"], "lex": "כיס", "morph": {"token": "כיס", "pos": "NOUN", "feats": {"Gender": "Masc", "Number": "Sing"}, "prefixes": [], "suffix": false}}, {"token": "חמש", "offsets": {"start": 175, "end": 178}, "syntax": {"word": "חמש", "dep_head_idx": 39, "dep_func": "nummod", "dep_head": "שנים"}, "seg": ["חמש"], "lex": "חמישה", "morph": {"token": "חמש", "pos": "NUM", "feats": {"Gender": "Fem"}, "prefixes": [], "suffix": false}}, {"token": "שנים", "offsets": {"start": 179, "end": 183}, "syntax": {"word": "שנים", "dep_head_idx": 35, "dep_func": "obl:tmod", "dep_head": "למלא"}, "seg": ["שנים"], "lex": "שנה", "morph": {"token": "שנים", "pos": "NOUN", "feats": {"Gender": "Fem", "Number": "Plur"}, "prefixes": [], "suffix": false}}, {"token": "אותם", "offsets": {"start": 184, "end": 188}, "syntax": {"word": "אותם", "dep_head_idx": 128, "dep_func": "obj", "dep_head": "בוער"}, "seg": ["אותם"], "lex": "את", "morph": {"token": "אותם", "pos": "ADP", "feats": {}, "prefixes": [], "suffix": "PRON", "suffix_feats": {"Gender": "Masc", "Number": "Plur", "Person": "3"}}}, {"token": "הפאקינג", "offsets": {"start": 189, "end": 196}, "syntax": {"word": "הפאקינג", "dep_head_idx": 265, "dep_func": "nsubj", "dep_head": "נשחק"}, "seg": ["ה", "פאקינג"], "lex": "[BLANK]", "morph": {"token": "הפאקינג", "pos": "NOUN", "feats": {"Gender": "Masc", "Number": "Sing"}, "prefixes": ["DET"], "suffix": false}}, {"token": "ג'", "offsets": {"start": 197, "end": 199}, "syntax": {"word": "ג'", "dep_head_idx": 41, "dep_func": "appos", "dep_head": "הפאקינג"}, "seg": ["ג'"], "lex": "[BLANK]", "morph": {"token": "ג'", "pos": "PROPN", "feats": {}, "prefixes": [], "suffix": false}}, {"token": "ינס", "offsets": {"start": 199, "end": 202}, "syntax": {"word": "ינס", "dep_head_idx": 42, "dep_func": "flat", "dep_head": "ג'"}, "seg": ["ינס"], "lex": "ינס", "morph": {"token": "ינס", "pos": "PROPN", "feats": {}, "prefixes": [], "suffix": false}}, {"token": "קבל", "offsets": {"start": 203, "end": 206}, "syntax": {"word": "קבל", "dep_head_idx": 41, "dep_func": "conj", "dep_head": "הפאקינג"}, "seg": ["קבל"], "lex": "קיבל", "morph": {"token": "קבל", "pos": "VERB", "feats": {"Gender": "Masc", "Number": "Sing", "Person": "2", "Tense": "Past"}, "prefixes": [], "suffix": false}}, {"token": "ת'", "offsets": {"start": 207, "end": 209}, "syntax": {"word": "ת'", "dep_head_idx": 148, "dep_func": "obj", "dep_head": "לשבור"}, "seg": ["ת'"], "lex": "ת'", "morph": {"token": "ת'", "pos": "X", "feats": {"Gender": "Masc", "Number": "Sing"}, "prefixes": [], "suffix": false}}, {"token": "אזעקה", "offsets": {"start": 209, "end": 214}, "syntax": {"word": "אזעקה", "dep_head_idx": 42, "dep_func": "flat", "dep_head": "ג'"}, "seg": ["אזעקה"], "lex": "אזעקה", "morph": {"token": "אזעקה", "pos": "NOUN", "feats": {"Gender": "Fem", "Number": "Sing"}, "prefixes": [], "suffix": false}}, {"token": "וקבל", "offsets": {"start": 215, "end": 219}, "syntax": {"word": "וקבל", "dep_head_idx": 256, "dep_func": "conj", "dep_head": "אמרתי"}, "seg": ["ו", "קבל"], "lex": "קיבל", "morph": {"token": "וקבל", "pos": "VERB", "feats": {"Gender": "Masc", "Number": "Sing", "Person": "2", "Tense": "Past"}, "prefixes": ["CCONJ"], "suffix": false}}, {"token": "אותי", "offsets": {"start": 220, "end": 224}, "syntax": {"word": "אותי", "dep_head_idx": 47, "dep_func": "obj", "dep_head": "וקבל"}, "seg": ["אותי"], "lex": "את", "morph": {"token": "אותי", "pos": "ADP", "feats": {}, "prefixes": [], "suffix": "PRON", "suffix_feats": {"Gender": "Masc", "Number": "Sing", "Person": "1"}}}, {"token": "מביא", "offsets": {"start": 225, "end": 229}, "syntax": {"word": "מביא", "dep_head_idx": 256, "dep_func": "ccomp", "dep_head": "אמרתי"}, "seg": ["מביא"], "lex": "מביא", "morph": {"token": "מביא", "pos": "VERB", "feats": {"Gender": "Masc", "Number": "Sing", "Person": "3", "Tense": "Pres"}, "prefixes": [], "suffix": false}}, {"token": "את", "offsets": {"start": 230, "end": 232}, "syntax": {"word": "את", "dep_head_idx": 51, "dep_func": "case:acc", "dep_head": "המכה"}, "seg": ["את"], "lex": "את", "morph": {"token": "את", "pos": "ADP", "feats": {}, "prefixes": [], "suffix": false}}, {"token": "המכה", "offsets": {"start": 233, "end": 237}, "syntax": {"word": "המכה", "dep_head_idx": 47, "dep_func": "obj", "dep_head": "וקבל"}, "seg": ["ה", "מכה"], "lex": "מכה", "morph": {"token": "המכה", "pos": "NOUN", "feats": {"Gender": "Fem", "Number": "Sing"}, "prefixes": ["DET"], "suffix": false}}, {"token": "שובר", "offsets": {"start": 238, "end": 242}, "syntax": {"word": "שובר", "dep_head_idx": 51, "dep_func": "acl", "dep_head": "המכה"}, "seg": ["שובר"], "lex": "שובר", "morph": {"token": "שובר", "pos": "VERB", "feats": {"Gender": "Masc", "Number": "Sing", "Person": "2", "Tense": "Pres"}, "prefixes": [], "suffix": false}}, {"token": "קופה", "offsets": {"start": 243, "end": 247}, "syntax": {"word": "קופה", "dep_head_idx": 52, "dep_func": "compound:smixut", "dep_head": "שובר"}, "seg": ["קופה"], "lex": "קופה", "morph": {"token": "קופה", "pos": "NOUN", "feats": {"Gender": "Masc", "Number": "Sing"}, "prefixes": [], "suffix": false}}, {"token": "דופק", "offsets": {"start": 248, "end": 252}, "syntax": {"word": "דופק", "dep_head_idx": 52, "dep_func": "obj", "dep_head": "שובר"}, "seg": ["דופק"], "lex": "דופק", "morph": {"token": "דופק", "pos": "NOUN", "feats": {"Gender": "Masc", "Number": "Sing"}, "prefixes": [], "suffix": false}}, {"token": "שפגט", "offsets": {"start": 253, "end": 257}, "syntax": {"word": "שפגט", "dep_head_idx": 52, "dep_func": "parataxis", "dep_head": "שובר"}, "seg": ["ש", "פגט"], "lex": "[BLANK]", "morph": {"token": "שפגט", "pos": "VERB", "feats": {"Gender": "Masc", "Number": "Sing", "Person": "3"}, "prefixes": [], "suffix": false}}, {"token": "לזכר", "offsets": {"start": 258, "end": 262}, "syntax": {"word": "לזכר", "dep_head_idx": 52, "dep_func": "obl", "dep_head": "שובר"}, "seg": ["ל", "זכר"], "lex": "זכר", "morph": {"token": "לזכר", "pos": "NOUN", "feats": {"Gender": "Masc", "Number": "Sing"}, "prefixes": ["ADP"], "suffix": false}}, {"token": "פרינס", "offsets": {"start": 263, "end": 268}, "syntax": {"word": "פרינס", "dep_head_idx": 56, "dep_func": "compound:smixut", "dep_head": "לזכר"}, "seg": ["פרינס"], "lex": "פרינס", "morph": {"token": "פרינס", "pos": "PROPN", "feats": {}, "prefixes": [], "suffix": false}}, {"token": "חי", "offsets": {"start": 270, "end": 272}, "syntax": {"word": "חי", "dep_head_idx": 57, "dep_func": "flat", "dep_head": "פרינס"}, "seg": ["חי"], "lex": "חי", "morph": {"token": "חי", "pos": "PROPN", "feats": {"Gender": "Masc", "Number": "Sing", "Tense": "Pres"}, "prefixes": [], "suffix": false}}, {"token": "מסשן", "offsets": {"start": 273, "end": 277}, "syntax": {"word": "מסשן", "dep_head_idx": 274, "dep_func": "nmod", "dep_head": "7"}, "seg": ["מ", "סשן"], "lex": "מוצ\"ש", "morph": {"token": "מסשן", "pos": "PROPN", "feats": {}, "prefixes": ["ADP"], "suffix": false}}, {"token": "לסשן", "offsets": {"start": 278, "end": 282}, "syntax": {"word": "לסשן", "dep_head_idx": 168, "dep_func": "obl", "dep_head": "יש"}, "seg": ["ל", "סשן"], "lex": "אולפן", "morph": {"token": "לסשן", "pos": "NOUN", "feats": {"Gender": "Masc", "Number": "Sing"}, "prefixes": ["DET", "ADP"], "suffix": false}}, {"token": "גם", "offsets": {"start": 283, "end": 285}, "syntax": {"word": "גם", "dep_head_idx": 168, "dep_func": "advmod", "dep_head": "יש"}, "seg": ["גם"], "lex": "גם", "morph": {"token": "גם", "pos": "ADV", "feats": {}, "prefixes": [], "suffix": false}}, {"token": "כשכל", "offsets": {"start": 286, "end": 290}, "syntax": {"word": "כשכל", "dep_head_idx": 63, "dep_func": "det", "dep_head": "המדינה"}, "seg": ["כש", "כל"], "lex": "כול", "morph": {"token": "כשכל", "pos": "DET", "feats": {}, "prefixes": [], "suffix": false}}, {"token": "המדינה", "offsets": {"start": 291, "end": 297}, "syntax": {"word": "המדינה", "dep_head_idx": 168, "dep_func": "nsubj", "dep_head": "יש"}, "seg": ["ה", "מדינה"], "lex": "מדינה", "morph": {"token": "המדינה", "pos": "NOUN", "feats": {"Gender": "Fem", "Number": "Sing"}, "prefixes": ["DET"], "suffix": false}}, {"token": "נופשת", "offsets": {"start": 298, "end": 303}, "syntax": {"word": "נופשת", "dep_head_idx": 2, "dep_func": "parataxis", "dep_head": "אבן"}, "seg": ["נופשת"], "lex": "נופש", "morph": {"token": "נופשת", "pos": "VERB", "feats": {"Gender": "Fem", "Number": "Sing", "Person": "3", "Tense": "Pres"}, "prefixes": [], "suffix": false}}, {"token": "שברתי", "offsets": {"start": 304, "end": 309}, "syntax": {"word": "שברתי", "dep_head_idx": 2, "dep_func": "parataxis", "dep_head": "אבן"}, "seg": ["שברתי"], "lex": "שבר", "morph": {"token": "שברתי", "pos": "VERB", "feats": {"Gender": "Masc", "Number": "Sing", "Person": "1", "Tense": "Past"}, "prefixes": [], "suffix": false}}, {"token": "את", "offsets": {"start": 310, "end": 312}, "syntax": {"word": "את", "dep_head_idx": 287, "dep_func": "case:acc", "dep_head": "מי"}, "seg": ["את"], "lex": "את", "morph": {"token": "את", "pos": "ADP", "feats": {}, "prefixes": [], "suffix": false}}, {"token": "השוק", "offsets": {"start": 313, "end": 317}, "syntax": {"word": "השוק", "dep_head_idx": 285, "dep_func": "obj", "dep_head": "להמליך"}, "seg": ["ה", "שוק"], "lex": "שוק", "morph": {"token": "השוק", "pos": "NOUN", "feats": {"Gender": "Masc", "Number": "Sing"}, "prefixes": ["DET"], "suffix": false}}, {"token": ",", "offsets": {"start": 317, "end": 318}, "syntax": {"word": ",", "dep_head_idx": 168, "dep_func": "punct", "dep_head": "יש"}, "seg": [","], "lex": ",", "morph": {"token": ",", "pos": "PUNCT", "feats": {}, "prefixes": [], "suffix": false}}, {"token": "ריסקתי", "offsets": {"start": 319, "end": 325}, "syntax": {"word": "ריסקתי", "dep_head_idx": 72, "dep_func": "ccomp", "dep_head": "אמרתי"}, "seg": ["ריסקתי"], "lex": "ריסק", "morph": {"token": "ריסקתי", "pos": "VERB", "feats": {"Gender": "Masc", "Number": "Sing", "Person": "3", "Tense": "Past"}, "prefixes": [], "suffix": false}}, {"token": "את", "offsets": {"start": 326, "end": 328}, "syntax": {"word": "את", "dep_head_idx": 71, "dep_func": "case:acc", "dep_head": "המשק"}, "seg": ["את"], "lex": "את", "morph": {"token": "את", "pos": "ADP", "feats": {}, "prefixes": [], "suffix": false}}, {"token": "המשק", "offsets": {"start": 329, "end": 333}, "syntax": {"word": "המשק", "dep_head_idx": 168, "dep_func": "obj", "dep_head": "יש"}, "seg": ["ה", "משק"], "lex": "משק", "morph": {"token": "המשק", "pos": "NOUN", "feats": {"Gender": "Masc", "Number": "Sing"}, "prefixes": ["DET"], "suffix": false}}, {"token": "אמרתי", "offsets": {"start": 334, "end": 339}, "syntax": {"word": "אמרתי", "dep_head_idx": 2, "dep_func": "parataxis", "dep_head": "אבן"}, "seg": ["אמרתי"], "lex": "אמר", "morph": {"token": "אמרתי", "pos": "VERB", "feats": {"Gender": "Masc", "Number": "Sing", "Person": "1", "Tense": "Past"}, "prefixes": [], "suffix": false}}, {"token": "סום", "offsets": {"start": 340, "end": 343}, "syntax": {"word": "סום", "dep_head_idx": 168, "dep_func": "nsubj", "dep_head": "יש"}, "seg": ["סום"], "lex": "סו", "morph": {"token": "סום", "pos": "PROPN", "feats": {}, "prefixes": [], "suffix": false}}, {"token": "סום", "offsets": {"start": 344, "end": 347}, "syntax": {"word": "סום", "dep_head_idx": 274, "dep_func": "flat", "dep_head": "7"}, "seg": ["סום"], "lex": "סו", "morph": {"token": "סום", "pos": "PROPN", "feats": {}, "prefixes": [], "suffix": false}}, {"token": "היפתח", "offsets": {"start": 348, "end": 353}, "syntax": {"word": "היפתח", "dep_head_idx": 72, "dep_func": "ccomp", "dep_head": "אמרתי"}, "seg": ["היפתח"], "lex": "הופ", "morph": {"token": "היפתח", "pos": "VERB", "feats": {"Gender": "Masc", "Number": "Sing", "Person": "3"}, "prefixes": [], "suffix": false}}, {"token": "והיקום", "offsets": {"start": 354, "end": 360}, "syntax": {"word": "והיקום", "dep_head_idx": 77, "dep_func": "nsubj", "dep_head": "נפתח"}, "seg": ["וה", "יקום"], "lex": "יקום", "morph": {"token": "והיקום", "pos": "NOUN", "feats": {"Gender": "Masc", "Number": "Sing"}, "prefixes": ["DET", "CCONJ"], "suffix": false}}, {"token": "נפתח", "offsets": {"start": 361, "end": 365}, "syntax": {"word": "נפתח", "dep_head_idx": 72, "dep_func": "conj", "dep_head": "אמרתי"}, "seg": ["נפתח"], "lex": "נפתח", "morph": {"token": "נפתח", "pos": "VERB", "feats": {"Gender": "Masc", "Number": "Sing", "Person": "3", "Tense": "Past"}, "prefixes": [], "suffix": false}}, {"token": "נצרח", "offsets": {"start": 366, "end": 370}, "syntax": {"word": "נצרח", "dep_head_idx": 72, "dep_func": "ccomp", "dep_head": "אמרתי"}, "seg": ["נצרח"], "lex": "[BLANK]", "morph": {"token": "נצרח", "pos": "VERB", "feats": {"Gender": "Masc", "Number": "Sing", "Person": "1", "Tense": "Fut"}, "prefixes": [], "suffix": false}}, {"token": "על", "offsets": {"start": 371, "end": 373}, "syntax": {"word": "על", "dep_head_idx": 80, "dep_func": "case", "dep_head": "הבמה"}, "seg": ["על"], "lex": "על", "morph": {"token": "על", "pos": "ADP", "feats": {}, "prefixes": [], "suffix": false}}, {"token": "הבמה", "offsets": {"start": 374, "end": 378}, "syntax": {"word": "הבמה", "dep_head_idx": 77, "dep_func": "obl", "dep_head": "נפתח"}, "seg": ["ה", "במה"], "lex": "במה", "morph": {"token": "הבמה", "pos": "NOUN", "feats": {"Gender": "Fem", "Number": "Sing"}, "prefixes": ["DET"], "suffix": false}}, {"token": "לכבוד", "offsets": {"start": 379, "end": 384}, "syntax": {"word": "לכבוד", "dep_head_idx": 82, "dep_func": "case", "dep_head": "המהפך"}, "seg": ["ל", "כבוד"], "lex": "לכבוד", "morph": {"token": "לכבוד", "pos": "ADP", "feats": {}, "prefixes": [], "suffix": false}}, {"token": "המהפך", "offsets": {"start": 385, "end": 390}, "syntax": {"word": "המהפך", "dep_head_idx": 72, "dep_func": "obl", "dep_head": "אמרתי"}, "seg": ["ה", "מהפך"], "lex": "מהפך", "morph": {"token": "המהפך", "pos": "NOUN", "feats": {"Gender": "Masc", "Number": "Sing"}, "prefixes": ["DET"], "suffix": false}}, {"token": "המהפך", "offsets": {"start": 392, "end": 397}, "syntax": {"word": "המהפך", "dep_head_idx": 100, "dep_func": "nsubj", "dep_head": "יעבור"}, "seg": ["ה", "מהפך"], "lex": "מהפך", "morph": {"token": "המהפך", "pos": "NOUN", "feats": {"Gender": "Masc", "Number": "Sing"}, "prefixes": ["DET"], "suffix": false}}, {"token": "שלי", "offsets": {"start": 398, "end": 401}, "syntax": {"word": "שלי", "dep_head_idx": 83, "dep_func": "nmod:poss", "dep_head": "המהפך"}, "seg": ["שלי"], "lex": "של", "morph": {"token": "שלי", "pos": "ADP", "feats": {}, "prefixes": [], "suffix": "PRON", "suffix_feats": {"Gender": "Masc", "Number": "Sing", "Person": "1"}}}, {"token": "טרי", "offsets": {"start": 402, "end": 405}, "syntax": {"word": "טרי", "dep_head_idx": 72, "dep_func": "obj", "dep_head": "אמרתי"}, "seg": ["טרי"], "lex": "טרי", "morph": {"token": "טרי", "pos": "PROPN", "feats": {}, "prefixes": [], "suffix": false}}, {"token": ",", "offsets": {"start": 405, "end": 406}, "syntax": {"word": ",", "dep_head_idx": 72, "dep_func": "punct", "dep_head": "אמרתי"}, "seg": [","], "lex": ",", "morph": {"token": ",", "pos": "PUNCT", "feats": {}, "prefixes": [], "suffix": false}}, {"token": "אתמול", "offsets": {"start": 407, "end": 412}, "syntax": {"word": "אתמול", "dep_head_idx": 205, "dep_func": "advmod", "dep_head": "נמצא"}, "seg": ["אתמול"], "lex": "אתמול", "morph": {"token": "אתמול", "pos": "ADV", "feats": {}, "prefixes": [], "suffix": false}}, {"token": "הכל", "offsets": {"start": 413, "end": 416}, "syntax": {"word": "הכל", "dep_head_idx": 205, "dep_func": "nsubj", "dep_head": "נמצא"}, "seg": ["ה", "כל"], "lex": "כול", "morph": {"token": "הכל", "pos": "DET", "feats": {}, "prefixes": [], "suffix": false}}, {"token": "היה", "offsets": {"start": 417, "end": 420}, "syntax": {"word": "היה", "dep_head_idx": 94, "dep_func": "cop", "dep_head": "זורקים"}, "seg": ["היה"], "lex": "היי", "morph": {"token": "היה", "pos": "AUX", "feats": {"Gender": "Masc", "Number": "Sing", "Person": "3", "Tense": "Past"}, "prefixes": [], "suffix": false}}, {"token": "בצבע", "offsets": {"start": 421, "end": 425}, "syntax": {"word": "בצבע", "dep_head_idx": 10, "dep_func": "obl", "dep_head": "שומר"}, "seg": ["ב", "צבע"], "lex": "צבע", "morph": {"token": "בצבע", "pos": "NOUN", "feats": {"Gender": "Masc", "Number": "Sing"}, "prefixes": ["ADP"], "suffix": false}}, {"token": "אפור", "offsets": {"start": 426, "end": 430}, "syntax": {"word": "אפור", "dep_head_idx": 90, "dep_func": "amod", "dep_head": "בצבע"}, "seg": ["אפור"], "lex": "אפור", "morph": {"token": "אפור", "pos": "ADJ", "feats": {"Gender": "Masc", "Number": "Sing"}, "prefixes": [], "suffix": false}}, {"token": "היום", "offsets": {"start": 431, "end": 435}, "syntax": {"word": "היום", "dep_head_idx": 205, "dep_func": "advmod", "dep_head": "נמצא"}, "seg": ["ה", "יום"], "lex": "יום", "morph": {"token": "היום", "pos": "ADV", "feats": {}, "prefixes": ["DET"], "suffix": false}}, {"token": "כולם", "offsets": {"start": 436, "end": 440}, "syntax": {"word": "כולם", "dep_head_idx": 192, "dep_func": "nsubj", "dep_head": "עזוב"}, "seg": ["כולם"], "lex": "כול", "morph": {"token": "כולם", "pos": "DET", "feats": {}, "prefixes": [], "suffix": "PRON", "suffix_feats": {"Gender": "Masc", "Number": "Plur", "Person": "3"}}}, {"token": "זורקים", "offsets": {"start": 441, "end": 447}, "syntax": {"word": "זורקים", "dep_head_idx": 72, "dep_func": "parataxis", "dep_head": "אמרתי"}, "seg": ["זורקים"], "lex": "זורק", "morph": {"token": "זורקים", "pos": "VERB", "feats": {"Gender": "Masc", "Number": "Plur", "Person": "3", "Tense": "Pres"}, "prefixes": [], "suffix": false}}, {"token": "בדיחות", "offsets": {"start": 448, "end": 454}, "syntax": {"word": "בדיחות", "dep_head_idx": 94, "dep_func": "obj", "dep_head": "זורקים"}, "seg": ["בדיחות"], "lex": "בדיחה", "morph": {"token": "בדיחות", "pos": "NOUN", "feats": {"Gender": "Fem", "Number": "Plur"}, "prefixes": [], "suffix": false}}, {"token": "על", "offsets": {"start": 455, "end": 457}, "syntax": {"word": "על", "dep_head_idx": 97, "dep_func": "case", "dep_head": "איך"}, "seg": ["על"], "lex": "על", "morph": {"token": "על", "pos": "ADP", "feats": {}, "prefixes": [], "suffix": false}}, {"token": "איך", "offsets": {"start": 458, "end": 461}, "syntax": {"word": "איך", "dep_head_idx": 205, "dep_func": "advmod", "dep_head": "נמצא"}, "seg": ["איך"], "lex": "איך", "morph": {"token": "איך", "pos": "ADV", "feats": {}, "prefixes": [], "suffix": false}}, {"token": "גם", "offsets": {"start": 462, "end": 464}, "syntax": {"word": "גם", "dep_head_idx": 99, "dep_func": "advmod", "dep_head": "זה"}, "seg": ["גם"], "lex": "גם", "morph": {"token": "גם", "pos": "ADV", "feats": {}, "prefixes": [], "suffix": false}}, {"token": "זה", "offsets": {"start": 465, "end": 467}, "syntax": {"word": "זה", "dep_head_idx": 100, "dep_func": "nsubj", "dep_head": "יעבור"}, "seg": ["זה"], "lex": "זה", "morph": {"token": "זה", "pos": "PRON", "feats": {"Gender": "Masc", "Number": "Sing", "Person": "3"}, "prefixes": [], "suffix": false}}, {"token": "יעבור", "offsets": {"start": 468, "end": 473}, "syntax": {"word": "יעבור", "dep_head_idx": 72, "dep_func": "ccomp", "dep_head": "אמרתי"}, "seg": ["יעבור"], "lex": "יעבור", "morph": {"token": "יעבור", "pos": "VERB", "feats": {"Gender": "Masc", "Number": "Sing", "Person": "3", "Tense": "Fut"}, "prefixes": [], "suffix": false}}, {"token": "אז", "offsets": {"start": 474, "end": 476}, "syntax": {"word": "אז", "dep_head_idx": 205, "dep_func": "advmod", "dep_head": "נמצא"}, "seg": ["אז"], "lex": "אז", "morph": {"token": "אז", "pos": "ADV", "feats": {}, "prefixes": [], "suffix": false}}, {"token": "בוא", "offsets": {"start": 477, "end": 480}, "syntax": {"word": "בוא", "dep_head_idx": 256, "dep_func": "parataxis", "dep_head": "אמרתי"}, "seg": ["בוא"], "lex": "בוא", "morph": {"token": "בוא", "pos": "VERB", "feats": {"Gender": "Masc", "Number": "Sing", "Person": "2", "Tense": "Imp"}, "prefixes": [], "suffix": false}}, {"token": "תשאל", "offsets": {"start": 481, "end": 485}, "syntax": {"word": "תשאל", "dep_head_idx": 72, "dep_func": "ccomp", "dep_head": "אמרתי"}, "seg": ["תשאל"], "lex": "תשאל", "morph": {"token": "תשאל", "pos": "VERB", "feats": {"Gender": "Masc", "Number": "Sing", "Person": "3", "Tense": "Fut"}, "prefixes": [], "suffix": false}}, {"token": "אותנו", "offsets": {"start": 486, "end": 491}, "syntax": {"word": "אותנו", "dep_head_idx": 103, "dep_func": "obj", "dep_head": "תשאל"}, "seg": ["אותנו"], "lex": "את", "morph": {"token": "אותנו", "pos": "ADP", "feats": {}, "prefixes": [], "suffix": "PRON", "suffix_feats": {"Gender": "Masc", "Number": "Plur", "Person": "1"}}}, {"token": ",", "offsets": {"start": 491, "end": 492}, "syntax": {"word": ",", "dep_head_idx": 107, "dep_func": "punct", "dep_head": "גרם"}, "seg": [","], "lex": ",", "morph": {"token": ",", "pos": "PUNCT", "feats": {}, "prefixes": [], "suffix": false}}, {"token": "מה", "offsets": {"start": 493, "end": 495}, "syntax": {"word": "מה", "dep_head_idx": 205, "dep_func": "obj", "dep_head": "נמצא"}, "seg": ["מה"], "lex": "מה", "morph": {"token": "מה", "pos": "PRON", "feats": {}, "prefixes": [], "suffix": false}}, {"token": "גרם", "offsets": {"start": 496, "end": 499}, "syntax": {"word": "גרם", "dep_head_idx": 97, "dep_func": "acl:relcl", "dep_head": "איך"}, "seg": ["גרם"], "lex": "גרם", "morph": {"token": "גרם", "pos": "VERB", "feats": {"Gender": "Masc", "Number": "Sing", "Person": "3", "Tense": "Past"}, "prefixes": [], "suffix": false}}, {"token": "להיפ", "offsets": {"start": 500, "end": 504}, "syntax": {"word": "להיפ", "dep_head_idx": 189, "dep_func": "nmod", "dep_head": "דרמה"}, "seg": ["להיפ"], "lex": "להיפ", "morph": {"token": "להיפ", "pos": "PROPN", "feats": {}, "prefixes": ["ADP"], "suffix": false}}, {"token": "הופ", "offsets": {"start": 505, "end": 508}, "syntax": {"word": "הופ", "dep_head_idx": 108, "dep_func": "flat", "dep_head": "להיפ"}, "seg": ["הופ"], "lex": "הופ", "morph": {"token": "הופ", "pos": "X", "feats": {}, "prefixes": [], "suffix": false}}, {"token": "לחזור", "offsets": {"start": 509, "end": 514}, "syntax": {"word": "לחזור", "dep_head_idx": 107, "dep_func": "xcomp", "dep_head": "גרם"}, "seg": ["לחזור"], "lex": "חזר", "morph": {"token": "לחזור", "pos": "VERB", "feats": {}, "prefixes": [], "suffix": false}}, {"token": "ותמשיך", "offsets": {"start": 515, "end": 521}, "syntax": {"word": "ותמשיך", "dep_head_idx": 27, "dep_func": "conj", "dep_head": "הלך"}, "seg": ["ו", "תמשיך"], "lex": "המשיך", "morph": {"token": "ותמשיך", "pos": "VERB", "feats": {"Gender": "Fem", "Number": "Sing", "Person": "3", "Tense": "Fut"}, "prefixes": ["CCONJ"], "suffix": false}}, {"token": "להמליך", "offsets": {"start": 522, "end": 528}, "syntax": {"word": "להמליך", "dep_head_idx": 107, "dep_func": "xcomp", "dep_head": "גרם"}, "seg": ["להמליך"], "lex": "להמליך", "morph": {"token": "להמליך", "pos": "VERB", "feats": {}, "prefixes": [], "suffix": false}}, {"token": "ולקבור", "offsets": {"start": 529, "end": 535}, "syntax": {"word": "ולקבור", "dep_head_idx": 128, "dep_func": "conj", "dep_head": "בוער"}, "seg": ["ו", "לקבור"], "lex": "קבר", "morph": {"token": "ולקבור", "pos": "VERB", "feats": {}, "prefixes": ["CCONJ"], "suffix": false}}, {"token": "אני", "offsets": {"start": 537, "end": 540}, "syntax": {"word": "אני", "dep_head_idx": 128, "dep_func": "nsubj", "dep_head": "בוער"}, "seg": ["אני"], "lex": "אני", "morph": {"token": "אני", "pos": "PRON", "feats": {"Gender": "Masc", "Number": "Sing", "Person": "1"}, "prefixes": [], "suffix": false}}, {"token": "כאן", "offsets": {"start": 541, "end": 544}, "syntax": {"word": "כאן", "dep_head_idx": 116, "dep_func": "advmod", "dep_head": "לשבור"}, "seg": ["כאן"], "lex": "כאן", "morph": {"token": "כאן", "pos": "ADV", "feats": {}, "prefixes": [], "suffix": false}}, {"token": "לשבור", "offsets": {"start": 545, "end": 550}, "syntax": {"word": "לשבור", "dep_head_idx": 107, "dep_func": "xcomp", "dep_head": "גרם"}, "seg": ["לשבור"], "lex": "שבר", "morph": {"token": "לשבור", "pos": "VERB", "feats": {}, "prefixes": [], "suffix": false}}, {"token": "אין", "offsets": {"start": 551, "end": 554}, "syntax": {"word": "אין", "dep_head_idx": 116, "dep_func": "parataxis", "dep_head": "לשבור"}, "seg": ["אין"], "lex": "אין", "morph": {"token": "אין", "pos": "VERB", "feats": {}, "prefixes": [], "suffix": false}}, {"token": "דבר", "offsets": {"start": 555, "end": 558}, "syntax": {"word": "דבר", "dep_head_idx": 117, "dep_func": "nsubj", "dep_head": "אין"}, "seg": ["דבר"], "lex": "דבר", "morph": {"token": "דבר", "pos": "NOUN", "feats": {"Gender": "Masc", "Number": "Sing"}, "prefixes": [], "suffix": false}}, {"token": "שיעצור", "offsets": {"start": 559, "end": 565}, "syntax": {"word": "שיעצור", "dep_head_idx": 118, "dep_func": "acl:relcl", "dep_head": "דבר"}, "seg": ["ש", "יעצור"], "lex": "עצר", "morph": {"token": "שיעצור", "pos": "VERB", "feats": {"Gender": "Masc", "Number": "Sing", "Person": "3", "Tense": "Fut"}, "prefixes": ["SCONJ"], "suffix": false}}, {"token": "חביבי", "offsets": {"start": 566, "end": 571}, "syntax": {"word": "חביבי", "dep_head_idx": 117, "dep_func": "advmod", "dep_head": "אין"}, "seg": ["חביבי"], "lex": "חביבי", "morph": {"token": "חביבי", "pos": "NOUN", "feats": {}, "prefixes": [], "suffix": "PRON", "suffix_feats": {"Gender": "Masc", "Number": "Sing", "Person": "1"}}}, {"token": "כלום", "offsets": {"start": 572, "end": 576}, "syntax": {"word": "כלום", "dep_head_idx": 123, "dep_func": "nsubj", "dep_head": "יעזור"}, "seg": ["כלום"], "lex": "כלום", "morph": {"token": "כלום", "pos": "ADV", "feats": {}, "prefixes": [], "suffix": false}}, {"token": "לא", "offsets": {"start": 577, "end": 579}, "syntax": {"word": "לא", "dep_head_idx": 123, "dep_func": "advmod", "dep_head": "יעזור"}, "seg": ["לא"], "lex": "לא", "morph": {"token": "לא", "pos": "ADV", "feats": {}, "prefixes": [], "suffix": false}}, {"token": "יעזור", "offsets": {"start": 580, "end": 585}, "syntax": {"word": "יעזור", "dep_head_idx": 118, "dep_func": "acl:relcl", "dep_head": "דבר"}, "seg": ["יעזור"], "lex": "יעזור", "morph": {"token": "יעזור", "pos": "VERB", "feats": {"Gender": "Masc", "Number": "Sing", "Person": "3", "Tense": "Fut"}, "prefixes": [], "suffix": false}}, {"token": "אני", "offsets": {"start": 586, "end": 589}, "syntax": {"word": "אני", "dep_head_idx": 123, "dep_func": "nsubj", "dep_head": "יעזור"}, "seg": ["אני"], "lex": "אני", "morph": {"token": "אני", "pos": "PRON", "feats": {"Gender": "Masc", "Number": "Sing", "Person": "1"}, "prefixes": [], "suffix": false}}, {"token": "כאן", "offsets": {"start": 590, "end": 593}, "syntax": {"word": "כאן", "dep_head_idx": 123, "dep_func": "advmod", "dep_head": "יעזור"}, "seg": ["כאן"], "lex": "כאן", "morph": {"token": "כאן", "pos": "ADV", "feats": {}, "prefixes": [], "suffix": false}}, {"token": "לשבור", "offsets": {"start": 594, "end": 599}, "syntax": {"word": "לשבור", "dep_head_idx": 123, "dep_func": "xcomp", "dep_head": "יעזור"}, "seg": ["לשבור"], "lex": "שבר", "morph": {"token": "לשבור", "pos": "VERB", "feats": {}, "prefixes": [], "suffix": false}}, {"token": "זה", "offsets": {"start": 600, "end": 602}, "syntax": {"word": "זה", "dep_head_idx": 128, "dep_func": "expl", "dep_head": "בוער"}, "seg": ["זה"], "lex": "זה", "morph": {"token": "זה", "pos": "PRON", "feats": {"Gender": "Masc", "Number": "Sing", "Person": "3"}, "prefixes": [], "suffix": false}}, {"token": "בוער", "offsets": {"start": 603, "end": 607}, "syntax": {"word": "בוער", "dep_head_idx": 126, "dep_func": "parataxis", "dep_head": "לשבור"}, "seg": ["בוער"], "lex": "בוער", "morph": {"token": "בוער", "pos": "VERB", "feats": {"Gender": "Masc", "Number": "Sing", "Person": "3", "Tense": "Pres"}, "prefixes": [], "suffix": false}}, {"token": "לי", "offsets": {"start": 608, "end": 610}, "syntax": {"word": "לי", "dep_head_idx": 128, "dep_func": "obl", "dep_head": "בוער"}, "seg": ["לי"], "lex": "לי", "morph": {"token": "לי", "pos": "PRON", "feats": {"Gender": "Masc", "Number": "Sing", "Person": "1"}, "prefixes": ["ADP"], "suffix": false}}, {"token": "בורידים", "offsets": {"start": 611, "end": 618}, "syntax": {"word": "בורידים", "dep_head_idx": 265, "dep_func": "obl", "dep_head": "נשחק"}, "seg": ["ב", "ורידים"], "lex": "בורי", "morph": {"token": "בורידים", "pos": "NOUN", "feats": {"Gender": "Masc", "Number": "Plur"}, "prefixes": ["DET", "ADP"], "suffix": false}}, {"token": "וזה", "offsets": {"start": 619, "end": 622}, "syntax": {"word": "וזה", "dep_head_idx": 128, "dep_func": "nsubj", "dep_head": "בוער"}, "seg": ["ו", "זה"], "lex": "זה", "morph": {"token": "וזה", "pos": "PRON", "feats": {"Gender": "Masc", "Number": "Sing", "Person": "3"}, "prefixes": ["CCONJ"], "suffix": false}}, {"token": "חרוט", "offsets": {"start": 623, "end": 627}, "syntax": {"word": "חרוט", "dep_head_idx": 44, "dep_func": "conj", "dep_head": "קבל"}, "seg": ["חרוט"], "lex": "חרוט", "morph": {"token": "חרוט", "pos": "VERB", "feats": {"Gender": "Masc", "Number": "Sing", "Person": "3", "Tense": "Pres"}, "prefixes": [], "suffix": false}}, {"token": "לי", "offsets": {"start": 628, "end": 630}, "syntax": {"word": "לי", "dep_head_idx": 132, "dep_func": "obl", "dep_head": "חרוט"}, "seg": ["לי"], "lex": "לי", "morph": {"token": "לי", "pos": "PRON", "feats": {"Gender": "Masc", "Number": "Sing", "Person": "1"}, "prefixes": ["ADP"], "suffix": false}}, {"token": "על", "offsets": {"start": 631, "end": 633}, "syntax": {"word": "על", "dep_head_idx": 135, "dep_func": "case", "dep_head": "העור"}, "seg": ["על"], "lex": "על", "morph": {"token": "על", "pos": "ADP", "feats": {}, "prefixes": [], "suffix": false}}, {"token": "העור", "offsets": {"start": 634, "end": 638}, "syntax": {"word": "העור", "dep_head_idx": 132, "dep_func": "obl", "dep_head": "חרוט"}, "seg": ["ה", "עור"], "lex": "עור", "morph": {"token": "העור", "pos": "NOUN", "feats": {"Gender": "Masc", "Number": "Sing"}, "prefixes": ["DET"], "suffix": false}}, {"token": "אני", "offsets": {"start": 639, "end": 642}, "syntax": {"word": "אני", "dep_head_idx": 123, "dep_func": "nsubj", "dep_head": "יעזור"}, "seg": ["אני"], "lex": "אני", "morph": {"token": "אני", "pos": "PRON", "feats": {"Gender": "Masc", "Number": "Sing", "Person": "1"}, "prefixes": [], "suffix": false}}, {"token": "כאן", "offsets": {"start": 643, "end": 646}, "syntax": {"word": "כאן", "dep_head_idx": 138, "dep_func": "advmod", "dep_head": "לשבור"}, "seg": ["כאן"], "lex": "כאן", "morph": {"token": "כאן", "pos": "ADV", "feats": {}, "prefixes": [], "suffix": false}}, {"token": "לשבור", "offsets": {"start": 647, "end": 652}, "syntax": {"word": "לשבור", "dep_head_idx": 123, "dep_func": "xcomp", "dep_head": "יעזור"}, "seg": ["לשבור"], "lex": "שבר", "morph": {"token": "לשבור", "pos": "VERB", "feats": {}, "prefixes": [], "suffix": false}}, {"token": "תן", "offsets": {"start": 653, "end": 655}, "syntax": {"word": "תן", "dep_head_idx": 51, "dep_func": "acl", "dep_head": "המכה"}, "seg": ["תן"], "lex": "תן", "morph": {"token": "תן", "pos": "VERB", "feats": {"Gender": "Masc", "Number": "Sing", "Person": "2", "Tense": "Imp"}, "prefixes": [], "suffix": false}}, {"token": "לזה", "offsets": {"start": 656, "end": 659}, "syntax": {"word": "לזה", "dep_head_idx": 52, "dep_func": "obl", "dep_head": "שובר"}, "seg": ["לזה"], "lex": "לזה", "morph": {"token": "לזה", "pos": "PRON", "feats": {"Gender": "Masc", "Number": "Sing", "Person": "3"}, "prefixes": ["ADP"], "suffix": false}}, {"token": "לצאת", "offsets": {"start": 660, "end": 664}, "syntax": {"word": "לצאת", "dep_head_idx": 123, "dep_func": "xcomp", "dep_head": "יעזור"}, "seg": ["לצאת"], "lex": "יצא", "morph": {"token": "לצאת", "pos": "VERB", "feats": {}, "prefixes": [], "suffix": false}}, {"token": ",", "offsets": {"start": 664, "end": 665}, "syntax": {"word": ",", "dep_head_idx": 143, "dep_func": "punct", "dep_head": "תן"}, "seg": [","], "lex": ",", "morph": {"token": ",", "pos": "PUNCT", "feats": {}, "prefixes": [], "suffix": false}}, {"token": "תן", "offsets": {"start": 666, "end": 668}, "syntax": {"word": "תן", "dep_head_idx": 52, "dep_func": "parataxis", "dep_head": "שובר"}, "seg": ["תן"], "lex": "תן", "morph": {"token": "תן", "pos": "VERB", "feats": {"Gender": "Masc", "Number": "Sing", "Person": "2", "Tense": "Imp"}, "prefixes": [], "suffix": false}}, {"token": "לזה", "offsets": {"start": 669, "end": 672}, "syntax": {"word": "לזה", "dep_head_idx": 148, "dep_func": "obl", "dep_head": "לשבור"}, "seg": ["לזה"], "lex": "זה", "morph": {"token": "לזה", "pos": "PRON", "feats": {"Gender": "Masc", "Number": "Sing", "Person": "3"}, "prefixes": ["ADP"], "suffix": false}}, {"token": "לבעור", "offsets": {"start": 673, "end": 678}, "syntax": {"word": "לבעור", "dep_head_idx": 143, "dep_func": "xcomp", "dep_head": "תן"}, "seg": ["לבעור"], "lex": "בוער", "morph": {"token": "לבעור", "pos": "VERB", "feats": {}, "prefixes": [], "suffix": false}}, {"token": "אני", "offsets": {"start": 679, "end": 682}, "syntax": {"word": "אני", "dep_head_idx": 128, "dep_func": "nsubj", "dep_head": "בוער"}, "seg": ["אני"], "lex": "אני", "morph": {"token": "אני", "pos": "PRON", "feats": {"Gender": "Masc", "Number": "Sing", "Person": "1"}, "prefixes": [], "suffix": false}}, {"token": "כאן", "offsets": {"start": 683, "end": 686}, "syntax": {"word": "כאן", "dep_head_idx": 148, "dep_func": "parataxis", "dep_head": "לשבור"}, "seg": ["כאן"], "lex": "כאן", "morph": {"token": "כאן", "pos": "ADV", "feats": {}, "prefixes": [], "suffix": false}}, {"token": "לשבור", "offsets": {"start": 687, "end": 692}, "syntax": {"word": "לשבור", "dep_head_idx": 143, "dep_func": "xcomp", "dep_head": "תן"}, "seg": ["לשבור"], "lex": "שבר", "morph": {"token": "לשבור", "pos": "VERB", "feats": {}, "prefixes": [], "suffix": false}}, {"token": "אינעל", "offsets": {"start": 693, "end": 698}, "syntax": {"word": "אינעל", "dep_head_idx": 148, "dep_func": "obj", "dep_head": "לשבור"}, "seg": ["אינעל"], "lex": "[BLANK]", "morph": {"token": "אינעל", "pos": "X", "feats": {}, "prefixes": [], "suffix": false}}, {"token": "דינק", "offsets": {"start": 699, "end": 703}, "syntax": {"word": "דינק", "dep_head_idx": 148, "dep_func": "obj", "dep_head": "לשבור"}, "seg": ["דינק"], "lex": "[BLANK]", "morph": {"token": "דינק", "pos": "PROPN", "feats": {}, "prefixes": [], "suffix": false}}, {"token": "העולם", "offsets": {"start": 704, "end": 709}, "syntax": {"word": "העולם", "dep_head_idx": 152, "dep_func": "obj", "dep_head": "עושים"}, "seg": ["ה", "עולם"], "lex": "עולם", "morph": {"token": "העולם", "pos": "NOUN", "feats": {"Gender": "Masc", "Number": "Sing"}, "prefixes": ["DET"], "suffix": false}}, {"token": "עושים", "offsets": {"start": 710, "end": 715}, "syntax": {"word": "עושים", "dep_head_idx": 132, "dep_func": "parataxis", "dep_head": "חרוט"}, "seg": ["עושים"], "lex": "עושה", "morph": {"token": "עושים", "pos": "VERB", "feats": {"Gender": "Masc", "Number": "Plur", "Person": "3", "Tense": "Pres"}, "prefixes": [], "suffix": false}}, {"token": "טרור", "offsets": {"start": 716, "end": 720}, "syntax": {"word": "טרור", "dep_head_idx": 152, "dep_func": "obj", "dep_head": "עושים"}, "seg": ["טרור"], "lex": "טרור", "morph": {"token": "טרור", "pos": "NOUN", "feats": {"Gender": "Masc", "Number": "Sing"}, "prefixes": [], "suffix": false}}, {"token": "וזה", "offsets": {"start": 722, "end": 725}, "syntax": {"word": "וזה", "dep_head_idx": 155, "dep_func": "nsubj", "dep_head": "מוקדש"}, "seg": ["ו", "זה"], "lex": "זה", "morph": {"token": "וזה", "pos": "PRON", "feats": {"Gender": "Masc", "Number": "Sing", "Person": "3"}, "prefixes": ["CCONJ"], "suffix": false}}, {"token": "מוקדש", "offsets": {"start": 726, "end": 731}, "syntax": {"word": "מוקדש", "dep_head_idx": 226, "dep_func": "conj", "dep_head": "הורג"}, "seg": ["מוקדש"], "lex": "הוקדש", "morph": {"token": "מוקדש", "pos": "VERB", "feats": {"Gender": "Masc", "Number": "Sing", "Person": "3", "Tense": "Pres"}, "prefixes": [], "suffix": false}}, {"token": "לכל", "offsets": {"start": 732, "end": 735}, "syntax": {"word": "לכל", "dep_head_idx": 157, "dep_func": "det", "dep_head": "רודפי"}, "seg": ["ל", "כל"], "lex": "כול", "morph": {"token": "לכל", "pos": "DET", "feats": {}, "prefixes": ["ADP"], "suffix": false}}, {"token": "רודפי", "offsets": {"start": 736, "end": 741}, "syntax": {"word": "רודפי", "dep_head_idx": 65, "dep_func": "obl", "dep_head": "שברתי"}, "seg": ["רודפי"], "lex": "רודף", "morph": {"token": "רודפי", "pos": "NOUN", "feats": {"Gender": "Masc", "Number": "Plur"}, "prefixes": [], "suffix": false}}, {"token": "החלומות", "offsets": {"start": 742, "end": 749}, "syntax": {"word": "החלומות", "dep_head_idx": 52, "dep_func": "compound:smixut", "dep_head": "שובר"}, "seg": ["ה", "חלומות"], "lex": "חלום", "morph": {"token": "החלומות", "pos": "NOUN", "feats": {"Gender": "Masc", "Number": "Plur"}, "prefixes": ["DET"], "suffix": false}}, {"token": "אנחנו", "offsets": {"start": 750, "end": 755}, "syntax": {"word": "אנחנו", "dep_head_idx": 161, "dep_func": "nsubj", "dep_head": "זרים"}, "seg": ["אנחנו"], "lex": "אני", "morph": {"token": "אנחנו", "pos": "PRON", "feats": {"Gender": "Masc", "Number": "Plur", "Person": "1"}, "prefixes": [], "suffix": false}}, {"token": "לא", "offsets": {"start": 756, "end": 758}, "syntax": {"word": "לא", "dep_head_idx": 161, "dep_func": "advmod", "dep_head": "זרים"}, "seg": ["לא"], "lex": "לא", "morph": {"token": "לא", "pos": "ADV", "feats": {}, "prefixes": [], "suffix": false}}, {"token": "זרים", "offsets": {"start": 759, "end": 763}, "syntax": {"word": "זרים", "dep_head_idx": 52, "dep_func": "conj", "dep_head": "שובר"}, "seg": ["זרים"], "lex": "זר", "morph": {"token": "זרים", "pos": "ADJ", "feats": {"Gender": "Masc", "Number": "Plur"}, "prefixes": [], "suffix": false}}, {"token": "לסבל", "offsets": {"start": 764, "end": 768}, "syntax": {"word": "לסבל", "dep_head_idx": 161, "dep_func": "obl", "dep_head": "זרים"}, "seg": ["ל", "סבל"], "lex": "סבל", "morph": {"token": "לסבל", "pos": "NOUN", "feats": {"Gender": "Masc", "Number": "Sing"}, "prefixes": ["DET", "ADP"], "suffix": false}}, {"token": "שונא", "offsets": {"start": 769, "end": 773}, "syntax": {"word": "שונא", "dep_head_idx": 52, "dep_func": "conj", "dep_head": "שובר"}, "seg": ["שונא"], "lex": "שונא", "morph": {"token": "שונא", "pos": "VERB", "feats": {"Gender": "Masc", "Number": "Sing", "Person": "3", "Tense": "Pres"}, "prefixes": [], "suffix": false}}, {"token": "להיות", "offsets": {"start": 774, "end": 779}, "syntax": {"word": "להיות", "dep_head_idx": 161, "dep_func": "cop", "dep_head": "זרים"}, "seg": ["להיות"], "lex": "היה", "morph": {"token": "להיות", "pos": "AUX", "feats": {}, "prefixes": [], "suffix": false}}, {"token": "ריאלי", "offsets": {"start": 780, "end": 785}, "syntax": {"word": "ריאלי", "dep_head_idx": 163, "dep_func": "xcomp", "dep_head": "שונא"}, "seg": ["ריאלי"], "lex": "ריאלי", "morph": {"token": "ריאלי", "pos": "ADJ", "feats": {"Gender": "Masc", "Number": "Sing"}, "prefixes": [], "suffix": false}}, {"token": ",", "offsets": {"start": 785, "end": 786}, "syntax": {"word": ",", "dep_head_idx": 168, "dep_func": "punct", "dep_head": "יש"}, "seg": [","], "lex": ",", "morph": {"token": ",", "pos": "PUNCT", "feats": {}, "prefixes": [], "suffix": false}}, {"token": "ריאליזם", "offsets": {"start": 787, "end": 794}, "syntax": {"word": "ריאליזם", "dep_head_idx": 168, "dep_func": "nsubj", "dep_head": "יש"}, "seg": ["ריאליזם"], "lex": "ריאליזם", "morph": {"token": "ריאליזם", "pos": "NOUN", "feats": {"Gender": "Masc", "Number": "Sing"}, "prefixes": [], "suffix": false}}, {"token": "יש", "offsets": {"start": 795, "end": 797}, "syntax": {"word": "יש", "dep_head_idx": 52, "dep_func": "parataxis", "dep_head": "שובר"}, "seg": ["יש"], "lex": "יש", "morph": {"token": "יש", "pos": "VERB", "feats": {}, "prefixes": [], "suffix": false}}, {"token": "כמו", "offsets": {"start": 798, "end": 801}, "syntax": {"word": "כמו", "dep_head_idx": 170, "dep_func": "case", "dep_head": "זבל"}, "seg": ["כמו"], "lex": "כמו", "morph": {"token": "כמו", "pos": "ADP", "feats": {}, "prefixes": [], "suffix": false}}, {"token": "זבל", "offsets": {"start": 802, "end": 805}, "syntax": {"word": "זבל", "dep_head_idx": 168, "dep_func": "obl", "dep_head": "יש"}, "seg": ["זבל"], "lex": "זבל", "morph": {"token": "זבל", "pos": "NOUN", "feats": {"Gender": "Masc", "Number": "Sing"}, "prefixes": [], "suffix": false}}, {"token": "לכן", "offsets": {"start": 806, "end": 809}, "syntax": {"word": "לכן", "dep_head_idx": 168, "dep_func": "advmod", "dep_head": "יש"}, "seg": ["לכן"], "lex": "לכן", "morph": {"token": "לכן", "pos": "ADV", "feats": {}, "prefixes": [], "suffix": false}}, {"token": "אני", "offsets": {"start": 810, "end": 813}, "syntax": {"word": "אני", "dep_head_idx": 107, "dep_func": "nsubj", "dep_head": "גרם"}, "seg": ["אני"], "lex": "אני", "morph": {"token": "אני", "pos": "PRON", "feats": {"Gender": "Masc", "Number": "Sing", "Person": "1"}, "prefixes": [], "suffix": false}}, {"token": "חותך", "offsets": {"start": 814, "end": 818}, "syntax": {"word": "חותך", "dep_head_idx": 72, "dep_func": "ccomp", "dep_head": "אמרתי"}, "seg": ["חותך"], "lex": "חותך", "morph": {"token": "חותך", "pos": "VERB", "feats": {"Gender": "Masc", "Number": "Sing", "Person": "3", "Tense": "Pres"}, "prefixes": [], "suffix": false}}, {"token": "ת'", "offsets": {"start": 819, "end": 821}, "syntax": {"word": "ת'", "dep_head_idx": 189, "dep_func": "compound:smixut", "dep_head": "דרמה"}, "seg": ["ת'"], "lex": "ת'", "morph": {"token": "ת'", "pos": "X", "feats": {}, "prefixes": [], "suffix": false}}, {"token": "מציאות", "offsets": {"start": 821, "end": 827}, "syntax": {"word": "מציאות", "dep_head_idx": 148, "dep_func": "obj", "dep_head": "לשבור"}, "seg": ["מציאות"], "lex": "מציאות", "morph": {"token": "מציאות", "pos": "NOUN", "feats": {"Gender": "Fem", "Number": "Sing"}, "prefixes": ["DET"], "suffix": false}}, {"token": "הזאת", "offsets": {"start": 828, "end": 832}, "syntax": {"word": "הזאת", "dep_head_idx": 14, "dep_func": "det", "dep_head": "אנרגיה"}, "seg": ["ה", "זאת"], "lex": "זה", "morph": {"token": "הזאת", "pos": "PRON", "feats": {"Gender": "Fem", "Number": "Sing", "Person": "3"}, "prefixes": ["DET"], "suffix": false}}, {"token": ",", "offsets": {"start": 832, "end": 833}, "syntax": {"word": ",", "dep_head_idx": 77, "dep_func": "punct", "dep_head": "נפתח"}, "seg": [","], "lex": ",", "morph": {"token": ",", "pos": "PUNCT", "feats": {}, "prefixes": [], "suffix": false}}, {"token": "פסטרמה", "offsets": {"start": 834, "end": 840}, "syntax": {"word": "פסטרמה", "dep_head_idx": 180, "dep_func": "obj", "dep_head": "המצאתי"}, "seg": ["פסטרמה"], "lex": "פסטרמה", "morph": {"token": "פסטרמה", "pos": "NOUN", "feats": {"Gender": "Fem", "Number": "Sing"}, "prefixes": [], "suffix": false}}, {"token": "לא", "offsets": {"start": 841, "end": 843}, "syntax": {"word": "לא", "dep_head_idx": 77, "dep_func": "advmod", "dep_head": "נפתח"}, "seg": ["לא"], "lex": "לא", "morph": {"token": "לא", "pos": "ADV", "feats": {}, "prefixes": [], "suffix": false}}, {"token": "המצאתי", "offsets": {"start": 844, "end": 850}, "syntax": {"word": "המצאתי", "dep_head_idx": 72, "dep_func": "ccomp", "dep_head": "אמרתי"}, "seg": ["המצאתי"], "lex": "המציא", "morph": {"token": "המצאתי", "pos": "VERB", "feats": {"Gender": "Fem", "Number": "Sing", "Person": "1", "Tense": "Past"}, "prefixes": [], "suffix": false}}, {"token": "ת'", "offsets": {"start": 851, "end": 853}, "syntax": {"word": "ת'", "dep_head_idx": 180, "dep_func": "obj", "dep_head": "המצאתי"}, "seg": ["ת'"], "lex": "ת'", "morph": {"token": "ת'", "pos": "X", "feats": {}, "prefixes": [], "suffix": false}}, {"token": "גלגל", "offsets": {"start": 853, "end": 857}, "syntax": {"word": "גלגל", "dep_head_idx": 180, "dep_func": "obj", "dep_head": "המצאתי"}, "seg": ["גלגל"], "lex": "גלגל", "morph": {"token": "גלגל", "pos": "NOUN", "feats": {"Gender": "Masc", "Number": "Sing"}, "prefixes": [], "suffix": false}}, {"token": "אבל", "offsets": {"start": 858, "end": 861}, "syntax": {"word": "אבל", "dep_head_idx": 205, "dep_func": "cc", "dep_head": "נמצא"}, "seg": ["אבל"], "lex": "אבל", "morph": {"token": "אבל", "pos": "CCONJ", "feats": {}, "prefixes": [], "suffix": false}}, {"token": "פינצ", "offsets": {"start": 862, "end": 866}, "syntax": {"word": "פינצ", "dep_head_idx": 102, "dep_func": "vocative", "dep_head": "בוא"}, "seg": ["פינצ"], "lex": "[BLANK]", "morph": {"token": "פינצ", "pos": "PROPN", "feats": {}, "prefixes": [], "suffix": false}}, {"token": "'", "offsets": {"start": 866, "end": 867}, "syntax": {"word": "'", "dep_head_idx": 184, "dep_func": "flat", "dep_head": "פינצ"}, "seg": ["'"], "lex": "'", "morph": {"token": "'", "pos": "PUNCT", "feats": {}, "prefixes": [], "suffix": false}}, {"token": "רתי", "offsets": {"start": 867, "end": 870}, "syntax": {"word": "רתי", "dep_head_idx": 201, "dep_func": "flat", "dep_head": "מאשין"}, "seg": ["רתי"], "lex": "[BLANK]", "morph": {"token": "רתי", "pos": "PROPN", "feats": {}, "prefixes": [], "suffix": false}}, {"token": "כמה", "offsets": {"start": 871, "end": 874}, "syntax": {"word": "כמה", "dep_head_idx": 189, "dep_func": "det", "dep_head": "דרמה"}, "seg": ["כמה"], "lex": "כמה", "morph": {"token": "כמה", "pos": "DET", "feats": {}, "prefixes": [], "suffix": false}}, {"token": "כמה", "offsets": {"start": 876, "end": 879}, "syntax": {"word": "כמה", "dep_head_idx": 189, "dep_func": "det", "dep_head": "דרמה"}, "seg": ["כמה"], "lex": "כמה", "morph": {"token": "כמה", "pos": "DET", "feats": {}, "prefixes": [], "suffix": false}}, {"token": "דרמה", "offsets": {"start": 880, "end": 884}, "syntax": {"word": "דרמה", "dep_head_idx": 168, "dep_func": "obj", "dep_head": "יש"}, "seg": ["דרמה"], "lex": "דרמה", "morph": {"token": "דרמה", "pos": "NOUN", "feats": {"Gender": "Fem", "Number": "Sing"}, "prefixes": [], "suffix": false}}, {"token": "למה", "offsets": {"start": 885, "end": 888}, "syntax": {"word": "למה", "dep_head_idx": 205, "dep_func": "advmod", "dep_head": "נמצא"}, "seg": ["למה"], "lex": "למה", "morph": {"token": "למה", "pos": "ADV", "feats": {}, "prefixes": [], "suffix": false}}, {"token": ",", "offsets": {"start": 888, "end": 889}, "syntax": {"word": ",", "dep_head_idx": 190, "dep_func": "punct", "dep_head": "למה"}, "seg": [","], "lex": ",", "morph": {"token": ",", "pos": "PUNCT", "feats": {}, "prefixes": [], "suffix": false}}, {"token": "עזוב", "offsets": {"start": 890, "end": 894}, "syntax": {"word": "עזוב", "dep_head_idx": 72, "dep_func": "parataxis", "dep_head": "אמרתי"}, "seg": ["עזוב"], "lex": "עזוב", "morph": {"token": "עזוב", "pos": "VERB", "feats": {"Gender": "Masc", "Number": "Sing", "Person": "2", "Tense": "Imp"}, "prefixes": [], "suffix": false}}, {"token": "שטויות", "offsets": {"start": 895, "end": 901}, "syntax": {"word": "שטויות", "dep_head_idx": 168, "dep_func": "obj", "dep_head": "יש"}, "seg": ["שטויות"], "lex": "שטות", "morph": {"token": "שטויות", "pos": "NOUN", "feats": {"Gender": "Fem", "Number": "Plur"}, "prefixes": [], "suffix": false}}, {"token": "עלינו", "offsets": {"start": 902, "end": 907}, "syntax": {"word": "עלינו", "dep_head_idx": 189, "dep_func": "nmod", "dep_head": "דרמה"}, "seg": ["עלינו"], "lex": "על", "morph": {"token": "עלינו", "pos": "ADP", "feats": {}, "prefixes": [], "suffix": "PRON", "suffix_feats": {"Number": "Plur", "Person": "1"}}}, {"token": "ליגה", "offsets": {"start": 908, "end": 912}, "syntax": {"word": "ליגה", "dep_head_idx": 168, "dep_func": "obj", "dep_head": "יש"}, "seg": ["ליגה"], "lex": "ליגה", "morph": {"token": "ליגה", "pos": "NOUN", "feats": {"Number": "Sing"}, "prefixes": [], "suffix": false}}, {"token": "שוורצע", "offsets": {"start": 913, "end": 919}, "syntax": {"word": "שוורצע", "dep_head_idx": 192, "dep_func": "nsubj", "dep_head": "עזוב"}, "seg": ["שוורצע"], "lex": "[BLANK]", "morph": {"token": "שוורצע", "pos": "PROPN", "feats": {}, "prefixes": [], "suffix": false}}, {"token": "חייה", "offsets": {"start": 920, "end": 924}, "syntax": {"word": "חייה", "dep_head_idx": 196, "dep_func": "compound:smixut", "dep_head": "שוורצע"}, "seg": ["חייה"], "lex": "חי", "morph": {"token": "חייה", "pos": "NOUN", "feats": {"Gender": "Masc", "Number": "Plur"}, "prefixes": [], "suffix": "PRON", "suffix_feats": {"Gender": "Fem", "Number": "Sing", "Person": "3"}}}, {"token": ",", "offsets": {"start": 924, "end": 925}, "syntax": {"word": ",", "dep_head_idx": 199, "dep_func": "punct", "dep_head": "משוגע"}, "seg": [","], "lex": ",", "morph": {"token": ",", "pos": "PUNCT", "feats": {}, "prefixes": [], "suffix": false}}, {"token": "משוגע", "offsets": {"start": 926, "end": 931}, "syntax": {"word": "משוגע", "dep_head_idx": 180, "dep_func": "obj", "dep_head": "המצאתי"}, "seg": ["משוגע"], "lex": "משוגע", "morph": {"token": "משוגע", "pos": "ADJ", "feats": {"Gender": "Masc", "Number": "Sing"}, "prefixes": [], "suffix": false}}, {"token": "עם", "offsets": {"start": 932, "end": 934}, "syntax": {"word": "עם", "dep_head_idx": 201, "dep_func": "case", "dep_head": "מאשין"}, "seg": ["עם"], "lex": "עם", "morph": {"token": "עם", "pos": "ADP", "feats": {}, "prefixes": [], "suffix": false}}, {"token": "מאשין", "offsets": {"start": 935, "end": 940}, "syntax": {"word": "מאשין", "dep_head_idx": 199, "dep_func": "obl", "dep_head": "משוגע"}, "seg": ["מאשין"], "lex": "מיה", "morph": {"token": "מאשין", "pos": "PROPN", "feats": {}, "prefixes": [], "suffix": false}}, {"token": "גאן", "offsets": {"start": 941, "end": 944}, "syntax": {"word": "גאן", "dep_head_idx": 201, "dep_func": "flat", "dep_head": "מאשין"}, "seg": ["גאן"], "lex": "גאן", "morph": {"token": "גאן", "pos": "PROPN", "feats": {}, "prefixes": [], "suffix": false}}, {"token": "הלב", "offsets": {"start": 945, "end": 948}, "syntax": {"word": "הלב", "dep_head_idx": 205, "dep_func": "nsubj", "dep_head": "נמצא"}, "seg": ["ה", "לב"], "lex": "לב", "morph": {"token": "הלב", "pos": "NOUN", "feats": {"Gender": "Masc", "Number": "Sing"}, "prefixes": ["DET"], "suffix": false}}, {"token": "שלי", "offsets": {"start": 949, "end": 952}, "syntax": {"word": "שלי", "dep_head_idx": 203, "dep_func": "nmod:poss", "dep_head": "הלב"}, "seg": ["שלי"], "lex": "של", "morph": {"token": "שלי", "pos": "ADP", "feats": {}, "prefixes": [], "suffix": "PRON", "suffix_feats": {"Gender": "Masc", "Number": "Sing", "Person": "1"}}}, {"token": "נמצא", "offsets": {"start": 953, "end": 957}, "syntax": {"word": "נמצא", "dep_head_idx": 72, "dep_func": "ccomp", "dep_head": "אמרתי"}, "seg": ["נמצא"], "lex": "נמצא", "morph": {"token": "נמצא", "pos": "VERB", "feats": {"Gender": "Masc", "Number": "Sing", "Person": "3", "Tense": "Past"}, "prefixes": [], "suffix": false}}, {"token": "על", "offsets": {"start": 958, "end": 960}, "syntax": {"word": "על", "dep_head_idx": 208, "dep_func": "case", "dep_head": "שיר"}, "seg": ["על"], "lex": "על", "morph": {"token": "על", "pos": "ADP", "feats": {}, "prefixes": [], "suffix": false}}, {"token": "כל", "offsets": {"start": 961, "end": 963}, "syntax": {"word": "כל", "dep_head_idx": 208, "dep_func": "det", "dep_head": "שיר"}, "seg": ["כל"], "lex": "כל", "morph": {"token": "כל", "pos": "DET", "feats": {}, "prefixes": [], "suffix": false}}, {"token": "שיר", "offsets": {"start": 964, "end": 967}, "syntax": {"word": "שיר", "dep_head_idx": 205, "dep_func": "obl", "dep_head": "נמצא"}, "seg": ["שיר"], "lex": "שיר", "morph": {"token": "שיר", "pos": "NOUN", "feats": {"Gender": "Masc", "Number": "Sing"}, "prefixes": [], "suffix": false}}, {"token": ",", "offsets": {"start": 967, "end": 968}, "syntax": {"word": ",", "dep_head_idx": 212, "dep_func": "punct", "dep_head": "גבוה"}, "seg": [","], "lex": ",", "morph": {"token": ",", "pos": "PUNCT", "feats": {}, "prefixes": [], "suffix": false}}, {"token": "אני", "offsets": {"start": 969, "end": 972}, "syntax": {"word": "אני", "dep_head_idx": 205, "dep_func": "nsubj", "dep_head": "נמצא"}, "seg": ["אני"], "lex": "אני", "morph": {"token": "אני", "pos": "PRON", "feats": {"Gender": "Masc", "Number": "Sing", "Person": "1"}, "prefixes": [], "suffix": false}}, {"token": ",", "offsets": {"start": 972, "end": 973}, "syntax": {"word": ",", "dep_head_idx": 212, "dep_func": "punct", "dep_head": "גבוה"}, "seg": [","], "lex": ",", "morph": {"token": ",", "pos": "PUNCT", "feats": {}, "prefixes": [], "suffix": false}}, {"token": "גבוה", "offsets": {"start": 974, "end": 978}, "syntax": {"word": "גבוה", "dep_head_idx": 205, "dep_func": "parataxis", "dep_head": "נמצא"}, "seg": ["גבוה"], "lex": "גבוה", "morph": {"token": "גבוה", "pos": "ADJ", "feats": {"Gender": "Masc", "Number": "Sing"}, "prefixes": [], "suffix": false}}, {"token": "על", "offsets": {"start": 979, "end": 981}, "syntax": {"word": "על", "dep_head_idx": 214, "dep_func": "case", "dep_head": "ענן"}, "seg": ["על"], "lex": "על", "morph": {"token": "על", "pos": "ADP", "feats": {}, "prefixes": [], "suffix": false}}, {"token": "ענן", "offsets": {"start": 982, "end": 985}, "syntax": {"word": "ענן", "dep_head_idx": 212, "dep_func": "obl", "dep_head": "גבוה"}, "seg": ["ענן"], "lex": "ענן", "morph": {"token": "ענן", "pos": "NOUN", "feats": {"Gender": "Masc", "Number": "Sing"}, "prefixes": [], "suffix": false}}, {"token": "גיטרות", "offsets": {"start": 986, "end": 992}, "syntax": {"word": "גיטרות", "dep_head_idx": 214, "dep_func": "compound:smixut", "dep_head": "ענן"}, "seg": ["גיטרות"], "lex": "גיטרה", "morph": {"token": "גיטרות", "pos": "NOUN", "feats": {"Gender": "Fem", "Number": "Plur"}, "prefixes": [], "suffix": false}}, {"token": "ניר", "offsets": {"start": 993, "end": 996}, "syntax": {"word": "ניר", "dep_head_idx": 42, "dep_func": "flat", "dep_head": "ג'"}, "seg": ["ניר"], "lex": "ניר", "morph": {"token": "ניר", "pos": "PROPN", "feats": {}, "prefixes": [], "suffix": false}}, {"token": "דנן", "offsets": {"start": 997, "end": 1000}, "syntax": {"word": "דנן", "dep_head_idx": 201, "dep_func": "flat", "dep_head": "מאשין"}, "seg": ["דנן"], "lex": "דנן", "morph": {"token": "דנן", "pos": "PROPN", "feats": {}, "prefixes": [], "suffix": false}}, {"token": ",", "offsets": {"start": 1000, "end": 1001}, "syntax": {"word": ",", "dep_head_idx": 244, "dep_func": "punct", "dep_head": "צ'"}, "seg": [","], "lex": ",", "morph": {"token": ",", "pos": "PUNCT", "feats": {}, "prefixes": [], "suffix": false}}, {"token": "סטריט", "offsets": {"start": 1002, "end": 1007}, "syntax": {"word": "סטריט", "dep_head_idx": 44, "dep_func": "vocative", "dep_head": "קבל"}, "seg": ["סטריט"], "lex": "סטריט", "morph": {"token": "סטריט", "pos": "PROPN", "feats": {}, "prefixes": [], "suffix": false}}, {"token": "כמו", "offsets": {"start": 1008, "end": 1011}, "syntax": {"word": "כמו", "dep_head_idx": 201, "dep_func": "case", "dep_head": "מאשין"}, "seg": ["כמו"], "lex": "כמו", "morph": {"token": "כמו", "pos": "ADP", "feats": {}, "prefixes": [], "suffix": false}}, {"token": "שאנן", "offsets": {"start": 1012, "end": 1016}, "syntax": {"word": "שאנן", "dep_head_idx": 44, "dep_func": "obl", "dep_head": "קבל"}, "seg": ["שאנן"], "lex": "שאנן", "morph": {"token": "שאנן", "pos": "PROPN", "feats": {}, "prefixes": [], "suffix": false}}, {"token": "נקי", "offsets": {"start": 1018, "end": 1021}, "syntax": {"word": "נקי", "dep_head_idx": 196, "dep_func": "amod", "dep_head": "שוורצע"}, "seg": ["נקי"], "lex": "נקי", "morph": {"token": "נקי", "pos": "ADJ", "feats": {"Gender": "Masc", "Number": "Sing"}, "prefixes": [], "suffix": false}}, {"token": "ורענן", "offsets": {"start": 1022, "end": 1027}, "syntax": {"word": "ורענן", "dep_head_idx": 222, "dep_func": "conj", "dep_head": "נקי"}, "seg": ["ו", "רענן"], "lex": "רענן", "morph": {"token": "ורענן", "pos": "ADJ", "feats": {"Gender": "Masc", "Number": "Sing"}, "prefixes": ["CCONJ"], "suffix": false}}, {"token": ",", "offsets": {"start": 1027, "end": 1028}, "syntax": {"word": ",", "dep_head_idx": 226, "dep_func": "punct", "dep_head": "הורג"}, "seg": [","], "lex": ",", "morph": {"token": ",", "pos": "PUNCT", "feats": {}, "prefixes": [], "suffix": false}}, {"token": "אני", "offsets": {"start": 1029, "end": 1032}, "syntax": {"word": "אני", "dep_head_idx": 226, "dep_func": "nsubj", "dep_head": "הורג"}, "seg": ["אני"], "lex": "אני", "morph": {"token": "אני", "pos": "PRON", "feats": {"Gender": "Masc", "Number": "Sing", "Person": "1"}, "prefixes": [], "suffix": false}}, {"token": "הורג", "offsets": {"start": 1033, "end": 1037}, "syntax": {"word": "הורג", "dep_head_idx": 256, "dep_func": "ccomp", "dep_head": "אמרתי"}, "seg": ["הורג"], "lex": "הורג", "morph": {"token": "הורג", "pos": "VERB", "feats": {"Gender": "Masc", "Number": "Sing", "Person": "3", "Tense": "Pres"}, "prefixes": [], "suffix": false}}, {"token": "אותם", "offsets": {"start": 1038, "end": 1042}, "syntax": {"word": "אותם", "dep_head_idx": 226, "dep_func": "obj", "dep_head": "הורג"}, "seg": ["אותם"], "lex": "את", "morph": {"token": "אותם", "pos": "ADP", "feats": {}, "prefixes": [], "suffix": "PRON", "suffix_feats": {"Gender": "Masc", "Number": "Plur", "Person": "3"}}}, {"token": "עם", "offsets": {"start": 1043, "end": 1045}, "syntax": {"word": "עם", "dep_head_idx": 229, "dep_func": "case", "dep_head": "ליריקס"}, "seg": ["עם"], "lex": "עם", "morph": {"token": "עם", "pos": "ADP", "feats": {}, "prefixes": [], "suffix": false}}, {"token": "ליריקס", "offsets": {"start": 1046, "end": 1052}, "syntax": {"word": "ליריקס", "dep_head_idx": 226, "dep_func": "obl", "dep_head": "הורג"}, "seg": ["ליריקס"], "lex": "לירי", "morph": {"token": "ליריקס", "pos": "PROPN", "feats": {}, "prefixes": [], "suffix": false}}, {"token": "אלוהים", "offsets": {"start": 1053, "end": 1059}, "syntax": {"word": "אלוהים", "dep_head_idx": 52, "dep_func": "discourse", "dep_head": "שובר"}, "seg": ["אלוהים"], "lex": "אלוהים", "morph": {"token": "אלוהים", "pos": "NOUN", "feats": {"Gender": "Masc", "Number": "Sing"}, "prefixes": [], "suffix": false}}, {"token": "הוא", "offsets": {"start": 1060, "end": 1063}, "syntax": {"word": "הוא", "dep_head_idx": 226, "dep_func": "nsubj", "dep_head": "הורג"}, "seg": ["הוא"], "lex": "הוא", "morph": {"token": "הוא", "pos": "PRON", "feats": {"Gender": "Masc", "Number": "Sing", "Person": "3"}, "prefixes": [], "suffix": false}}, {"token": "בטח", "offsets": {"start": 1064, "end": 1067}, "syntax": {"word": "בטח", "dep_head_idx": 123, "dep_func": "advmod", "dep_head": "יעזור"}, "seg": ["בטח"], "lex": "בטח", "morph": {"token": "בטח", "pos": "ADV", "feats": {}, "prefixes": [], "suffix": false}}, {"token": "דיג", "offsets": {"start": 1068, "end": 1071}, "syntax": {"word": "דיג", "dep_head_idx": 265, "dep_func": "nsubj", "dep_head": "נשחק"}, "seg": ["דיג"], "lex": "דיג", "morph": {"token": "דיג", "pos": "NOUN", "feats": {"Gender": "Masc", "Number": "Sing"}, "prefixes": [], "suffix": false}}, {"token": "'", "offsets": {"start": 1071, "end": 1072}, "syntax": {"word": "'", "dep_head_idx": 42, "dep_func": "punct", "dep_head": "ג'"}, "seg": ["'"], "lex": "'", "morph": {"token": "'", "pos": "PUNCT", "feats": {}, "prefixes": [], "suffix": false}}, {"token": "יי", "offsets": {"start": 1072, "end": 1074}, "syntax": {"word": "יי", "dep_head_idx": 42, "dep_func": "flat", "dep_head": "ג'"}, "seg": ["יי"], "lex": "יי", "morph": {"token": "יי", "pos": "PROPN", "feats": {}, "prefixes": [], "suffix": false}}, {"token": ",", "offsets": {"start": 1074, "end": 1075}, "syntax": {"word": ",", "dep_head_idx": 192, "dep_func": "punct", "dep_head": "עזוב"}, "seg": [","], "lex": ",", "morph": {"token": ",", "pos": "PUNCT", "feats": {}, "prefixes": [], "suffix": false}}, {"token": "החיים", "offsets": {"start": 1076, "end": 1081}, "syntax": {"word": "החיים", "dep_head_idx": 168, "dep_func": "nsubj", "dep_head": "יש"}, "seg": ["ה", "חיים"], "lex": "חי", "morph": {"token": "החיים", "pos": "NOUN", "feats": {"Gender": "Masc", "Number": "Plur"}, "prefixes": ["DET"], "suffix": false}}, {"token": "שלי", "offsets": {"start": 1082, "end": 1085}, "syntax": {"word": "שלי", "dep_head_idx": 237, "dep_func": "nmod:poss", "dep_head": "החיים"}, "seg": ["שלי"], "lex": "של", "morph": {"token": "שלי", "pos": "ADP", "feats": {}, "prefixes": [], "suffix": "PRON", "suffix_feats": {"Gender": "Masc", "Number": "Sing", "Person": "1"}}}, {"token": "הם", "offsets": {"start": 1086, "end": 1088}, "syntax": {"word": "הם", "dep_head_idx": 90, "dep_func": "cop", "dep_head": "בצבע"}, "seg": ["הם"], "lex": "הוא", "morph": {"token": "הם", "pos": "PRON", "feats": {"Gender": "Masc", "Number": "Plur", "Person": "3"}, "prefixes": [], "suffix": false}}, {"token": "רמיקס", "offsets": {"start": 1089, "end": 1094}, "syntax": {"word": "רמיקס", "dep_head_idx": 243, "dep_func": "nmod", "dep_head": "מייק"}, "seg": ["רמיקס"], "lex": "רמיקס", "morph": {"token": "רמיקס", "pos": "NOUN", "feats": {"Gender": "Masc", "Number": "Sing"}, "prefixes": [], "suffix": false}}, {"token": "זה", "offsets": {"start": 1095, "end": 1097}, "syntax": {"word": "זה", "dep_head_idx": 244, "dep_func": "det", "dep_head": "צ'"}, "seg": ["זה"], "lex": "זה", "morph": {"token": "זה", "pos": "PRON", "feats": {"Gender": "Masc", "Number": "Sing", "Person": "3"}, "prefixes": [], "suffix": false}}, {"token": "לא", "offsets": {"start": 1098, "end": 1100}, "syntax": {"word": "לא", "dep_head_idx": 244, "dep_func": "advmod", "dep_head": "צ'"}, "seg": ["לא"], "lex": "לא", "morph": {"token": "לא", "pos": "ADV", "feats": {}, "prefixes": [], "suffix": false}}, {"token": "מייק", "offsets": {"start": 1101, "end": 1105}, "syntax": {"word": "מייק", "dep_head_idx": 168, "dep_func": "nsubj", "dep_head": "יש"}, "seg": ["מייק"], "lex": "מייק", "morph": {"token": "מייק", "pos": "PROPN", "feats": {}, "prefixes": [], "suffix": false}}, {"token": "צ'", "offsets": {"start": 1106, "end": 1108}, "syntax": {"word": "צ'", "dep_head_idx": 10, "dep_func": "parataxis", "dep_head": "שומר"}, "seg": ["צ'"], "lex": "וצ", "morph": {"token": "צ'", "pos": "X", "feats": {}, "prefixes": [], "suffix": false}}, {"token": "ק", "offsets": {"start": 1108, "end": 1109}, "syntax": {"word": "ק", "dep_head_idx": 42, "dep_func": "flat", "dep_head": "ג'"}, "seg": ["ק"], "lex": "ק", "morph": {"token": "ק", "pos": "PROPN", "feats": {}, "prefixes": [], "suffix": false}}, {"token": "וואן", "offsets": {"start": 1110, "end": 1114}, "syntax": {"word": "וואן", "dep_head_idx": 244, "dep_func": "flat", "dep_head": "צ'"}, "seg": ["וואן"], "lex": "וואן", "morph": {"token": "וואן", "pos": "X", "feats": {}, "prefixes": [], "suffix": false}}, {"token": "טו", "offsets": {"start": 1115, "end": 1117}, "syntax": {"word": "טו", "dep_head_idx": 42, "dep_func": "flat", "dep_head": "ג'"}, "seg": ["טו"], "lex": "טו", "morph": {"token": "טו", "pos": "X", "feats": {}, "prefixes": [], "suffix": false}}, {"token": "-", "offsets": {"start": 1118, "end": 1119}, "syntax": {"word": "-", "dep_head_idx": 247, "dep_func": "punct", "dep_head": "טו"}, "seg": ["-"], "lex": "-", "morph": {"token": "-", "pos": "PUNCT", "feats": {}, "prefixes": [], "suffix": false}}, {"token": "זה", "offsets": {"start": 1120, "end": 1122}, "syntax": {"word": "זה", "dep_head_idx": 42, "dep_func": "flat", "dep_head": "ג'"}, "seg": ["זה"], "lex": "זה", "morph": {"token": "זה", "pos": "PRON", "feats": {"Gender": "Masc", "Number": "Sing", "Person": "3"}, "prefixes": [], "suffix": false}}, {"token": "קוואנטום", "offsets": {"start": 1123, "end": 1131}, "syntax": {"word": "קוואנטום", "dep_head_idx": 274, "dep_func": "flat", "dep_head": "7"}, "seg": ["קוואנטום"], "lex": "[BLANK]", "morph": {"token": "קוואנטום", "pos": "PROPN", "feats": {}, "prefixes": [], "suffix": false}}, {"token": "פיזיקס", "offsets": {"start": 1132, "end": 1138}, "syntax": {"word": "פיזיקס", "dep_head_idx": 244, "dep_func": "flat", "dep_head": "צ'"}, "seg": ["פיזיקס"], "lex": "פיזיק", "morph": {"token": "פיזיקס", "pos": "PROPN", "feats": {}, "prefixes": [], "suffix": false}}, {"token": "ממריא", "offsets": {"start": 1139, "end": 1144}, "syntax": {"word": "ממריא", "dep_head_idx": 116, "dep_func": "advcl", "dep_head": "לשבור"}, "seg": ["ממריא"], "lex": "ממריא", "morph": {"token": "ממריא", "pos": "VERB", "feats": {"Gender": "Masc", "Number": "Sing", "Person": "3", "Tense": "Pres"}, "prefixes": [], "suffix": false}}, {"token": "מהמדבר", "offsets": {"start": 1145, "end": 1151}, "syntax": {"word": "מהמדבר", "dep_head_idx": 288, "dep_func": "obl", "dep_head": "לקבור"}, "seg": ["מה", "מדבר"], "lex": "מפרץ", "morph": {"token": "מהמדבר", "pos": "NOUN", "feats": {"Gender": "Masc", "Number": "Sing"}, "prefixes": ["DET", "ADP"], "suffix": false}}, {"token": "כמו", "offsets": {"start": 1152, "end": 1155}, "syntax": {"word": "כמו", "dep_head_idx": 255, "dep_func": "case", "dep_head": "פיניקס"}, "seg": ["כמו"], "lex": "כמו", "morph": {"token": "כמו", "pos": "ADP", "feats": {}, "prefixes": [], "suffix": false}}, {"token": "פיניקס", "offsets": {"start": 1156, "end": 1162}, "syntax": {"word": "פיניקס", "dep_head_idx": 51, "dep_func": "nmod", "dep_head": "המכה"}, "seg": ["פיניקס"], "lex": "פיניקס", "morph": {"token": "פיניקס", "pos": "PROPN", "feats": {}, "prefixes": [], "suffix": false}}, {"token": "אמרתי", "offsets": {"start": 1164, "end": 1169}, "syntax": {"word": "אמרתי", "dep_head_idx": 2, "dep_func": "parataxis", "dep_head": "אבן"}, "seg": ["אמרתי"], "lex": "אמר", "morph": {"token": "אמרתי", "pos": "VERB", "feats": {"Gender": "Masc", "Number": "Sing", "Person": "1", "Tense": "Past"}, "prefixes": [], "suffix": false}}, {"token": "לשקל", "offsets": {"start": 1170, "end": 1174}, "syntax": {"word": "לשקל", "dep_head_idx": 52, "dep_func": "obl", "dep_head": "שובר"}, "seg": ["ל", "שקל"], "lex": "שקל", "morph": {"token": "לשקל", "pos": "PROPN", "feats": {"Gender": "Masc", "Number": "Sing"}, "prefixes": ["DET", "ADP"], "suffix": false}}, {"token": "בתחילת", "offsets": {"start": 1175, "end": 1181}, "syntax": {"word": "בתחילת", "dep_head_idx": 256, "dep_func": "obl", "dep_head": "אמרתי"}, "seg": ["ב", "תחילת"], "lex": "תחילה", "morph": {"token": "בתחילת", "pos": "NOUN", "feats": {"Gender": "Fem", "Number": "Sing"}, "prefixes": ["ADP"], "suffix": false}}, {"token": "הדרך", "offsets": {"start": 1182, "end": 1186}, "syntax": {"word": "הדרך", "dep_head_idx": 258, "dep_func": "compound:smixut", "dep_head": "בתחילת"}, "seg": ["ה", "דרך"], "lex": "דרך", "morph": {"token": "הדרך", "pos": "NOUN", "feats": {"Gender": "Fem", "Number": "Sing"}, "prefixes": ["DET"], "suffix": false}}, {"token": ",", "offsets": {"start": 1186, "end": 1187}, "syntax": {"word": ",", "dep_head_idx": 261, "dep_func": "punct", "dep_head": "תקשיב"}, "seg": [","], "lex": ",", "morph": {"token": ",", "pos": "PUNCT", "feats": {}, "prefixes": [], "suffix": false}}, {"token": "תקשיב", "offsets": {"start": 1188, "end": 1193}, "syntax": {"word": "תקשיב", "dep_head_idx": 52, "dep_func": "parataxis", "dep_head": "שובר"}, "seg": ["תקשיב"], "lex": "הקשיב", "morph": {"token": "תקשיב", "pos": "VERB", "feats": {"Gender": "Masc", "Number": "Sing", "Person": "2", "Tense": "Fut"}, "prefixes": [], "suffix": false}}, {"token": "לי", "offsets": {"start": 1194, "end": 1196}, "syntax": {"word": "לי", "dep_head_idx": 261, "dep_func": "obl", "dep_head": "תקשיב"}, "seg": ["לי"], "lex": "לי", "morph": {"token": "לי", "pos": "PRON", "feats": {"Gender": "Masc", "Number": "Sing", "Person": "1"}, "prefixes": ["ADP"], "suffix": false}}, {"token": "ג'", "offsets": {"start": 1197, "end": 1199}, "syntax": {"word": "ג'", "dep_head_idx": 52, "dep_func": "obj", "dep_head": "שובר"}, "seg": ["ג'"], "lex": "[BLANK]", "morph": {"token": "ג'", "pos": "NUM", "feats": {"Gender": "Masc"}, "prefixes": [], "suffix": false}}, {"token": "ונאם", "offsets": {"start": 1199, "end": 1203}, "syntax": {"word": "ונאם", "dep_head_idx": 256, "dep_func": "conj", "dep_head": "אמרתי"}, "seg": ["ו", "נאם"], "lex": "[BLANK]", "morph": {"token": "ונאם", "pos": "VERB", "feats": {"Gender": "Masc", "Number": "Plur", "Person": "1", "Tense": "Fut"}, "prefixes": ["CCONJ"], "suffix": false}}, {"token": "נשחק", "offsets": {"start": 1204, "end": 1208}, "syntax": {"word": "נשחק", "dep_head_idx": 138, "dep_func": "conj", "dep_head": "לשבור"}, "seg": ["נשחק"], "lex": "שיחק", "morph": {"token": "נשחק", "pos": "VERB", "feats": {"Gender": "Masc", "Number": "Plur", "Person": "1", "Tense": "Fut"}, "prefixes": [], "suffix": false}}, {"token": "את", "offsets": {"start": 1209, "end": 1211}, "syntax": {"word": "את", "dep_head_idx": 267, "dep_func": "case:acc", "dep_head": "הקלפים"}, "seg": ["את"], "lex": "את", "morph": {"token": "את", "pos": "ADP", "feats": {}, "prefixes": [], "suffix": false}}, {"token": "הקלפים", "offsets": {"start": 1212, "end": 1218}, "syntax": {"word": "הקלפים", "dep_head_idx": 168, "dep_func": "obj", "dep_head": "יש"}, "seg": ["ה", "קלפים"], "lex": "קלף", "morph": {"token": "הקלפים", "pos": "NOUN", "feats": {"Gender": "Masc", "Number": "Plur"}, "prefixes": ["DET"], "suffix": false}}, {"token": "נכון", "offsets": {"start": 1219, "end": 1223}, "syntax": {"word": "נכון", "dep_head_idx": 52, "dep_func": "discourse", "dep_head": "שובר"}, "seg": ["נכון"], "lex": "נכון", "morph": {"token": "נכון", "pos": "ADJ", "feats": {"Gender": "Masc", "Number": "Sing"}, "prefixes": [], "suffix": false}}, {"token": ",", "offsets": {"start": 1223, "end": 1224}, "syntax": {"word": ",", "dep_head_idx": 168, "dep_func": "punct", "dep_head": "יש"}, "seg": [","], "lex": ",", "morph": {"token": ",", "pos": "PUNCT", "feats": {}, "prefixes": [], "suffix": false}}, {"token": "נצא", "offsets": {"start": 1225, "end": 1228}, "syntax": {"word": "נצא", "dep_head_idx": 265, "dep_func": "conj", "dep_head": "נשחק"}, "seg": ["נצא"], "lex": "יצא", "morph": {"token": "נצא", "pos": "VERB", "feats": {"Gender": "Masc", "Number": "Plur", "Person": "1", "Tense": "Fut"}, "prefixes": [], "suffix": false}}, {"token": "כל", "offsets": {"start": 1229, "end": 1231}, "syntax": {"word": "כל", "dep_head_idx": 272, "dep_func": "det", "dep_head": "אחד"}, "seg": ["כל"], "lex": "כל", "morph": {"token": "כל", "pos": "DET", "feats": {}, "prefixes": [], "suffix": false}}, {"token": "אחד", "offsets": {"start": 1232, "end": 1235}, "syntax": {"word": "אחד", "dep_head_idx": 270, "dep_func": "nsubj", "dep_head": "נצא"}, "seg": ["אחד"], "lex": "אחד", "morph": {"token": "אחד", "pos": "NUM", "feats": {"Gender": "Masc", "Number": "Sing"}, "prefixes": [], "suffix": false}}, {"token": "עם", "offsets": {"start": 1236, "end": 1238}, "syntax": {"word": "עם", "dep_head_idx": 274, "dep_func": "case", "dep_head": "7"}, "seg": ["עם"], "lex": "עם", "morph": {"token": "עם", "pos": "ADP", "feats": {}, "prefixes": [], "suffix": false}}, {"token": "7", "offsets": {"start": 1239, "end": 1240}, "syntax": {"word": "7", "dep_head_idx": 272, "dep_func": "obl", "dep_head": "אחד"}, "seg": ["7"], "lex": "7", "morph": {"token": "7", "pos": "NUM", "feats": {}, "prefixes": [], "suffix": false}}, {"token": "דונאם", "offsets": {"start": 1241, "end": 1246}, "syntax": {"word": "דונאם", "dep_head_idx": 274, "dep_func": "flat", "dep_head": "7"}, "seg": ["דונאם"], "lex": "דונ", "morph": {"token": "דונאם", "pos": "PROPN", "feats": {}, "prefixes": [], "suffix": false}}, {"token": "טונה", "offsets": {"start": 1247, "end": 1251}, "syntax": {"word": "טונה", "dep_head_idx": 42, "dep_func": "flat", "dep_head": "ג'"}, "seg": ["טונה"], "lex": "טונה", "morph": {"token": "טונה", "pos": "PROPN", "feats": {}, "prefixes": [], "suffix": false}}, {"token": ",", "offsets": {"start": 1251, "end": 1252}, "syntax": {"word": ",", "dep_head_idx": 278, "dep_func": "punct", "dep_head": "ניתן"}, "seg": [","], "lex": ",", "morph": {"token": ",", "pos": "PUNCT", "feats": {}, "prefixes": [], "suffix": false}}, {"token": "ניתן", "offsets": {"start": 1253, "end": 1257}, "syntax": {"word": "ניתן", "dep_head_idx": 256, "dep_func": "conj", "dep_head": "אמרתי"}, "seg": ["ניתן"], "lex": "נתן", "morph": {"token": "ניתן", "pos": "VERB", "feats": {"Gender": "Masc", "Number": "Plur", "Person": "2", "Tense": "Fut"}, "prefixes": [], "suffix": false}}, {"token": "להם", "offsets": {"start": 1258, "end": 1261}, "syntax": {"word": "להם", "dep_head_idx": 132, "dep_func": "obl", "dep_head": "חרוט"}, "seg": ["להם"], "lex": "לו", "morph": {"token": "להם", "pos": "PRON", "feats": {"Gender": "Masc", "Number": "Plur", "Person": "3"}, "prefixes": ["ADP"], "suffix": false}}, {"token": "מיליון", "offsets": {"start": 1262, "end": 1268}, "syntax": {"word": "מיליון", "dep_head_idx": 281, "dep_func": "nummod", "dep_head": "סיבות"}, "seg": ["מיליון"], "lex": "מיליון", "morph": {"token": "מיליון", "pos": "NUM", "feats": {"Gender": "Masc", "Number": "Sing"}, "prefixes": [], "suffix": false}}, {"token": "סיבות", "offsets": {"start": 1269, "end": 1274}, "syntax": {"word": "סיבות", "dep_head_idx": 47, "dep_func": "obj", "dep_head": "וקבל"}, "seg": ["סיבות"], "lex": "סיבה", "morph": {"token": "סיבות", "pos": "NOUN", "feats": {"Gender": "Fem", "Number": "Plur"}, "prefixes": [], "suffix": false}}, {"token": "לחפור", "offsets": {"start": 1275, "end": 1280}, "syntax": {"word": "לחפור", "dep_head_idx": 143, "dep_func": "xcomp", "dep_head": "תן"}, "seg": ["לחפור"], "lex": "שחפר", "morph": {"token": "לחפור", "pos": "VERB", "feats": {}, "prefixes": [], "suffix": false}}, {"token": "שיהיה", "offsets": {"start": 1281, "end": 1286}, "syntax": {"word": "שיהיה", "dep_head_idx": 161, "dep_func": "cop", "dep_head": "זרים"}, "seg": ["ש", "יהיה"], "lex": "היי", "morph": {"token": "שיהיה", "pos": "AUX", "feats": {"Gender": "Masc", "Number": "Sing", "Person": "3", "Tense": "Fut"}, "prefixes": ["SCONJ"], "suffix": false}}, {"token": "מי", "offsets": {"start": 1287, "end": 1289}, "syntax": {"word": "מי", "dep_head_idx": 168, "dep_func": "nsubj", "dep_head": "יש"}, "seg": ["מי"], "lex": "מי", "morph": {"token": "מי", "pos": "PRON", "feats": {}, "prefixes": [], "suffix": false}}, {"token": "להמליך", "offsets": {"start": 1290, "end": 1296}, "syntax": {"word": "להמליך", "dep_head_idx": 2, "dep_func": "acl", "dep_head": "אבן"}, "seg": ["להמליך"], "lex": "[BLANK]", "morph": {"token": "להמליך", "pos": "VERB", "feats": {}, "prefixes": [], "suffix": false}}, {"token": "את", "offsets": {"start": 1297, "end": 1299}, "syntax": {"word": "את", "dep_head_idx": 287, "dep_func": "case:acc", "dep_head": "מי"}, "seg": ["את"], "lex": "את", "morph": {"token": "את", "pos": "ADP", "feats": {}, "prefixes": [], "suffix": false}}, {"token": "מי", "offsets": {"start": 1300, "end": 1302}, "syntax": {"word": "מי", "dep_head_idx": 288, "dep_func": "obj", "dep_head": "לקבור"}, "seg": ["מי"], "lex": "מים", "morph": {"token": "מי", "pos": "PRON", "feats": {}, "prefixes": [], "suffix": false}}, {"token": "לקבור", "offsets": {"start": 1303, "end": 1308}, "syntax": {"word": "לקבור", "dep_head_idx": 2, "dep_func": "acl", "dep_head": "אבן"}, "seg": ["לקבור"], "lex": "קברו", "morph": {"token": "לקבור", "pos": "VERB", "feats": {}, "prefixes": [], "suffix": false}}], "root_idx": 2, "ner_entities": [{"phrase": "המלט", "label": "WOA", "start": 134, "end": 138, "token_start": 28, "token_end": 28}, {"phrase": "ג'", "label": "DUC", "start": 197, "end": 199, "token_start": 42, "token_end": 42}, {"phrase": "פרינס", "label": "PER", "start": 263, "end": 268, "token_start": 57, "token_end": 57}, {"phrase": "טרי", "label": "PER", "start": 402, "end": 405, "token_start": 85, "token_end": 85}, {"phrase": "להיפ", "label": "MISC", "start": 500, "end": 504, "token_start": 108, "token_end": 108}, {"phrase": "פינצ ' רת", "label": "PER", "start": 862, "end": 870, "token_start": 184, "token_end": 186}, {"phrase": "מאש גאן", "label": "PER", "start": 935, "end": 944, "token_start": 201, "token_end": 202}, {"phrase": "ניר דנן", "label": "PER", "start": 993, "end": 1000, "token_start": 216, "token_end": 217}, {"phrase": "סטריט", "label": "PER", "start": 1002, "end": 1007, "token_start": 219, "token_end": 219}, {"phrase": "שאנן", "label": "PER", "start": 1012, "end": 1016, "token_start": 221, "token_end": 221}, {"phrase": "לירי", "label": "PER", "start": 1046, "end": 1052, "token_start": 229, "token_end": 229}, {"phrase": "קווא", "label": "DUC", "start": 1123, "end": 1131, "token_start": 250, "token_end": 250}, {"phrase": "פיניקס", "label": "GPE", "start": 1156, "end": 1162, "token_start": 255, "token_end": 255}, {"phrase": "לשקל", "label": "MISC", "start": 1170, "end": 1174, "token_start": 257, "token_end": 257}, {"phrase": "7", "label": "DUC", "start": 1239, "end": 1240, "token_start": 274, "token_end": 274}]}
